Workbook

Sheet Exchange Rate
A1: KEN JP ANIME FIGURES SHOP — EXCHANGE RATE REGISTRY
A4: PHP → JPY BASE RATE | D4: JPY → PHP BASE RATE
A5: 1 PHP equals (JPY): | B5: 2.7 | D5: 1 JPY equals (PHP): | E5: 0.37
A6: ▸ Used in Col G: Selling Price (JPY) = Col F × this rate | D6: ▸ Used in Col E: Purchase Price (PHP) = Col D × this rate
A8: ⚠️ HOW TO USE THIS SHEET — READ CAREFULLY
A9: ▸ Edit ONLY the yellow cells: B5 (PHP→JPY) and E5 (JPY→PHP).
A10: ▸ All 8 tracking sheets reference these cells directly via formula.
A11: ▸ Changing a rate here instantly recalculates every currency conversion in the workbook.
A12: ▸ Do NOT rename this sheet — it is referenced by the exact name 'Exchange Rate'.
A13: ▸ Do NOT move B5 or E5 — all inventory formulas point to these locked absolute addresses.

Sheet 1. Anime Figures
A1: KEN JP ANIME FIGURES SHOP
A4: 📦 1. ANIME FIGURES | Rates: 'Exchange Rate'!B5 (PHP→JPY) & E5 (JPY→PHP)
A5: 🔍 FUZZY SEARCH | B5: ⬇ type partial name or ID: | D5: =IF($C$5="","← type above",IFERROR(ROWS(filter($M$8:$M$107,ISNUMBER(SEARCH($C$5,$M$8:$M$107))))&" match(es) found","❌ 0 found")) -> ← type above | E5: View match #: | F5: 1 | G5: =IF($C$5="","— no active search —",IFERROR(INDEX(filter($M$8:$M$107,ISNUMBER(SEARCH($C$5,$M$8:$M$107)),"❌ No Data Found"),VALUE($F$5)),"❌ No Data Found")) -> — no active search — | H5: =IFERROR(IF($G$5="❌ No Data Found","—",IF($G$5="— no active search —","—",INDEX($D$8:$D$107,MATCH($G$5,$M$8:$M$107,0)))),"—") -> — | I5: =IFERROR(IF($G$5="❌ No Data Found","—",IF($G$5="— no active search —","—",INDEX($F$8:$F$107,MATCH($G$5,$M$8:$M$107,0)))),"—") -> — | J5: =IFERROR(IF($G$5="❌ No Data Found","—",IF($G$5="— no active search —","—",INDEX($H$8:$H$107,MATCH($G$5,$M$8:$M$107,0)))),"—") -> — | K5: =IFERROR(IF($G$5="❌ No Data Found","—",IF($G$5="— no active search —","—",INDEX($J$8:$J$107,MATCH($G$5,$M$8:$M$107,0)))),"—") -> — | L5: =IFERROR(IF($G$5="❌ No Data Found","—",IF($G$5="— no active search —","—",INDEX($L$8:$L$107,MATCH($G$5,$M$8:$M$107,0)))),"—") -> —
A7: Product ID | B7: Date of Entry | C7: Transaction Month | D7: Purchase Price (JPY) | E7: Purchase Price (PHP) | F7: Selling Price (PHP) | G7: Selling Price (JPY) | H7: Net Profit (JPY) | I7: Net Profit (PHP) | J7: Net Loss (JPY) | K7: Net Loss (PHP) | L7: Stock Status | M7: SEARCH_KEY (hidden)
C8: =IF(B8="","",TEXT(B8,"mmmm")) | E8: =IF(D8="","",D8*'Exchange Rate'!$E$5) | G8: =IF(F8="","",F8*'Exchange Rate'!$B$5) | H8: =IF(L8="Inactive",0,IF(ISNUMBER(G8)*ISNUMBER(D8),IF(G8>D8,G8-D8,0),0)) -> 0 | I8: =IF(L8="Inactive",0,IF(ISNUMBER(F8)*ISNUMBER(E8),IF(F8>E8,F8-E8,0),0)) -> 0 | J8: =IF(L8="Inactive",0,IF(ISNUMBER(D8)*ISNUMBER(G8),IF(D8>G8,D8-G8,0),0)) -> 0 | K8: =IF(L8="Inactive",0,IF(ISNUMBER(E8)*ISNUMBER(F8),IF(E8>F8,E8-F8,0),0)) -> 0 | L8: Active | M8: =IF(A8="","—",A8&" ("&TEXT(B8,"MM/DD/YYYY")&")") -> —
C9: =IF(B9="","",TEXT(B9,"mmmm")) | E9: =IF(D9="","",D9*'Exchange Rate'!$E$5) | G9: =IF(F9="","",F9*'Exchange Rate'!$B$5) | H9: =IF(L9="Inactive",0,IF(ISNUMBER(G9)*ISNUMBER(D9),IF(G9>D9,G9-D9,0),0)) -> 0 | I9: =IF(L9="Inactive",0,IF(ISNUMBER(F9)*ISNUMBER(E9),IF(F9>E9,F9-E9,0),0)) -> 0 | J9: =IF(L9="Inactive",0,IF(ISNUMBER(D9)*ISNUMBER(G9),IF(D9>G9,D9-G9,0),0)) -> 0 | K9: =IF(L9="Inactive",0,IF(ISNUMBER(E9)*ISNUMBER(F9),IF(E9>F9,E9-F9,0),0)) -> 0 | L9: Active | M9: =IF(A9="","—",A9&" ("&TEXT(B9,"MM/DD/YYYY")&")") -> —
C10: =IF(B10="","",TEXT(B10,"mmmm")) | E10: =IF(D10="","",D10*'Exchange Rate'!$E$5) | G10: =IF(F10="","",F10*'Exchange Rate'!$B$5) | H10: =IF(L10="Inactive",0,IF(ISNUMBER(G10)*ISNUMBER(D10),IF(G10>D10,G10-D10,0),0)) -> 0 | I10: =IF(L10="Inactive",0,IF(ISNUMBER(F10)*ISNUMBER(E10),IF(F10>E10,F10-E10,0),0)) -> 0 | J10: =IF(L10="Inactive",0,IF(ISNUMBER(D10)*ISNUMBER(G10),IF(D10>G10,D10-G10,0),0)) -> 0 | K10: =IF(L10="Inactive",0,IF(ISNUMBER(E10)*ISNUMBER(F10),IF(E10>F10,E10-F10,0),0)) -> 0 | L10: Active | M10: =IF(A10="","—",A10&" ("&TEXT(B10,"MM/DD/YYYY")&")") -> —
C11: =IF(B11="","",TEXT(B11,"mmmm")) | E11: =IF(D11="","",D11*'Exchange Rate'!$E$5) | G11: =IF(F11="","",F11*'Exchange Rate'!$B$5) | H11: =IF(L11="Inactive",0,IF(ISNUMBER(G11)*ISNUMBER(D11),IF(G11>D11,G11-D11,0),0)) -> 0 | I11: =IF(L11="Inactive",0,IF(ISNUMBER(F11)*ISNUMBER(E11),IF(F11>E11,F11-E11,0),0)) -> 0 | J11: =IF(L11="Inactive",0,IF(ISNUMBER(D11)*ISNUMBER(G11),IF(D11>G11,D11-G11,0),0)) -> 0 | K11: =IF(L11="Inactive",0,IF(ISNUMBER(E11)*ISNUMBER(F11),IF(E11>F11,E11-F11,0),0)) -> 0 | L11: Active | M11: =IF(A11="","—",A11&" ("&TEXT(B11,"MM/DD/YYYY")&")") -> —
C12: =IF(B12="","",TEXT(B12,"mmmm")) | E12: =IF(D12="","",D12*'Exchange Rate'!$E$5) | G12: =IF(F12="","",F12*'Exchange Rate'!$B$5) | H12: =IF(L12="Inactive",0,IF(ISNUMBER(G12)*ISNUMBER(D12),IF(G12>D12,G12-D12,0),0)) -> 0 | I12: =IF(L12="Inactive",0,IF(ISNUMBER(F12)*ISNUMBER(E12),IF(F12>E12,F12-E12,0),0)) -> 0 | J12: =IF(L12="Inactive",0,IF(ISNUMBER(D12)*ISNUMBER(G12),IF(D12>G12,D12-G12,0),0)) -> 0 | K12: =IF(L12="Inactive",0,IF(ISNUMBER(E12)*ISNUMBER(F12),IF(E12>F12,E12-F12,0),0)) -> 0 | L12: Active | M12: =IF(A12="","—",A12&" ("&TEXT(B12,"MM/DD/YYYY")&")") -> —
C13: =IF(B13="","",TEXT(B13,"mmmm")) | E13: =IF(D13="","",D13*'Exchange Rate'!$E$5) | G13: =IF(F13="","",F13*'Exchange Rate'!$B$5) | H13: =IF(L13="Inactive",0,IF(ISNUMBER(G13)*ISNUMBER(D13),IF(G13>D13,G13-D13,0),0)) -> 0 | I13: =IF(L13="Inactive",0,IF(ISNUMBER(F13)*ISNUMBER(E13),IF(F13>E13,F13-E13,0),0)) -> 0 | J13: =IF(L13="Inactive",0,IF(ISNUMBER(D13)*ISNUMBER(G13),IF(D13>G13,D13-G13,0),0)) -> 0 | K13: =IF(L13="Inactive",0,IF(ISNUMBER(E13)*ISNUMBER(F13),IF(E13>F13,E13-F13,0),0)) -> 0 | L13: Active | M13: =IF(A13="","—",A13&" ("&TEXT(B13,"MM/DD/YYYY")&")") -> —
C14: =IF(B14="","",TEXT(B14,"mmmm")) | E14: =IF(D14="","",D14*'Exchange Rate'!$E$5) | G14: =IF(F14="","",F14*'Exchange Rate'!$B$5) | H14: =IF(L14="Inactive",0,IF(ISNUMBER(G14)*ISNUMBER(D14),IF(G14>D14,G14-D14,0),0)) -> 0 | I14: =IF(L14="Inactive",0,IF(ISNUMBER(F14)*ISNUMBER(E14),IF(F14>E14,F14-E14,0),0)) -> 0 | J14: =IF(L14="Inactive",0,IF(ISNUMBER(D14)*ISNUMBER(G14),IF(D14>G14,D14-G14,0),0)) -> 0 | K14: =IF(L14="Inactive",0,IF(ISNUMBER(E14)*ISNUMBER(F14),IF(E14>F14,E14-F14,0),0)) -> 0 | L14: Active | M14: =IF(A14="","—",A14&" ("&TEXT(B14,"MM/DD/YYYY")&")") -> —
C15: =IF(B15="","",TEXT(B15,"mmmm")) | E15: =IF(D15="","",D15*'Exchange Rate'!$E$5) | G15: =IF(F15="","",F15*'Exchange Rate'!$B$5) | H15: =IF(L15="Inactive",0,IF(ISNUMBER(G15)*ISNUMBER(D15),IF(G15>D15,G15-D15,0),0)) -> 0 | I15: =IF(L15="Inactive",0,IF(ISNUMBER(F15)*ISNUMBER(E15),IF(F15>E15,F15-E15,0),0)) -> 0 | J15: =IF(L15="Inactive",0,IF(ISNUMBER(D15)*ISNUMBER(G15),IF(D15>G15,D15-G15,0),0)) -> 0 | K15: =IF(L15="Inactive",0,IF(ISNUMBER(E15)*ISNUMBER(F15),IF(E15>F15,E15-F15,0),0)) -> 0 | L15: Active | M15: =IF(A15="","—",A15&" ("&TEXT(B15,"MM/DD/YYYY")&")") -> —
C16: =IF(B16="","",TEXT(B16,"mmmm")) | E16: =IF(D16="","",D16*'Exchange Rate'!$E$5) | G16: =IF(F16="","",F16*'Exchange Rate'!$B$5) | H16: =IF(L16="Inactive",0,IF(ISNUMBER(G16)*ISNUMBER(D16),IF(G16>D16,G16-D16,0),0)) -> 0 | I16: =IF(L16="Inactive",0,IF(ISNUMBER(F16)*ISNUMBER(E16),IF(F16>E16,F16-E16,0),0)) -> 0 | J16: =IF(L16="Inactive",0,IF(ISNUMBER(D16)*ISNUMBER(G16),IF(D16>G16,D16-G16,0),0)) -> 0 | K16: =IF(L16="Inactive",0,IF(ISNUMBER(E16)*ISNUMBER(F16),IF(E16>F16,E16-F16,0),0)) -> 0 | L16: Active | M16: =IF(A16="","—",A16&" ("&TEXT(B16,"MM/DD/YYYY")&")") -> —
C17: =IF(B17="","",TEXT(B17,"mmmm")) | E17: =IF(D17="","",D17*'Exchange Rate'!$E$5) | G17: =IF(F17="","",F17*'Exchange Rate'!$B$5) | H17: =IF(L17="Inactive",0,IF(ISNUMBER(G17)*ISNUMBER(D17),IF(G17>D17,G17-D17,0),0)) -> 0 | I17: =IF(L17="Inactive",0,IF(ISNUMBER(F17)*ISNUMBER(E17),IF(F17>E17,F17-E17,0),0)) -> 0 | J17: =IF(L17="Inactive",0,IF(ISNUMBER(D17)*ISNUMBER(G17),IF(D17>G17,D17-G17,0),0)) -> 0 | K17: =IF(L17="Inactive",0,IF(ISNUMBER(E17)*ISNUMBER(F17),IF(E17>F17,E17-F17,0),0)) -> 0 | L17: Active | M17: =IF(A17="","—",A17&" ("&TEXT(B17,"MM/DD/YYYY")&")") -> —
C18: =IF(B18="","",TEXT(B18,"mmmm")) | E18: =IF(D18="","",D18*'Exchange Rate'!$E$5) | G18: =IF(F18="","",F18*'Exchange Rate'!$B$5) | H18: =IF(L18="Inactive",0,IF(ISNUMBER(G18)*ISNUMBER(D18),IF(G18>D18,G18-D18,0),0)) -> 0 | I18: =IF(L18="Inactive",0,IF(ISNUMBER(F18)*ISNUMBER(E18),IF(F18>E18,F18-E18,0),0)) -> 0 | J18: =IF(L18="Inactive",0,IF(ISNUMBER(D18)*ISNUMBER(G18),IF(D18>G18,D18-G18,0),0)) -> 0 | K18: =IF(L18="Inactive",0,IF(ISNUMBER(E18)*ISNUMBER(F18),IF(E18>F18,E18-F18,0),0)) -> 0 | L18: Active | M18: =IF(A18="","—",A18&" ("&TEXT(B18,"MM/DD/YYYY")&")") -> —
C19: =IF(B19="","",TEXT(B19,"mmmm")) | E19: =IF(D19="","",D19*'Exchange Rate'!$E$5) | G19: =IF(F19="","",F19*'Exchange Rate'!$B$5) | H19: =IF(L19="Inactive",0,IF(ISNUMBER(G19)*ISNUMBER(D19),IF(G19>D19,G19-D19,0),0)) -> 0 | I19: =IF(L19="Inactive",0,IF(ISNUMBER(F19)*ISNUMBER(E19),IF(F19>E19,F19-E19,0),0)) -> 0 | J19: =IF(L19="Inactive",0,IF(ISNUMBER(D19)*ISNUMBER(G19),IF(D19>G19,D19-G19,0),0)) -> 0 | K19: =IF(L19="Inactive",0,IF(ISNUMBER(E19)*ISNUMBER(F19),IF(E19>F19,E19-F19,0),0)) -> 0 | L19: Active | M19: =IF(A19="","—",A19&" ("&TEXT(B19,"MM/DD/YYYY")&")") -> —
... C107: =IF(B107="","",TEXT(B107,"mmmm")) | E107: =IF(D107="","",D107*'Exchange Rate'!$E$5) | G107: =IF(F107="","",F107*'Exchange Rate'!$B$5) | H107: =IF(L107="Inactive",0,IF(ISNUMBER(G107)*ISNUMBER(D107),IF(G107>D107,G107-D107,0),0)) -> 0 | I107: =IF(L107="Inactive",0,IF(ISNUMBER(F107)*ISNUMBER(E107),IF(F107>E107,F107-E107,0),0)) -> 0 | J107: =IF(L107="Inactive",0,IF(ISNUMBER(D107)*ISNUMBER(G107),IF(D107>G107,D107-G107,0),0)) -> 0 | K107: =IF(L107="Inactive",0,IF(ISNUMBER(E107)*ISNUMBER(F107),IF(E107>F107,E107-F107,0),0)) -> 0 | L107: Active | M107: =IF(A107="","—",A107&" ("&TEXT(B107,"MM/DD/YYYY")&")") -> —
A108: TOTAL CATEGORY VALUE | D108: =SUM(D8:D107) -> 0 | E108: =SUM(E8:E107) -> 0 | F108: =SUM(F8:F107) -> 0 | G108: =SUM(G8:G107) -> 0 | H108: =SUM(H8:H107) -> 0 | I108: =SUM(I8:I107) -> 0 | J108: =SUM(J8:J107) -> 0 | K108: =SUM(K8:K107) -> 0 | L108: =SUM(L8:L107) -> 0
A110: 📋 USER GUIDE & OPERATIONAL INSTRUCTIONS
A111: Step 1 — DATA ENTRY
A112: Input rows sequentially. Type directly into Col D (Purchase JPY) and Col F (Selling PHP) ONLY. All other columns auto-calculate. Yellow cells = manual entry. White cells = formulas.
A113: Step 2 — DUPLICATE IDs
A114: If tracking duplicate items, check the QUICK-VIEW bar (Row 5). A ⚠️ alert fires when the same Product ID appears more than once. Use the 'Date of Entry' (Col B) timestamp in the lookup to immediately distinguish which entry is which.
A115: Step 3 — ANALYTICS FILTER
A116: Toggle the Analytics view on the '9. Overall Analytics' sheet using the timeframe filter (D2) to review Weekly, Monthly, or Annual financial health variations.
A117: Step 4 — EXCHANGE RATES
A118: Never manually edit currency columns. To update rates, go to the 'Exchange Rate' sheet and edit ONLY cells B5 (PHP→JPY) or E5 (JPY→PHP). All values across the workbook update instantly.
A119: Step 5 — STOCK STATUS
A120: Use Column L dropdown (Active/Inactive) to toggle items. Inactive rows contribute ZERO to profit, loss, and analytics totals — ideal for recalled, damaged, or discontinued stock.

Sheet 2. Mercari and Online store
A1: KEN JP ANIME FIGURES SHOP
A4: 📦 2. MERCARI AND ONLINE STORE | Rates: 'Exchange Rate'!B5 (PHP→JPY) & E5 (JPY→PHP)
A5: 🔍 FUZZY SEARCH | B5: ⬇ type partial name or ID: | D5: =IF($C$5="","← type above",IFERROR(ROWS(filter($O$8:$O$107,ISNUMBER(SEARCH($C$5,$O$8:$O$107))))&" match(es) found","❌ 0 found")) -> ← type above | E5: View match #: | F5: 1 | G5: =IF($C$5="","— no active search —",IFERROR(INDEX(filter($O$8:$O$107,ISNUMBER(SEARCH($C$5,$O$8:$O$107)),"❌ No Data Found"),VALUE($F$5)),"❌ No Data Found")) -> — no active search — | H5: =IFERROR(IF($G$5="❌ No Data Found","—",IF($G$5="— no active search —","—",INDEX($D$8:$D$107,MATCH($G$5,$O$8:$O$107,0)))),"—") -> — | I5: =IFERROR(IF($G$5="❌ No Data Found","—",IF($G$5="— no active search —","—",INDEX($F$8:$F$107,MATCH($G$5,$O$8:$O$107,0)))),"—") -> — | J5: =IFERROR(IF($G$5="❌ No Data Found","—",IF($G$5="— no active search —","—",INDEX($H$8:$H$107,MATCH($G$5,$O$8:$O$107,0)))),"—") -> — | K5: =IFERROR(IF($G$5="❌ No Data Found","—",IF($G$5="— no active search —","—",INDEX($J$8:$J$107,MATCH($G$5,$O$8:$O$107,0)))),"—") -> — | L5: =IFERROR(IF($G$5="❌ No Data Found","—",IF($G$5="— no active search —","—",INDEX($L$8:$L$107,MATCH($G$5,$O$8:$O$107,0)))),"—") -> —
A7: Product ID | B7: Date of Entry | C7: Transaction Month | D7: Purchase Price (JPY) | E7: Purchase Price (PHP) | F7: Selling Price (PHP) | G7: Selling Price (JPY) | H7: Net Profit (JPY) | I7: Net Profit (PHP) | J7: Net Loss (JPY) | K7: Net Loss (PHP) | L7: Stock Status | M7: Customer Name | N7: Purchase Link | O7: SEARCH_KEY (hidden)
C8: =IF(B8="","",TEXT(B8,"mmmm")) | E8: =IF(D8="","",D8*'Exchange Rate'!$E$5) | G8: =IF(F8="","",F8*'Exchange Rate'!$B$5) | H8: =IF(L8="Inactive",0,IF(ISNUMBER(G8)*ISNUMBER(D8),IF(G8>D8,G8-D8,0),0)) -> 0 | I8: =IF(L8="Inactive",0,IF(ISNUMBER(F8)*ISNUMBER(E8),IF(F8>E8,F8-E8,0),0)) -> 0 | J8: =IF(L8="Inactive",0,IF(ISNUMBER(D8)*ISNUMBER(G8),IF(D8>G8,D8-G8,0),0)) -> 0 | K8: =IF(L8="Inactive",0,IF(ISNUMBER(E8)*ISNUMBER(F8),IF(E8>F8,E8-F8,0),0)) -> 0 | L8: Active | O8: =IF(A8="","—",A8&" ("&TEXT(B8,"MM/DD/YYYY")&")") -> —
C9: =IF(B9="","",TEXT(B9,"mmmm")) | E9: =IF(D9="","",D9*'Exchange Rate'!$E$5) | G9: =IF(F9="","",F9*'Exchange Rate'!$B$5) | H9: =IF(L9="Inactive",0,IF(ISNUMBER(G9)*ISNUMBER(D9),IF(G9>D9,G9-D9,0),0)) -> 0 | I9: =IF(L9="Inactive",0,IF(ISNUMBER(F9)*ISNUMBER(E9),IF(F9>E9,F9-E9,0),0)) -> 0 | J9: =IF(L9="Inactive",0,IF(ISNUMBER(D9)*ISNUMBER(G9),IF(D9>G9,D9-G9,0),0)) -> 0 | K9: =IF(L9="Inactive",0,IF(ISNUMBER(E9)*ISNUMBER(F9),IF(E9>F9,E9-F9,0),0)) -> 0 | L9: Active | O9: =IF(A9="","—",A9&" ("&TEXT(B9,"MM/DD/YYYY")&")") -> —
C10: =IF(B10="","",TEXT(B10,"mmmm")) | E10: =IF(D10="","",D10*'Exchange Rate'!$E$5) | G10: =IF(F10="","",F10*'Exchange Rate'!$B$5) | H10: =IF(L10="Inactive",0,IF(ISNUMBER(G10)*ISNUMBER(D10),IF(G10>D10,G10-D10,0),0)) -> 0 | I10: =IF(L10="Inactive",0,IF(ISNUMBER(F10)*ISNUMBER(E10),IF(F10>E10,F10-E10,0),0)) -> 0 | J10: =IF(L10="Inactive",0,IF(ISNUMBER(D10)*ISNUMBER(G10),IF(D10>G10,D10-G10,0),0)) -> 0 | K10: =IF(L10="Inactive",0,IF(ISNUMBER(E10)*ISNUMBER(F10),IF(E10>F10,E10-F10,0),0)) -> 0 | L10: Active | O10: =IF(A10="","—",A10&" ("&TEXT(B10,"MM/DD/YYYY")&")") -> —
C11: =IF(B11="","",TEXT(B11,"mmmm")) | E11: =IF(D11="","",D11*'Exchange Rate'!$E$5) | G11: =IF(F11="","",F11*'Exchange Rate'!$B$5) | H11: =IF(L11="Inactive",0,IF(ISNUMBER(G11)*ISNUMBER(D11),IF(G11>D11,G11-D11,0),0)) -> 0 | I11: =IF(L11="Inactive",0,IF(ISNUMBER(F11)*ISNUMBER(E11),IF(F11>E11,F11-E11,0),0)) -> 0 | J11: =IF(L11="Inactive",0,IF(ISNUMBER(D11)*ISNUMBER(G11),IF(D11>G11,D11-G11,0),0)) -> 0 | K11: =IF(L11="Inactive",0,IF(ISNUMBER(E11)*ISNUMBER(F11),IF(E11>F11,E11-F11,0),0)) -> 0 | L11: Active | O11: =IF(A11="","—",A11&" ("&TEXT(B11,"MM/DD/YYYY")&")") -> —
C12: =IF(B12="","",TEXT(B12,"mmmm")) | E12: =IF(D12="","",D12*'Exchange Rate'!$E$5) | G12: =IF(F12="","",F12*'Exchange Rate'!$B$5) | H12: =IF(L12="Inactive",0,IF(ISNUMBER(G12)*ISNUMBER(D12),IF(G12>D12,G12-D12,0),0)) -> 0 | I12: =IF(L12="Inactive",0,IF(ISNUMBER(F12)*ISNUMBER(E12),IF(F12>E12,F12-E12,0),0)) -> 0 | J12: =IF(L12="Inactive",0,IF(ISNUMBER(D12)*ISNUMBER(G12),IF(D12>G12,D12-G12,0),0)) -> 0 | K12: =IF(L12="Inactive",0,IF(ISNUMBER(E12)*ISNUMBER(F12),IF(E12>F12,E12-F12,0),0)) -> 0 | L12: Active | O12: =IF(A12="","—",A12&" ("&TEXT(B12,"MM/DD/YYYY")&")") -> —
C13: =IF(B13="","",TEXT(B13,"mmmm")) | E13: =IF(D13="","",D13*'Exchange Rate'!$E$5) | G13: =IF(F13="","",F13*'Exchange Rate'!$B$5) | H13: =IF(L13="Inactive",0,IF(ISNUMBER(G13)*ISNUMBER(D13),IF(G13>D13,G13-D13,0),0)) -> 0 | I13: =IF(L13="Inactive",0,IF(ISNUMBER(F13)*ISNUMBER(E13),IF(F13>E13,F13-E13,0),0)) -> 0 | J13: =IF(L13="Inactive",0,IF(ISNUMBER(D13)*ISNUMBER(G13),IF(D13>G13,D13-G13,0),0)) -> 0 | K13: =IF(L13="Inactive",0,IF(ISNUMBER(E13)*ISNUMBER(F13),IF(E13>F13,E13-F13,0),0)) -> 0 | L13: Active | O13: =IF(A13="","—",A13&" ("&TEXT(B13,"MM/DD/YYYY")&")") -> —
C14: =IF(B14="","",TEXT(B14,"mmmm")) | E14: =IF(D14="","",D14*'Exchange Rate'!$E$5) | G14: =IF(F14="","",F14*'Exchange Rate'!$B$5) | H14: =IF(L14="Inactive",0,IF(ISNUMBER(G14)*ISNUMBER(D14),IF(G14>D14,G14-D14,0),0)) -> 0 | I14: =IF(L14="Inactive",0,IF(ISNUMBER(F14)*ISNUMBER(E14),IF(F14>E14,F14-E14,0),0)) -> 0 | J14: =IF(L14="Inactive",0,IF(ISNUMBER(D14)*ISNUMBER(G14),IF(D14>G14,D14-G14,0),0)) -> 0 | K14: =IF(L14="Inactive",0,IF(ISNUMBER(E14)*ISNUMBER(F14),IF(E14>F14,E14-F14,0),0)) -> 0 | L14: Active | O14: =IF(A14="","—",A14&" ("&TEXT(B14,"MM/DD/YYYY")&")") -> —
C15: =IF(B15="","",TEXT(B15,"mmmm")) | E15: =IF(D15="","",D15*'Exchange Rate'!$E$5) | G15: =IF(F15="","",F15*'Exchange Rate'!$B$5) | H15: =IF(L15="Inactive",0,IF(ISNUMBER(G15)*ISNUMBER(D15),IF(G15>D15,G15-D15,0),0)) -> 0 | I15: =IF(L15="Inactive",0,IF(ISNUMBER(F15)*ISNUMBER(E15),IF(F15>E15,F15-E15,0),0)) -> 0 | J15: =IF(L15="Inactive",0,IF(ISNUMBER(D15)*ISNUMBER(G15),IF(D15>G15,D15-G15,0),0)) -> 0 | K15: =IF(L15="Inactive",0,IF(ISNUMBER(E15)*ISNUMBER(F15),IF(E15>F15,E15-F15,0),0)) -> 0 | L15: Active | O15: =IF(A15="","—",A15&" ("&TEXT(B15,"MM/DD/YYYY")&")") -> —
C16: =IF(B16="","",TEXT(B16,"mmmm")) | E16: =IF(D16="","",D16*'Exchange Rate'!$E$5) | G16: =IF(F16="","",F16*'Exchange Rate'!$B$5) | H16: =IF(L16="Inactive",0,IF(ISNUMBER(G16)*ISNUMBER(D16),IF(G16>D16,G16-D16,0),0)) -> 0 | I16: =IF(L16="Inactive",0,IF(ISNUMBER(F16)*ISNUMBER(E16),IF(F16>E16,F16-E16,0),0)) -> 0 | J16: =IF(L16="Inactive",0,IF(ISNUMBER(D16)*ISNUMBER(G16),IF(D16>G16,D16-G16,0),0)) -> 0 | K16: =IF(L16="Inactive",0,IF(ISNUMBER(E16)*ISNUMBER(F16),IF(E16>F16,E16-F16,0),0)) -> 0 | L16: Active | O16: =IF(A16="","—",A16&" ("&TEXT(B16,"MM/DD/YYYY")&")") -> —
C17: =IF(B17="","",TEXT(B17,"mmmm")) | E17: =IF(D17="","",D17*'Exchange Rate'!$E$5) | G17: =IF(F17="","",F17*'Exchange Rate'!$B$5) | H17: =IF(L17="Inactive",0,IF(ISNUMBER(G17)*ISNUMBER(D17),IF(G17>D17,G17-D17,0),0)) -> 0 | I17: =IF(L17="Inactive",0,IF(ISNUMBER(F17)*ISNUMBER(E17),IF(F17>E17,F17-E17,0),0)) -> 0 | J17: =IF(L17="Inactive",0,IF(ISNUMBER(D17)*ISNUMBER(G17),IF(D17>G17,D17-G17,0),0)) -> 0 | K17: =IF(L17="Inactive",0,IF(ISNUMBER(E17)*ISNUMBER(F17),IF(E17>F17,E17-F17,0),0)) -> 0 | L17: Active | O17: =IF(A17="","—",A17&" ("&TEXT(B17,"MM/DD/YYYY")&")") -> —
C18: =IF(B18="","",TEXT(B18,"mmmm")) | E18: =IF(D18="","",D18*'Exchange Rate'!$E$5) | G18: =IF(F18="","",F18*'Exchange Rate'!$B$5) | H18: =IF(L18="Inactive",0,IF(ISNUMBER(G18)*ISNUMBER(D18),IF(G18>D18,G18-D18,0),0)) -> 0 | I18: =IF(L18="Inactive",0,IF(ISNUMBER(F18)*ISNUMBER(E18),IF(F18>E18,F18-E18,0),0)) -> 0 | J18: =IF(L18="Inactive",0,IF(ISNUMBER(D18)*ISNUMBER(G18),IF(D18>G18,D18-G18,0),0)) -> 0 | K18: =IF(L18="Inactive",0,IF(ISNUMBER(E18)*ISNUMBER(F18),IF(E18>F18,E18-F18,0),0)) -> 0 | L18: Active | O18: =IF(A18="","—",A18&" ("&TEXT(B18,"MM/DD/YYYY")&")") -> —
C19: =IF(B19="","",TEXT(B19,"mmmm")) | E19: =IF(D19="","",D19*'Exchange Rate'!$E$5) | G19: =IF(F19="","",F19*'Exchange Rate'!$B$5) | H19: =IF(L19="Inactive",0,IF(ISNUMBER(G19)*ISNUMBER(D19),IF(G19>D19,G19-D19,0),0)) -> 0 | I19: =IF(L19="Inactive",0,IF(ISNUMBER(F19)*ISNUMBER(E19),IF(F19>E19,F19-E19,0),0)) -> 0 | J19: =IF(L19="Inactive",0,IF(ISNUMBER(D19)*ISNUMBER(G19),IF(D19>G19,D19-G19,0),0)) -> 0 | K19: =IF(L19="Inactive",0,IF(ISNUMBER(E19)*ISNUMBER(F19),IF(E19>F19,E19-F19,0),0)) -> 0 | L19: Active | O19: =IF(A19="","—",A19&" ("&TEXT(B19,"MM/DD/YYYY")&")") -> —
... C107: =IF(B107="","",TEXT(B107,"mmmm")) | E107: =IF(D107="","",D107*'Exchange Rate'!$E$5) | G107: =IF(F107="","",F107*'Exchange Rate'!$B$5) | H107: =IF(L107="Inactive",0,IF(ISNUMBER(G107)*ISNUMBER(D107),IF(G107>D107,G107-D107,0),0)) -> 0 | I107: =IF(L107="Inactive",0,IF(ISNUMBER(F107)*ISNUMBER(E107),IF(F107>E107,F107-E107,0),0)) -> 0 | J107: =IF(L107="Inactive",0,IF(ISNUMBER(D107)*ISNUMBER(G107),IF(D107>G107,D107-G107,0),0)) -> 0 | K107: =IF(L107="Inactive",0,IF(ISNUMBER(E107)*ISNUMBER(F107),IF(E107>F107,E107-F107,0),0)) -> 0 | L107: Active | O107: =IF(A107="","—",A107&" ("&TEXT(B107,"MM/DD/YYYY")&")") -> —
A108: TOTAL CATEGORY VALUE | D108: =SUM(D8:D107) -> 0 | E108: =SUM(E8:E107) -> 0 | F108: =SUM(F8:F107) -> 0 | G108: =SUM(G8:G107) -> 0 | H108: =SUM(H8:H107) -> 0 | I108: =SUM(I8:I107) -> 0 | J108: =SUM(J8:J107) -> 0 | K108: =SUM(K8:K107) -> 0 | ... N108: =SUM(N8:N107) -> 0
A110: 📋 USER GUIDE & OPERATIONAL INSTRUCTIONS
A111: Step 1 — DATA ENTRY
A112: Input rows sequentially. Type directly into Col D (Purchase JPY) and Col F (Selling PHP) ONLY. All other columns auto-calculate. Yellow cells = manual entry. White cells = formulas.
A113: Step 2 — DUPLICATE IDs
A114: If tracking duplicate items, check the QUICK-VIEW bar (Row 5). A ⚠️ alert fires when the same Product ID appears more than once. Use the 'Date of Entry' (Col B) timestamp in the lookup to immediately distinguish which entry is which.
A115: Step 3 — ANALYTICS FILTER
A116: Toggle the Analytics view on the '9. Overall Analytics' sheet using the timeframe filter (D2) to review Weekly, Monthly, or Annual financial health variations.
A117: Step 4 — EXCHANGE RATES
A118: Never manually edit currency columns. To update rates, go to the 'Exchange Rate' sheet and edit ONLY cells B5 (PHP→JPY) or E5 (JPY→PHP). All values across the workbook update instantly.
A119: Step 5 — STOCK STATUS
A120: Use Column L dropdown (Active/Inactive) to toggle items. Inactive rows contribute ZERO to profit, loss, and analytics totals — ideal for recalled, damaged, or discontinued stock.

Sheet 3. Onhand orders JPY
A1: KEN JP ANIME FIGURES SHOP
A4: 📦 3. ONHAND ORDERS JPY | Rates: 'Exchange Rate'!B5 (PHP→JPY) & E5 (JPY→PHP)
A5: 🔍 FUZZY SEARCH | B5: ⬇ type partial name or ID: | D5: =IF($C$5="","← type above",IFERROR(ROWS(filter($M$8:$M$107,ISNUMBER(SEARCH($C$5,$M$8:$M$107))))&" match(es) found","❌ 0 found")) -> ← type above | E5: View match #: | F5: 1 | G5: =IF($C$5="","— no active search —",IFERROR(INDEX(filter($M$8:$M$107,ISNUMBER(SEARCH($C$5,$M$8:$M$107)),"❌ No Data Found"),VALUE($F$5)),"❌ No Data Found")) -> — no active search — | H5: =IFERROR(IF($G$5="❌ No Data Found","—",IF($G$5="— no active search —","—",INDEX($D$8:$D$107,MATCH($G$5,$M$8:$M$107,0)))),"—") -> — | I5: =IFERROR(IF($G$5="❌ No Data Found","—",IF($G$5="— no active search —","—",INDEX($F$8:$F$107,MATCH($G$5,$M$8:$M$107,0)))),"—") -> — | J5: =IFERROR(IF($G$5="❌ No Data Found","—",IF($G$5="— no active search —","—",INDEX($H$8:$H$107,MATCH($G$5,$M$8:$M$107,0)))),"—") -> — | K5: =IFERROR(IF($G$5="❌ No Data Found","—",IF($G$5="— no active search —","—",INDEX($J$8:$J$107,MATCH($G$5,$M$8:$M$107,0)))),"—") -> — | L5: =IFERROR(IF($G$5="❌ No Data Found","—",IF($G$5="— no active search —","—",INDEX($L$8:$L$107,MATCH($G$5,$M$8:$M$107,0)))),"—") -> —
A7: Product ID | B7: Date of Entry | C7: Transaction Month | D7: Purchase Price (JPY) | E7: Purchase Price (PHP) | F7: Selling Price (PHP) | G7: Selling Price (JPY) | H7: Net Profit (JPY) | I7: Net Profit (PHP) | J7: Net Loss (JPY) | K7: Net Loss (PHP) | L7: Stock Status | M7: SEARCH_KEY (hidden)
C8: =IF(B8="","",TEXT(B8,"mmmm")) | E8: =IF(D8="","",D8*'Exchange Rate'!$E$5) | G8: =IF(F8="","",F8*'Exchange Rate'!$B$5) | H8: =IF(L8="Inactive",0,IF(ISNUMBER(G8)*ISNUMBER(D8),IF(G8>D8,G8-D8,0),0)) -> 0 | I8: =IF(L8="Inactive",0,IF(ISNUMBER(F8)*ISNUMBER(E8),IF(F8>E8,F8-E8,0),0)) -> 0 | J8: =IF(L8="Inactive",0,IF(ISNUMBER(D8)*ISNUMBER(G8),IF(D8>G8,D8-G8,0),0)) -> 0 | K8: =IF(L8="Inactive",0,IF(ISNUMBER(E8)*ISNUMBER(F8),IF(E8>F8,E8-F8,0),0)) -> 0 | L8: Active | M8: =IF(A8="","—",A8&" ("&TEXT(B8,"MM/DD/YYYY")&")") -> —
C9: =IF(B9="","",TEXT(B9,"mmmm")) | E9: =IF(D9="","",D9*'Exchange Rate'!$E$5) | G9: =IF(F9="","",F9*'Exchange Rate'!$B$5) | H9: =IF(L9="Inactive",0,IF(ISNUMBER(G9)*ISNUMBER(D9),IF(G9>D9,G9-D9,0),0)) -> 0 | I9: =IF(L9="Inactive",0,IF(ISNUMBER(F9)*ISNUMBER(E9),IF(F9>E9,F9-E9,0),0)) -> 0 | J9: =IF(L9="Inactive",0,IF(ISNUMBER(D9)*ISNUMBER(G9),IF(D9>G9,D9-G9,0),0)) -> 0 | K9: =IF(L9="Inactive",0,IF(ISNUMBER(E9)*ISNUMBER(F9),IF(E9>F9,E9-F9,0),0)) -> 0 | L9: Active | M9: =IF(A9="","—",A9&" ("&TEXT(B9,"MM/DD/YYYY")&")") -> —
C10: =IF(B10="","",TEXT(B10,"mmmm")) | E10: =IF(D10="","",D10*'Exchange Rate'!$E$5) | G10: =IF(F10="","",F10*'Exchange Rate'!$B$5) | H10: =IF(L10="Inactive",0,IF(ISNUMBER(G10)*ISNUMBER(D10),IF(G10>D10,G10-D10,0),0)) -> 0 | I10: =IF(L10="Inactive",0,IF(ISNUMBER(F10)*ISNUMBER(E10),IF(F10>E10,F10-E10,0),0)) -> 0 | J10: =IF(L10="Inactive",0,IF(ISNUMBER(D10)*ISNUMBER(G10),IF(D10>G10,D10-G10,0),0)) -> 0 | K10: =IF(L10="Inactive",0,IF(ISNUMBER(E10)*ISNUMBER(F10),IF(E10>F10,E10-F10,0),0)) -> 0 | L10: Active | M10: =IF(A10="","—",A10&" ("&TEXT(B10,"MM/DD/YYYY")&")") -> —
C11: =IF(B11="","",TEXT(B11,"mmmm")) | E11: =IF(D11="","",D11*'Exchange Rate'!$E$5) | G11: =IF(F11="","",F11*'Exchange Rate'!$B$5) | H11: =IF(L11="Inactive",0,IF(ISNUMBER(G11)*ISNUMBER(D11),IF(G11>D11,G11-D11,0),0)) -> 0 | I11: =IF(L11="Inactive",0,IF(ISNUMBER(F11)*ISNUMBER(E11),IF(F11>E11,F11-E11,0),0)) -> 0 | J11: =IF(L11="Inactive",0,IF(ISNUMBER(D11)*ISNUMBER(G11),IF(D11>G11,D11-G11,0),0)) -> 0 | K11: =IF(L11="Inactive",0,IF(ISNUMBER(E11)*ISNUMBER(F11),IF(E11>F11,E11-F11,0),0)) -> 0 | L11: Active | M11: =IF(A11="","—",A11&" ("&TEXT(B11,"MM/DD/YYYY")&")") -> —
C12: =IF(B12="","",TEXT(B12,"mmmm")) | E12: =IF(D12="","",D12*'Exchange Rate'!$E$5) | G12: =IF(F12="","",F12*'Exchange Rate'!$B$5) | H12: =IF(L12="Inactive",0,IF(ISNUMBER(G12)*ISNUMBER(D12),IF(G12>D12,G12-D12,0),0)) -> 0 | I12: =IF(L12="Inactive",0,IF(ISNUMBER(F12)*ISNUMBER(E12),IF(F12>E12,F12-E12,0),0)) -> 0 | J12: =IF(L12="Inactive",0,IF(ISNUMBER(D12)*ISNUMBER(G12),IF(D12>G12,D12-G12,0),0)) -> 0 | K12: =IF(L12="Inactive",0,IF(ISNUMBER(E12)*ISNUMBER(F12),IF(E12>F12,E12-F12,0),0)) -> 0 | L12: Active | M12: =IF(A12="","—",A12&" ("&TEXT(B12,"MM/DD/YYYY")&")") -> —
C13: =IF(B13="","",TEXT(B13,"mmmm")) | E13: =IF(D13="","",D13*'Exchange Rate'!$E$5) | G13: =IF(F13="","",F13*'Exchange Rate'!$B$5) | H13: =IF(L13="Inactive",0,IF(ISNUMBER(G13)*ISNUMBER(D13),IF(G13>D13,G13-D13,0),0)) -> 0 | I13: =IF(L13="Inactive",0,IF(ISNUMBER(F13)*ISNUMBER(E13),IF(F13>E13,F13-E13,0),0)) -> 0 | J13: =IF(L13="Inactive",0,IF(ISNUMBER(D13)*ISNUMBER(G13),IF(D13>G13,D13-G13,0),0)) -> 0 | K13: =IF(L13="Inactive",0,IF(ISNUMBER(E13)*ISNUMBER(F13),IF(E13>F13,E13-F13,0),0)) -> 0 | L13: Active | M13: =IF(A13="","—",A13&" ("&TEXT(B13,"MM/DD/YYYY")&")") -> —
C14: =IF(B14="","",TEXT(B14,"mmmm")) | E14: =IF(D14="","",D14*'Exchange Rate'!$E$5) | G14: =IF(F14="","",F14*'Exchange Rate'!$B$5) | H14: =IF(L14="Inactive",0,IF(ISNUMBER(G14)*ISNUMBER(D14),IF(G14>D14,G14-D14,0),0)) -> 0 | I14: =IF(L14="Inactive",0,IF(ISNUMBER(F14)*ISNUMBER(E14),IF(F14>E14,F14-E14,0),0)) -> 0 | J14: =IF(L14="Inactive",0,IF(ISNUMBER(D14)*ISNUMBER(G14),IF(D14>G14,D14-G14,0),0)) -> 0 | K14: =IF(L14="Inactive",0,IF(ISNUMBER(E14)*ISNUMBER(F14),IF(E14>F14,E14-F14,0),0)) -> 0 | L14: Active | M14: =IF(A14="","—",A14&" ("&TEXT(B14,"MM/DD/YYYY")&")") -> —
C15: =IF(B15="","",TEXT(B15,"mmmm")) | E15: =IF(D15="","",D15*'Exchange Rate'!$E$5) | G15: =IF(F15="","",F15*'Exchange Rate'!$B$5) | H15: =IF(L15="Inactive",0,IF(ISNUMBER(G15)*ISNUMBER(D15),IF(G15>D15,G15-D15,0),0)) -> 0 | I15: =IF(L15="Inactive",0,IF(ISNUMBER(F15)*ISNUMBER(E15),IF(F15>E15,F15-E15,0),0)) -> 0 | J15: =IF(L15="Inactive",0,IF(ISNUMBER(D15)*ISNUMBER(G15),IF(D15>G15,D15-G15,0),0)) -> 0 | K15: =IF(L15="Inactive",0,IF(ISNUMBER(E15)*ISNUMBER(F15),IF(E15>F15,E15-F15,0),0)) -> 0 | L15: Active | M15: =IF(A15="","—",A15&" ("&TEXT(B15,"MM/DD/YYYY")&")") -> —
C16: =IF(B16="","",TEXT(B16,"mmmm")) | E16: =IF(D16="","",D16*'Exchange Rate'!$E$5) | G16: =IF(F16="","",F16*'Exchange Rate'!$B$5) | H16: =IF(L16="Inactive",0,IF(ISNUMBER(G16)*ISNUMBER(D16),IF(G16>D16,G16-D16,0),0)) -> 0 | I16: =IF(L16="Inactive",0,IF(ISNUMBER(F16)*ISNUMBER(E16),IF(F16>E16,F16-E16,0),0)) -> 0 | J16: =IF(L16="Inactive",0,IF(ISNUMBER(D16)*ISNUMBER(G16),IF(D16>G16,D16-G16,0),0)) -> 0 | K16: =IF(L16="Inactive",0,IF(ISNUMBER(E16)*ISNUMBER(F16),IF(E16>F16,E16-F16,0),0)) -> 0 | L16: Active | M16: =IF(A16="","—",A16&" ("&TEXT(B16,"MM/DD/YYYY")&")") -> —
C17: =IF(B17="","",TEXT(B17,"mmmm")) | E17: =IF(D17="","",D17*'Exchange Rate'!$E$5) | G17: =IF(F17="","",F17*'Exchange Rate'!$B$5) | H17: =IF(L17="Inactive",0,IF(ISNUMBER(G17)*ISNUMBER(D17),IF(G17>D17,G17-D17,0),0)) -> 0 | I17: =IF(L17="Inactive",0,IF(ISNUMBER(F17)*ISNUMBER(E17),IF(F17>E17,F17-E17,0),0)) -> 0 | J17: =IF(L17="Inactive",0,IF(ISNUMBER(D17)*ISNUMBER(G17),IF(D17>G17,D17-G17,0),0)) -> 0 | K17: =IF(L17="Inactive",0,IF(ISNUMBER(E17)*ISNUMBER(F17),IF(E17>F17,E17-F17,0),0)) -> 0 | L17: Active | M17: =IF(A17="","—",A17&" ("&TEXT(B17,"MM/DD/YYYY")&")") -> —
C18: =IF(B18="","",TEXT(B18,"mmmm")) | E18: =IF(D18="","",D18*'Exchange Rate'!$E$5) | G18: =IF(F18="","",F18*'Exchange Rate'!$B$5) | H18: =IF(L18="Inactive",0,IF(ISNUMBER(G18)*ISNUMBER(D18),IF(G18>D18,G18-D18,0),0)) -> 0 | I18: =IF(L18="Inactive",0,IF(ISNUMBER(F18)*ISNUMBER(E18),IF(F18>E18,F18-E18,0),0)) -> 0 | J18: =IF(L18="Inactive",0,IF(ISNUMBER(D18)*ISNUMBER(G18),IF(D18>G18,D18-G18,0),0)) -> 0 | K18: =IF(L18="Inactive",0,IF(ISNUMBER(E18)*ISNUMBER(F18),IF(E18>F18,E18-F18,0),0)) -> 0 | L18: Active | M18: =IF(A18="","—",A18&" ("&TEXT(B18,"MM/DD/YYYY")&")") -> —
C19: =IF(B19="","",TEXT(B19,"mmmm")) | E19: =IF(D19="","",D19*'Exchange Rate'!$E$5) | G19: =IF(F19="","",F19*'Exchange Rate'!$B$5) | H19: =IF(L19="Inactive",0,IF(ISNUMBER(G19)*ISNUMBER(D19),IF(G19>D19,G19-D19,0),0)) -> 0 | I19: =IF(L19="Inactive",0,IF(ISNUMBER(F19)*ISNUMBER(E19),IF(F19>E19,F19-E19,0),0)) -> 0 | J19: =IF(L19="Inactive",0,IF(ISNUMBER(D19)*ISNUMBER(G19),IF(D19>G19,D19-G19,0),0)) -> 0 | K19: =IF(L19="Inactive",0,IF(ISNUMBER(E19)*ISNUMBER(F19),IF(E19>F19,E19-F19,0),0)) -> 0 | L19: Active | M19: =IF(A19="","—",A19&" ("&TEXT(B19,"MM/DD/YYYY")&")") -> —
... C107: =IF(B107="","",TEXT(B107,"mmmm")) | E107: =IF(D107="","",D107*'Exchange Rate'!$E$5) | G107: =IF(F107="","",F107*'Exchange Rate'!$B$5) | H107: =IF(L107="Inactive",0,IF(ISNUMBER(G107)*ISNUMBER(D107),IF(G107>D107,G107-D107,0),0)) -> 0 | I107: =IF(L107="Inactive",0,IF(ISNUMBER(F107)*ISNUMBER(E107),IF(F107>E107,F107-E107,0),0)) -> 0 | J107: =IF(L107="Inactive",0,IF(ISNUMBER(D107)*ISNUMBER(G107),IF(D107>G107,D107-G107,0),0)) -> 0 | K107: =IF(L107="Inactive",0,IF(ISNUMBER(E107)*ISNUMBER(F107),IF(E107>F107,E107-F107,0),0)) -> 0 | L107: Active | M107: =IF(A107="","—",A107&" ("&TEXT(B107,"MM/DD/YYYY")&")") -> —
A108: TOTAL CATEGORY VALUE | D108: =SUM(D8:D107) -> 0 | E108: =SUM(E8:E107) -> 0 | F108: =SUM(F8:F107) -> 0 | G108: =SUM(G8:G107) -> 0 | H108: =SUM(H8:H107) -> 0 | I108: =SUM(I8:I107) -> 0 | J108: =SUM(J8:J107) -> 0 | K108: =SUM(K8:K107) -> 0 | L108: =SUM(L8:L107) -> 0
A110: 📋 USER GUIDE & OPERATIONAL INSTRUCTIONS
A111: Step 1 — DATA ENTRY
A112: Input rows sequentially. Type directly into Col D (Purchase JPY) and Col F (Selling PHP) ONLY. All other columns auto-calculate. Yellow cells = manual entry. White cells = formulas.
A113: Step 2 — DUPLICATE IDs
A114: If tracking duplicate items, check the QUICK-VIEW bar (Row 5). A ⚠️ alert fires when the same Product ID appears more than once. Use the 'Date of Entry' (Col B) timestamp in the lookup to immediately distinguish which entry is which.
A115: Step 3 — ANALYTICS FILTER
A116: Toggle the Analytics view on the '9. Overall Analytics' sheet using the timeframe filter (D2) to review Weekly, Monthly, or Annual financial health variations.
A117: Step 4 — EXCHANGE RATES
A118: Never manually edit currency columns. To update rates, go to the 'Exchange Rate' sheet and edit ONLY cells B5 (PHP→JPY) or E5 (JPY→PHP). All values across the workbook update instantly.
A119: Step 5 — STOCK STATUS
A120: Use Column L dropdown (Active/Inactive) to toggle items. Inactive rows contribute ZERO to profit, loss, and analytics totals — ideal for recalled, damaged, or discontinued stock.

Sheet 4. Live Selling Orders
A1: KEN JP ANIME FIGURES SHOP
A4: 📦 4. LIVE SELLING ORDERS | Rates: 'Exchange Rate'!B5 (PHP→JPY) & E5 (JPY→PHP)
A5: 🔍 FUZZY SEARCH | B5: ⬇ type partial name or ID: | D5: =IF($C$5="","← type above",IFERROR(ROWS(filter($M$8:$M$107,ISNUMBER(SEARCH($C$5,$M$8:$M$107))))&" match(es) found","❌ 0 found")) -> ← type above | E5: View match #: | F5: 1 | G5: =IF($C$5="","— no active search —",IFERROR(INDEX(filter($M$8:$M$107,ISNUMBER(SEARCH($C$5,$M$8:$M$107)),"❌ No Data Found"),VALUE($F$5)),"❌ No Data Found")) -> — no active search — | H5: =IFERROR(IF($G$5="❌ No Data Found","—",IF($G$5="— no active search —","—",INDEX($D$8:$D$107,MATCH($G$5,$M$8:$M$107,0)))),"—") -> — | I5: =IFERROR(IF($G$5="❌ No Data Found","—",IF($G$5="— no active search —","—",INDEX($F$8:$F$107,MATCH($G$5,$M$8:$M$107,0)))),"—") -> — | J5: =IFERROR(IF($G$5="❌ No Data Found","—",IF($G$5="— no active search —","—",INDEX($H$8:$H$107,MATCH($G$5,$M$8:$M$107,0)))),"—") -> — | K5: =IFERROR(IF($G$5="❌ No Data Found","—",IF($G$5="— no active search —","—",INDEX($J$8:$J$107,MATCH($G$5,$M$8:$M$107,0)))),"—") -> — | L5: =IFERROR(IF($G$5="❌ No Data Found","—",IF($G$5="— no active search —","—",INDEX($L$8:$L$107,MATCH($G$5,$M$8:$M$107,0)))),"—") -> —
A7: Product ID | B7: Date of Entry | C7: Transaction Month | D7: Purchase Price (JPY) | E7: Purchase Price (PHP) | F7: Selling Price (PHP) | G7: Selling Price (JPY) | H7: Net Profit (JPY) | I7: Net Profit (PHP) | J7: Net Loss (JPY) | K7: Net Loss (PHP) | L7: Stock Status | M7: SEARCH_KEY (hidden)
C8: =IF(B8="","",TEXT(B8,"mmmm")) | E8: =IF(D8="","",D8*'Exchange Rate'!$E$5) | G8: =IF(F8="","",F8*'Exchange Rate'!$B$5) | H8: =IF(L8="Inactive",0,IF(ISNUMBER(G8)*ISNUMBER(D8),IF(G8>D8,G8-D8,0),0)) -> 0 | I8: =IF(L8="Inactive",0,IF(ISNUMBER(F8)*ISNUMBER(E8),IF(F8>E8,F8-E8,0),0)) -> 0 | J8: =IF(L8="Inactive",0,IF(ISNUMBER(D8)*ISNUMBER(G8),IF(D8>G8,D8-G8,0),0)) -> 0 | K8: =IF(L8="Inactive",0,IF(ISNUMBER(E8)*ISNUMBER(F8),IF(E8>F8,E8-F8,0),0)) -> 0 | L8: Active | M8: =IF(A8="","—",A8&" ("&TEXT(B8,"MM/DD/YYYY")&")") -> —
C9: =IF(B9="","",TEXT(B9,"mmmm")) | E9: =IF(D9="","",D9*'Exchange Rate'!$E$5) | G9: =IF(F9="","",F9*'Exchange Rate'!$B$5) | H9: =IF(L9="Inactive",0,IF(ISNUMBER(G9)*ISNUMBER(D9),IF(G9>D9,G9-D9,0),0)) -> 0 | I9: =IF(L9="Inactive",0,IF(ISNUMBER(F9)*ISNUMBER(E9),IF(F9>E9,F9-E9,0),0)) -> 0 | J9: =IF(L9="Inactive",0,IF(ISNUMBER(D9)*ISNUMBER(G9),IF(D9>G9,D9-G9,0),0)) -> 0 | K9: =IF(L9="Inactive",0,IF(ISNUMBER(E9)*ISNUMBER(F9),IF(E9>F9,E9-F9,0),0)) -> 0 | L9: Active | M9: =IF(A9="","—",A9&" ("&TEXT(B9,"MM/DD/YYYY")&")") -> —
C10: =IF(B10="","",TEXT(B10,"mmmm")) | E10: =IF(D10="","",D10*'Exchange Rate'!$E$5) | G10: =IF(F10="","",F10*'Exchange Rate'!$B$5) | H10: =IF(L10="Inactive",0,IF(ISNUMBER(G10)*ISNUMBER(D10),IF(G10>D10,G10-D10,0),0)) -> 0 | I10: =IF(L10="Inactive",0,IF(ISNUMBER(F10)*ISNUMBER(E10),IF(F10>E10,F10-E10,0),0)) -> 0 | J10: =IF(L10="Inactive",0,IF(ISNUMBER(D10)*ISNUMBER(G10),IF(D10>G10,D10-G10,0),0)) -> 0 | K10: =IF(L10="Inactive",0,IF(ISNUMBER(E10)*ISNUMBER(F10),IF(E10>F10,E10-F10,0),0)) -> 0 | L10: Active | M10: =IF(A10="","—",A10&" ("&TEXT(B10,"MM/DD/YYYY")&")") -> —
C11: =IF(B11="","",TEXT(B11,"mmmm")) | E11: =IF(D11="","",D11*'Exchange Rate'!$E$5) | G11: =IF(F11="","",F11*'Exchange Rate'!$B$5) | H11: =IF(L11="Inactive",0,IF(ISNUMBER(G11)*ISNUMBER(D11),IF(G11>D11,G11-D11,0),0)) -> 0 | I11: =IF(L11="Inactive",0,IF(ISNUMBER(F11)*ISNUMBER(E11),IF(F11>E11,F11-E11,0),0)) -> 0 | J11: =IF(L11="Inactive",0,IF(ISNUMBER(D11)*ISNUMBER(G11),IF(D11>G11,D11-G11,0),0)) -> 0 | K11: =IF(L11="Inactive",0,IF(ISNUMBER(E11)*ISNUMBER(F11),IF(E11>F11,E11-F11,0),0)) -> 0 | L11: Active | M11: =IF(A11="","—",A11&" ("&TEXT(B11,"MM/DD/YYYY")&")") -> —
C12: =IF(B12="","",TEXT(B12,"mmmm")) | E12: =IF(D12="","",D12*'Exchange Rate'!$E$5) | G12: =IF(F12="","",F12*'Exchange Rate'!$B$5) | H12: =IF(L12="Inactive",0,IF(ISNUMBER(G12)*ISNUMBER(D12),IF(G12>D12,G12-D12,0),0)) -> 0 | I12: =IF(L12="Inactive",0,IF(ISNUMBER(F12)*ISNUMBER(E12),IF(F12>E12,F12-E12,0),0)) -> 0 | J12: =IF(L12="Inactive",0,IF(ISNUMBER(D12)*ISNUMBER(G12),IF(D12>G12,D12-G12,0),0)) -> 0 | K12: =IF(L12="Inactive",0,IF(ISNUMBER(E12)*ISNUMBER(F12),IF(E12>F12,E12-F12,0),0)) -> 0 | L12: Active | M12: =IF(A12="","—",A12&" ("&TEXT(B12,"MM/DD/YYYY")&")") -> —
C13: =IF(B13="","",TEXT(B13,"mmmm")) | E13: =IF(D13="","",D13*'Exchange Rate'!$E$5) | G13: =IF(F13="","",F13*'Exchange Rate'!$B$5) | H13: =IF(L13="Inactive",0,IF(ISNUMBER(G13)*ISNUMBER(D13),IF(G13>D13,G13-D13,0),0)) -> 0 | I13: =IF(L13="Inactive",0,IF(ISNUMBER(F13)*ISNUMBER(E13),IF(F13>E13,F13-E13,0),0)) -> 0 | J13: =IF(L13="Inactive",0,IF(ISNUMBER(D13)*ISNUMBER(G13),IF(D13>G13,D13-G13,0),0)) -> 0 | K13: =IF(L13="Inactive",0,IF(ISNUMBER(E13)*ISNUMBER(F13),IF(E13>F13,E13-F13,0),0)) -> 0 | L13: Active | M13: =IF(A13="","—",A13&" ("&TEXT(B13,"MM/DD/YYYY")&")") -> —
C14: =IF(B14="","",TEXT(B14,"mmmm")) | E14: =IF(D14="","",D14*'Exchange Rate'!$E$5) | G14: =IF(F14="","",F14*'Exchange Rate'!$B$5) | H14: =IF(L14="Inactive",0,IF(ISNUMBER(G14)*ISNUMBER(D14),IF(G14>D14,G14-D14,0),0)) -> 0 | I14: =IF(L14="Inactive",0,IF(ISNUMBER(F14)*ISNUMBER(E14),IF(F14>E14,F14-E14,0),0)) -> 0 | J14: =IF(L14="Inactive",0,IF(ISNUMBER(D14)*ISNUMBER(G14),IF(D14>G14,D14-G14,0),0)) -> 0 | K14: =IF(L14="Inactive",0,IF(ISNUMBER(E14)*ISNUMBER(F14),IF(E14>F14,E14-F14,0),0)) -> 0 | L14: Active | M14: =IF(A14="","—",A14&" ("&TEXT(B14,"MM/DD/YYYY")&")") -> —
C15: =IF(B15="","",TEXT(B15,"mmmm")) | E15: =IF(D15="","",D15*'Exchange Rate'!$E$5) | G15: =IF(F15="","",F15*'Exchange Rate'!$B$5) | H15: =IF(L15="Inactive",0,IF(ISNUMBER(G15)*ISNUMBER(D15),IF(G15>D15,G15-D15,0),0)) -> 0 | I15: =IF(L15="Inactive",0,IF(ISNUMBER(F15)*ISNUMBER(E15),IF(F15>E15,F15-E15,0),0)) -> 0 | J15: =IF(L15="Inactive",0,IF(ISNUMBER(D15)*ISNUMBER(G15),IF(D15>G15,D15-G15,0),0)) -> 0 | K15: =IF(L15="Inactive",0,IF(ISNUMBER(E15)*ISNUMBER(F15),IF(E15>F15,E15-F15,0),0)) -> 0 | L15: Active | M15: =IF(A15="","—",A15&" ("&TEXT(B15,"MM/DD/YYYY")&")") -> —
C16: =IF(B16="","",TEXT(B16,"mmmm")) | E16: =IF(D16="","",D16*'Exchange Rate'!$E$5) | G16: =IF(F16="","",F16*'Exchange Rate'!$B$5) | H16: =IF(L16="Inactive",0,IF(ISNUMBER(G16)*ISNUMBER(D16),IF(G16>D16,G16-D16,0),0)) -> 0 | I16: =IF(L16="Inactive",0,IF(ISNUMBER(F16)*ISNUMBER(E16),IF(F16>E16,F16-E16,0),0)) -> 0 | J16: =IF(L16="Inactive",0,IF(ISNUMBER(D16)*ISNUMBER(G16),IF(D16>G16,D16-G16,0),0)) -> 0 | K16: =IF(L16="Inactive",0,IF(ISNUMBER(E16)*ISNUMBER(F16),IF(E16>F16,E16-F16,0),0)) -> 0 | L16: Active | M16: =IF(A16="","—",A16&" ("&TEXT(B16,"MM/DD/YYYY")&")") -> —
C17: =IF(B17="","",TEXT(B17,"mmmm")) | E17: =IF(D17="","",D17*'Exchange Rate'!$E$5) | G17: =IF(F17="","",F17*'Exchange Rate'!$B$5) | H17: =IF(L17="Inactive",0,IF(ISNUMBER(G17)*ISNUMBER(D17),IF(G17>D17,G17-D17,0),0)) -> 0 | I17: =IF(L17="Inactive",0,IF(ISNUMBER(F17)*ISNUMBER(E17),IF(F17>E17,F17-E17,0),0)) -> 0 | J17: =IF(L17="Inactive",0,IF(ISNUMBER(D17)*ISNUMBER(G17),IF(D17>G17,D17-G17,0),0)) -> 0 | K17: =IF(L17="Inactive",0,IF(ISNUMBER(E17)*ISNUMBER(F17),IF(E17>F17,E17-F17,0),0)) -> 0 | L17: Active | M17: =IF(A17="","—",A17&" ("&TEXT(B17,"MM/DD/YYYY")&")") -> —
C18: =IF(B18="","",TEXT(B18,"mmmm")) | E18: =IF(D18="","",D18*'Exchange Rate'!$E$5) | G18: =IF(F18="","",F18*'Exchange Rate'!$B$5) | H18: =IF(L18="Inactive",0,IF(ISNUMBER(G18)*ISNUMBER(D18),IF(G18>D18,G18-D18,0),0)) -> 0 | I18: =IF(L18="Inactive",0,IF(ISNUMBER(F18)*ISNUMBER(E18),IF(F18>E18,F18-E18,0),0)) -> 0 | J18: =IF(L18="Inactive",0,IF(ISNUMBER(D18)*ISNUMBER(G18),IF(D18>G18,D18-G18,0),0)) -> 0 | K18: =IF(L18="Inactive",0,IF(ISNUMBER(E18)*ISNUMBER(F18),IF(E18>F18,E18-F18,0),0)) -> 0 | L18: Active | M18: =IF(A18="","—",A18&" ("&TEXT(B18,"MM/DD/YYYY")&")") -> —
C19: =IF(B19="","",TEXT(B19,"mmmm")) | E19: =IF(D19="","",D19*'Exchange Rate'!$E$5) | G19: =IF(F19="","",F19*'Exchange Rate'!$B$5) | H19: =IF(L19="Inactive",0,IF(ISNUMBER(G19)*ISNUMBER(D19),IF(G19>D19,G19-D19,0),0)) -> 0 | I19: =IF(L19="Inactive",0,IF(ISNUMBER(F19)*ISNUMBER(E19),IF(F19>E19,F19-E19,0),0)) -> 0 | J19: =IF(L19="Inactive",0,IF(ISNUMBER(D19)*ISNUMBER(G19),IF(D19>G19,D19-G19,0),0)) -> 0 | K19: =IF(L19="Inactive",0,IF(ISNUMBER(E19)*ISNUMBER(F19),IF(E19>F19,E19-F19,0),0)) -> 0 | L19: Active | M19: =IF(A19="","—",A19&" ("&TEXT(B19,"MM/DD/YYYY")&")") -> —
... C107: =IF(B107="","",TEXT(B107,"mmmm")) | E107: =IF(D107="","",D107*'Exchange Rate'!$E$5) | G107: =IF(F107="","",F107*'Exchange Rate'!$B$5) | H107: =IF(L107="Inactive",0,IF(ISNUMBER(G107)*ISNUMBER(D107),IF(G107>D107,G107-D107,0),0)) -> 0 | I107: =IF(L107="Inactive",0,IF(ISNUMBER(F107)*ISNUMBER(E107),IF(F107>E107,F107-E107,0),0)) -> 0 | J107: =IF(L107="Inactive",0,IF(ISNUMBER(D107)*ISNUMBER(G107),IF(D107>G107,D107-G107,0),0)) -> 0 | K107: =IF(L107="Inactive",0,IF(ISNUMBER(E107)*ISNUMBER(F107),IF(E107>F107,E107-F107,0),0)) -> 0 | L107: Active | M107: =IF(A107="","—",A107&" ("&TEXT(B107,"MM/DD/YYYY")&")") -> —
A108: TOTAL CATEGORY VALUE | D108: =SUM(D8:D107) -> 0 | E108: =SUM(E8:E107) -> 0 | F108: =SUM(F8:F107) -> 0 | G108: =SUM(G8:G107) -> 0 | H108: =SUM(H8:H107) -> 0 | I108: =SUM(I8:I107) -> 0 | J108: =SUM(J8:J107) -> 0 | K108: =SUM(K8:K107) -> 0 | L108: =SUM(L8:L107) -> 0
A110: 📋 USER GUIDE & OPERATIONAL INSTRUCTIONS
A111: Step 1 — DATA ENTRY
A112: Input rows sequentially. Type directly into Col D (Purchase JPY) and Col F (Selling PHP) ONLY. All other columns auto-calculate. Yellow cells = manual entry. White cells = formulas.
A113: Step 2 — DUPLICATE IDs
A114: If tracking duplicate items, check the QUICK-VIEW bar (Row 5). A ⚠️ alert fires when the same Product ID appears more than once. Use the 'Date of Entry' (Col B) timestamp in the lookup to immediately distinguish which entry is which.
A115: Step 3 — ANALYTICS FILTER
A116: Toggle the Analytics view on the '9. Overall Analytics' sheet using the timeframe filter (D2) to review Weekly, Monthly, or Annual financial health variations.
A117: Step 4 — EXCHANGE RATES
A118: Never manually edit currency columns. To update rates, go to the 'Exchange Rate' sheet and edit ONLY cells B5 (PHP→JPY) or E5 (JPY→PHP). All values across the workbook update instantly.
A119: Step 5 — STOCK STATUS
A120: Use Column L dropdown (Active/Inactive) to toggle items. Inactive rows contribute ZERO to profit, loss, and analytics totals — ideal for recalled, damaged, or discontinued stock.

Sheet 5. On hand orders PHP
A1: KEN JP ANIME FIGURES SHOP
A4: 📦 5. ON HAND ORDERS PHP | Rates: 'Exchange Rate'!B5 (PHP→JPY) & E5 (JPY→PHP)
A5: 🔍 FUZZY SEARCH | B5: ⬇ type partial name or ID: | D5: =IF($C$5="","← type above",IFERROR(ROWS(filter($M$8:$M$107,ISNUMBER(SEARCH($C$5,$M$8:$M$107))))&" match(es) found","❌ 0 found")) -> ← type above | E5: View match #: | F5: 1 | G5: =IF($C$5="","— no active search —",IFERROR(INDEX(filter($M$8:$M$107,ISNUMBER(SEARCH($C$5,$M$8:$M$107)),"❌ No Data Found"),VALUE($F$5)),"❌ No Data Found")) -> — no active search — | H5: =IFERROR(IF($G$5="❌ No Data Found","—",IF($G$5="— no active search —","—",INDEX($D$8:$D$107,MATCH($G$5,$M$8:$M$107,0)))),"—") -> — | I5: =IFERROR(IF($G$5="❌ No Data Found","—",IF($G$5="— no active search —","—",INDEX($F$8:$F$107,MATCH($G$5,$M$8:$M$107,0)))),"—") -> — | J5: =IFERROR(IF($G$5="❌ No Data Found","—",IF($G$5="— no active search —","—",INDEX($H$8:$H$107,MATCH($G$5,$M$8:$M$107,0)))),"—") -> — | K5: =IFERROR(IF($G$5="❌ No Data Found","—",IF($G$5="— no active search —","—",INDEX($J$8:$J$107,MATCH($G$5,$M$8:$M$107,0)))),"—") -> — | L5: =IFERROR(IF($G$5="❌ No Data Found","—",IF($G$5="— no active search —","—",INDEX($L$8:$L$107,MATCH($G$5,$M$8:$M$107,0)))),"—") -> —
A7: Product ID | B7: Date of Entry | C7: Transaction Month | D7: Purchase Price (JPY) | E7: Purchase Price (PHP) | F7: Selling Price (PHP) | G7: Selling Price (JPY) | H7: Net Profit (JPY) | I7: Net Profit (PHP) | J7: Net Loss (JPY) | K7: Net Loss (PHP) | L7: Stock Status | M7: SEARCH_KEY (hidden)
C8: =IF(B8="","",TEXT(B8,"mmmm")) | E8: =IF(D8="","",D8*'Exchange Rate'!$E$5) | G8: =IF(F8="","",F8*'Exchange Rate'!$B$5) | H8: =IF(L8="Inactive",0,IF(ISNUMBER(G8)*ISNUMBER(D8),IF(G8>D8,G8-D8,0),0)) -> 0 | I8: =IF(L8="Inactive",0,IF(ISNUMBER(F8)*ISNUMBER(E8),IF(F8>E8,F8-E8,0),0)) -> 0 | J8: =IF(L8="Inactive",0,IF(ISNUMBER(D8)*ISNUMBER(G8),IF(D8>G8,D8-G8,0),0)) -> 0 | K8: =IF(L8="Inactive",0,IF(ISNUMBER(E8)*ISNUMBER(F8),IF(E8>F8,E8-F8,0),0)) -> 0 | L8: Active | M8: =IF(A8="","—",A8&" ("&TEXT(B8,"MM/DD/YYYY")&")") -> —
C9: =IF(B9="","",TEXT(B9,"mmmm")) | E9: =IF(D9="","",D9*'Exchange Rate'!$E$5) | G9: =IF(F9="","",F9*'Exchange Rate'!$B$5) | H9: =IF(L9="Inactive",0,IF(ISNUMBER(G9)*ISNUMBER(D9),IF(G9>D9,G9-D9,0),0)) -> 0 | I9: =IF(L9="Inactive",0,IF(ISNUMBER(F9)*ISNUMBER(E9),IF(F9>E9,F9-E9,0),0)) -> 0 | J9: =IF(L9="Inactive",0,IF(ISNUMBER(D9)*ISNUMBER(G9),IF(D9>G9,D9-G9,0),0)) -> 0 | K9: =IF(L9="Inactive",0,IF(ISNUMBER(E9)*ISNUMBER(F9),IF(E9>F9,E9-F9,0),0)) -> 0 | L9: Active | M9: =IF(A9="","—",A9&" ("&TEXT(B9,"MM/DD/YYYY")&")") -> —
C10: =IF(B10="","",TEXT(B10,"mmmm")) | E10: =IF(D10="","",D10*'Exchange Rate'!$E$5) | G10: =IF(F10="","",F10*'Exchange Rate'!$B$5) | H10: =IF(L10="Inactive",0,IF(ISNUMBER(G10)*ISNUMBER(D10),IF(G10>D10,G10-D10,0),0)) -> 0 | I10: =IF(L10="Inactive",0,IF(ISNUMBER(F10)*ISNUMBER(E10),IF(F10>E10,F10-E10,0),0)) -> 0 | J10: =IF(L10="Inactive",0,IF(ISNUMBER(D10)*ISNUMBER(G10),IF(D10>G10,D10-G10,0),0)) -> 0 | K10: =IF(L10="Inactive",0,IF(ISNUMBER(E10)*ISNUMBER(F10),IF(E10>F10,E10-F10,0),0)) -> 0 | L10: Active | M10: =IF(A10="","—",A10&" ("&TEXT(B10,"MM/DD/YYYY")&")") -> —
C11: =IF(B11="","",TEXT(B11,"mmmm")) | E11: =IF(D11="","",D11*'Exchange Rate'!$E$5) | G11: =IF(F11="","",F11*'Exchange Rate'!$B$5) | H11: =IF(L11="Inactive",0,IF(ISNUMBER(G11)*ISNUMBER(D11),IF(G11>D11,G11-D11,0),0)) -> 0 | I11: =IF(L11="Inactive",0,IF(ISNUMBER(F11)*ISNUMBER(E11),IF(F11>E11,F11-E11,0),0)) -> 0 | J11: =IF(L11="Inactive",0,IF(ISNUMBER(D11)*ISNUMBER(G11),IF(D11>G11,D11-G11,0),0)) -> 0 | K11: =IF(L11="Inactive",0,IF(ISNUMBER(E11)*ISNUMBER(F11),IF(E11>F11,E11-F11,0),0)) -> 0 | L11: Active | M11: =IF(A11="","—",A11&" ("&TEXT(B11,"MM/DD/YYYY")&")") -> —
C12: =IF(B12="","",TEXT(B12,"mmmm")) | E12: =IF(D12="","",D12*'Exchange Rate'!$E$5) | G12: =IF(F12="","",F12*'Exchange Rate'!$B$5) | H12: =IF(L12="Inactive",0,IF(ISNUMBER(G12)*ISNUMBER(D12),IF(G12>D12,G12-D12,0),0)) -> 0 | I12: =IF(L12="Inactive",0,IF(ISNUMBER(F12)*ISNUMBER(E12),IF(F12>E12,F12-E12,0),0)) -> 0 | J12: =IF(L12="Inactive",0,IF(ISNUMBER(D12)*ISNUMBER(G12),IF(D12>G12,D12-G12,0),0)) -> 0 | K12: =IF(L12="Inactive",0,IF(ISNUMBER(E12)*ISNUMBER(F12),IF(E12>F12,E12-F12,0),0)) -> 0 | L12: Active | M12: =IF(A12="","—",A12&" ("&TEXT(B12,"MM/DD/YYYY")&")") -> —
C13: =IF(B13="","",TEXT(B13,"mmmm")) | E13: =IF(D13="","",D13*'Exchange Rate'!$E$5) | G13: =IF(F13="","",F13*'Exchange Rate'!$B$5) | H13: =IF(L13="Inactive",0,IF(ISNUMBER(G13)*ISNUMBER(D13),IF(G13>D13,G13-D13,0),0)) -> 0 | I13: =IF(L13="Inactive",0,IF(ISNUMBER(F13)*ISNUMBER(E13),IF(F13>E13,F13-E13,0),0)) -> 0 | J13: =IF(L13="Inactive",0,IF(ISNUMBER(D13)*ISNUMBER(G13),IF(D13>G13,D13-G13,0),0)) -> 0 | K13: =IF(L13="Inactive",0,IF(ISNUMBER(E13)*ISNUMBER(F13),IF(E13>F13,E13-F13,0),0)) -> 0 | L13: Active | M13: =IF(A13="","—",A13&" ("&TEXT(B13,"MM/DD/YYYY")&")") -> —
C14: =IF(B14="","",TEXT(B14,"mmmm")) | E14: =IF(D14="","",D14*'Exchange Rate'!$E$5) | G14: =IF(F14="","",F14*'Exchange Rate'!$B$5) | H14: =IF(L14="Inactive",0,IF(ISNUMBER(G14)*ISNUMBER(D14),IF(G14>D14,G14-D14,0),0)) -> 0 | I14: =IF(L14="Inactive",0,IF(ISNUMBER(F14)*ISNUMBER(E14),IF(F14>E14,F14-E14,0),0)) -> 0 | J14: =IF(L14="Inactive",0,IF(ISNUMBER(D14)*ISNUMBER(G14),IF(D14>G14,D14-G14,0),0)) -> 0 | K14: =IF(L14="Inactive",0,IF(ISNUMBER(E14)*ISNUMBER(F14),IF(E14>F14,E14-F14,0),0)) -> 0 | L14: Active | M14: =IF(A14="","—",A14&" ("&TEXT(B14,"MM/DD/YYYY")&")") -> —
C15: =IF(B15="","",TEXT(B15,"mmmm")) | E15: =IF(D15="","",D15*'Exchange Rate'!$E$5) | G15: =IF(F15="","",F15*'Exchange Rate'!$B$5) | H15: =IF(L15="Inactive",0,IF(ISNUMBER(G15)*ISNUMBER(D15),IF(G15>D15,G15-D15,0),0)) -> 0 | I15: =IF(L15="Inactive",0,IF(ISNUMBER(F15)*ISNUMBER(E15),IF(F15>E15,F15-E15,0),0)) -> 0 | J15: =IF(L15="Inactive",0,IF(ISNUMBER(D15)*ISNUMBER(G15),IF(D15>G15,D15-G15,0),0)) -> 0 | K15: =IF(L15="Inactive",0,IF(ISNUMBER(E15)*ISNUMBER(F15),IF(E15>F15,E15-F15,0),0)) -> 0 | L15: Active | M15: =IF(A15="","—",A15&" ("&TEXT(B15,"MM/DD/YYYY")&")") -> —
C16: =IF(B16="","",TEXT(B16,"mmmm")) | E16: =IF(D16="","",D16*'Exchange Rate'!$E$5) | G16: =IF(F16="","",F16*'Exchange Rate'!$B$5) | H16: =IF(L16="Inactive",0,IF(ISNUMBER(G16)*ISNUMBER(D16),IF(G16>D16,G16-D16,0),0)) -> 0 | I16: =IF(L16="Inactive",0,IF(ISNUMBER(F16)*ISNUMBER(E16),IF(F16>E16,F16-E16,0),0)) -> 0 | J16: =IF(L16="Inactive",0,IF(ISNUMBER(D16)*ISNUMBER(G16),IF(D16>G16,D16-G16,0),0)) -> 0 | K16: =IF(L16="Inactive",0,IF(ISNUMBER(E16)*ISNUMBER(F16),IF(E16>F16,E16-F16,0),0)) -> 0 | L16: Active | M16: =IF(A16="","—",A16&" ("&TEXT(B16,"MM/DD/YYYY")&")") -> —
C17: =IF(B17="","",TEXT(B17,"mmmm")) | E17: =IF(D17="","",D17*'Exchange Rate'!$E$5) | G17: =IF(F17="","",F17*'Exchange Rate'!$B$5) | H17: =IF(L17="Inactive",0,IF(ISNUMBER(G17)*ISNUMBER(D17),IF(G17>D17,G17-D17,0),0)) -> 0 | I17: =IF(L17="Inactive",0,IF(ISNUMBER(F17)*ISNUMBER(E17),IF(F17>E17,F17-E17,0),0)) -> 0 | J17: =IF(L17="Inactive",0,IF(ISNUMBER(D17)*ISNUMBER(G17),IF(D17>G17,D17-G17,0),0)) -> 0 | K17: =IF(L17="Inactive",0,IF(ISNUMBER(E17)*ISNUMBER(F17),IF(E17>F17,E17-F17,0),0)) -> 0 | L17: Active | M17: =IF(A17="","—",A17&" ("&TEXT(B17,"MM/DD/YYYY")&")") -> —
C18: =IF(B18="","",TEXT(B18,"mmmm")) | E18: =IF(D18="","",D18*'Exchange Rate'!$E$5) | G18: =IF(F18="","",F18*'Exchange Rate'!$B$5) | H18: =IF(L18="Inactive",0,IF(ISNUMBER(G18)*ISNUMBER(D18),IF(G18>D18,G18-D18,0),0)) -> 0 | I18: =IF(L18="Inactive",0,IF(ISNUMBER(F18)*ISNUMBER(E18),IF(F18>E18,F18-E18,0),0)) -> 0 | J18: =IF(L18="Inactive",0,IF(ISNUMBER(D18)*ISNUMBER(G18),IF(D18>G18,D18-G18,0),0)) -> 0 | K18: =IF(L18="Inactive",0,IF(ISNUMBER(E18)*ISNUMBER(F18),IF(E18>F18,E18-F18,0),0)) -> 0 | L18: Active | M18: =IF(A18="","—",A18&" ("&TEXT(B18,"MM/DD/YYYY")&")") -> —
C19: =IF(B19="","",TEXT(B19,"mmmm")) | E19: =IF(D19="","",D19*'Exchange Rate'!$E$5) | G19: =IF(F19="","",F19*'Exchange Rate'!$B$5) | H19: =IF(L19="Inactive",0,IF(ISNUMBER(G19)*ISNUMBER(D19),IF(G19>D19,G19-D19,0),0)) -> 0 | I19: =IF(L19="Inactive",0,IF(ISNUMBER(F19)*ISNUMBER(E19),IF(F19>E19,F19-E19,0),0)) -> 0 | J19: =IF(L19="Inactive",0,IF(ISNUMBER(D19)*ISNUMBER(G19),IF(D19>G19,D19-G19,0),0)) -> 0 | K19: =IF(L19="Inactive",0,IF(ISNUMBER(E19)*ISNUMBER(F19),IF(E19>F19,E19-F19,0),0)) -> 0 | L19: Active | M19: =IF(A19="","—",A19&" ("&TEXT(B19,"MM/DD/YYYY")&")") -> —
... C107: =IF(B107="","",TEXT(B107,"mmmm")) | E107: =IF(D107="","",D107*'Exchange Rate'!$E$5) | G107: =IF(F107="","",F107*'Exchange Rate'!$B$5) | H107: =IF(L107="Inactive",0,IF(ISNUMBER(G107)*ISNUMBER(D107),IF(G107>D107,G107-D107,0),0)) -> 0 | I107: =IF(L107="Inactive",0,IF(ISNUMBER(F107)*ISNUMBER(E107),IF(F107>E107,F107-E107,0),0)) -> 0 | J107: =IF(L107="Inactive",0,IF(ISNUMBER(D107)*ISNUMBER(G107),IF(D107>G107,D107-G107,0),0)) -> 0 | K107: =IF(L107="Inactive",0,IF(ISNUMBER(E107)*ISNUMBER(F107),IF(E107>F107,E107-F107,0),0)) -> 0 | L107: Active | M107: =IF(A107="","—",A107&" ("&TEXT(B107,"MM/DD/YYYY")&")") -> —
A108: TOTAL CATEGORY VALUE | D108: =SUM(D8:D107) -> 0 | E108: =SUM(E8:E107) -> 0 | F108: =SUM(F8:F107) -> 0 | G108: =SUM(G8:G107) -> 0 | H108: =SUM(H8:H107) -> 0 | I108: =SUM(I8:I107) -> 0 | J108: =SUM(J8:J107) -> 0 | K108: =SUM(K8:K107) -> 0 | L108: =SUM(L8:L107) -> 0
A110: 📋 USER GUIDE & OPERATIONAL INSTRUCTIONS
A111: Step 1 — DATA ENTRY
A112: Input rows sequentially. Type directly into Col D (Purchase JPY) and Col F (Selling PHP) ONLY. All other columns auto-calculate. Yellow cells = manual entry. White cells = formulas.
A113: Step 2 — DUPLICATE IDs
A114: If tracking duplicate items, check the QUICK-VIEW bar (Row 5). A ⚠️ alert fires when the same Product ID appears more than once. Use the 'Date of Entry' (Col B) timestamp in the lookup to immediately distinguish which entry is which.
A115: Step 3 — ANALYTICS FILTER
A116: Toggle the Analytics view on the '9. Overall Analytics' sheet using the timeframe filter (D2) to review Weekly, Monthly, or Annual financial health variations.
A117: Step 4 — EXCHANGE RATES
A118: Never manually edit currency columns. To update rates, go to the 'Exchange Rate' sheet and edit ONLY cells B5 (PHP→JPY) or E5 (JPY→PHP). All values across the workbook update instantly.
A119: Step 5 — STOCK STATUS
A120: Use Column L dropdown (Active/Inactive) to toggle items. Inactive rows contribute ZERO to profit, loss, and analytics totals — ideal for recalled, damaged, or discontinued stock.

Sheet 6. Pre Orders
A1: KEN JP ANIME FIGURES SHOP
A4: 📦 6. PRE ORDERS | Rates: 'Exchange Rate'!B5 (PHP→JPY) & E5 (JPY→PHP)
A5: 🔍 FUZZY SEARCH | B5: ⬇ type partial name or ID: | D5: =IF($C$5="","← type above",IFERROR(ROWS(filter($M$8:$M$107,ISNUMBER(SEARCH($C$5,$M$8:$M$107))))&" match(es) found","❌ 0 found")) -> ← type above | E5: View match #: | F5: 1 | G5: =IF($C$5="","— no active search —",IFERROR(INDEX(filter($M$8:$M$107,ISNUMBER(SEARCH($C$5,$M$8:$M$107)),"❌ No Data Found"),VALUE($F$5)),"❌ No Data Found")) -> — no active search — | H5: =IFERROR(IF($G$5="❌ No Data Found","—",IF($G$5="— no active search —","—",INDEX($D$8:$D$107,MATCH($G$5,$M$8:$M$107,0)))),"—") -> — | I5: =IFERROR(IF($G$5="❌ No Data Found","—",IF($G$5="— no active search —","—",INDEX($F$8:$F$107,MATCH($G$5,$M$8:$M$107,0)))),"—") -> — | J5: =IFERROR(IF($G$5="❌ No Data Found","—",IF($G$5="— no active search —","—",INDEX($H$8:$H$107,MATCH($G$5,$M$8:$M$107,0)))),"—") -> — | K5: =IFERROR(IF($G$5="❌ No Data Found","—",IF($G$5="— no active search —","—",INDEX($J$8:$J$107,MATCH($G$5,$M$8:$M$107,0)))),"—") -> — | L5: =IFERROR(IF($G$5="❌ No Data Found","—",IF($G$5="— no active search —","—",INDEX($L$8:$L$107,MATCH($G$5,$M$8:$M$107,0)))),"—") -> —
A7: Product ID | B7: Date of Entry | C7: Transaction Month | D7: Purchase Price (JPY) | E7: Purchase Price (PHP) | F7: Selling Price (PHP) | G7: Selling Price (JPY) | H7: Net Profit (JPY) | I7: Net Profit (PHP) | J7: Net Loss (JPY) | K7: Net Loss (PHP) | L7: Stock Status | M7: SEARCH_KEY (hidden)
C8: =IF(B8="","",TEXT(B8,"mmmm")) | E8: =IF(D8="","",D8*'Exchange Rate'!$E$5) | G8: =IF(F8="","",F8*'Exchange Rate'!$B$5) | H8: =IF(L8="Inactive",0,IF(ISNUMBER(G8)*ISNUMBER(D8),IF(G8>D8,G8-D8,0),0)) -> 0 | I8: =IF(L8="Inactive",0,IF(ISNUMBER(F8)*ISNUMBER(E8),IF(F8>E8,F8-E8,0),0)) -> 0 | J8: =IF(L8="Inactive",0,IF(ISNUMBER(D8)*ISNUMBER(G8),IF(D8>G8,D8-G8,0),0)) -> 0 | K8: =IF(L8="Inactive",0,IF(ISNUMBER(E8)*ISNUMBER(F8),IF(E8>F8,E8-F8,0),0)) -> 0 | L8: Active | M8: =IF(A8="","—",A8&" ("&TEXT(B8,"MM/DD/YYYY")&")") -> —
C9: =IF(B9="","",TEXT(B9,"mmmm")) | E9: =IF(D9="","",D9*'Exchange Rate'!$E$5) | G9: =IF(F9="","",F9*'Exchange Rate'!$B$5) | H9: =IF(L9="Inactive",0,IF(ISNUMBER(G9)*ISNUMBER(D9),IF(G9>D9,G9-D9,0),0)) -> 0 | I9: =IF(L9="Inactive",0,IF(ISNUMBER(F9)*ISNUMBER(E9),IF(F9>E9,F9-E9,0),0)) -> 0 | J9: =IF(L9="Inactive",0,IF(ISNUMBER(D9)*ISNUMBER(G9),IF(D9>G9,D9-G9,0),0)) -> 0 | K9: =IF(L9="Inactive",0,IF(ISNUMBER(E9)*ISNUMBER(F9),IF(E9>F9,E9-F9,0),0)) -> 0 | L9: Active | M9: =IF(A9="","—",A9&" ("&TEXT(B9,"MM/DD/YYYY")&")") -> —
C10: =IF(B10="","",TEXT(B10,"mmmm")) | E10: =IF(D10="","",D10*'Exchange Rate'!$E$5) | G10: =IF(F10="","",F10*'Exchange Rate'!$B$5) | H10: =IF(L10="Inactive",0,IF(ISNUMBER(G10)*ISNUMBER(D10),IF(G10>D10,G10-D10,0),0)) -> 0 | I10: =IF(L10="Inactive",0,IF(ISNUMBER(F10)*ISNUMBER(E10),IF(F10>E10,F10-E10,0),0)) -> 0 | J10: =IF(L10="Inactive",0,IF(ISNUMBER(D10)*ISNUMBER(G10),IF(D10>G10,D10-G10,0),0)) -> 0 | K10: =IF(L10="Inactive",0,IF(ISNUMBER(E10)*ISNUMBER(F10),IF(E10>F10,E10-F10,0),0)) -> 0 | L10: Active | M10: =IF(A10="","—",A10&" ("&TEXT(B10,"MM/DD/YYYY")&")") -> —
C11: =IF(B11="","",TEXT(B11,"mmmm")) | E11: =IF(D11="","",D11*'Exchange Rate'!$E$5) | G11: =IF(F11="","",F11*'Exchange Rate'!$B$5) | H11: =IF(L11="Inactive",0,IF(ISNUMBER(G11)*ISNUMBER(D11),IF(G11>D11,G11-D11,0),0)) -> 0 | I11: =IF(L11="Inactive",0,IF(ISNUMBER(F11)*ISNUMBER(E11),IF(F11>E11,F11-E11,0),0)) -> 0 | J11: =IF(L11="Inactive",0,IF(ISNUMBER(D11)*ISNUMBER(G11),IF(D11>G11,D11-G11,0),0)) -> 0 | K11: =IF(L11="Inactive",0,IF(ISNUMBER(E11)*ISNUMBER(F11),IF(E11>F11,E11-F11,0),0)) -> 0 | L11: Active | M11: =IF(A11="","—",A11&" ("&TEXT(B11,"MM/DD/YYYY")&")") -> —
C12: =IF(B12="","",TEXT(B12,"mmmm")) | E12: =IF(D12="","",D12*'Exchange Rate'!$E$5) | G12: =IF(F12="","",F12*'Exchange Rate'!$B$5) | H12: =IF(L12="Inactive",0,IF(ISNUMBER(G12)*ISNUMBER(D12),IF(G12>D12,G12-D12,0),0)) -> 0 | I12: =IF(L12="Inactive",0,IF(ISNUMBER(F12)*ISNUMBER(E12),IF(F12>E12,F12-E12,0),0)) -> 0 | J12: =IF(L12="Inactive",0,IF(ISNUMBER(D12)*ISNUMBER(G12),IF(D12>G12,D12-G12,0),0)) -> 0 | K12: =IF(L12="Inactive",0,IF(ISNUMBER(E12)*ISNUMBER(F12),IF(E12>F12,E12-F12,0),0)) -> 0 | L12: Active | M12: =IF(A12="","—",A12&" ("&TEXT(B12,"MM/DD/YYYY")&")") -> —
C13: =IF(B13="","",TEXT(B13,"mmmm")) | E13: =IF(D13="","",D13*'Exchange Rate'!$E$5) | G13: =IF(F13="","",F13*'Exchange Rate'!$B$5) | H13: =IF(L13="Inactive",0,IF(ISNUMBER(G13)*ISNUMBER(D13),IF(G13>D13,G13-D13,0),0)) -> 0 | I13: =IF(L13="Inactive",0,IF(ISNUMBER(F13)*ISNUMBER(E13),IF(F13>E13,F13-E13,0),0)) -> 0 | J13: =IF(L13="Inactive",0,IF(ISNUMBER(D13)*ISNUMBER(G13),IF(D13>G13,D13-G13,0),0)) -> 0 | K13: =IF(L13="Inactive",0,IF(ISNUMBER(E13)*ISNUMBER(F13),IF(E13>F13,E13-F13,0),0)) -> 0 | L13: Active | M13: =IF(A13="","—",A13&" ("&TEXT(B13,"MM/DD/YYYY")&")") -> —
C14: =IF(B14="","",TEXT(B14,"mmmm")) | E14: =IF(D14="","",D14*'Exchange Rate'!$E$5) | G14: =IF(F14="","",F14*'Exchange Rate'!$B$5) | H14: =IF(L14="Inactive",0,IF(ISNUMBER(G14)*ISNUMBER(D14),IF(G14>D14,G14-D14,0),0)) -> 0 | I14: =IF(L14="Inactive",0,IF(ISNUMBER(F14)*ISNUMBER(E14),IF(F14>E14,F14-E14,0),0)) -> 0 | J14: =IF(L14="Inactive",0,IF(ISNUMBER(D14)*ISNUMBER(G14),IF(D14>G14,D14-G14,0),0)) -> 0 | K14: =IF(L14="Inactive",0,IF(ISNUMBER(E14)*ISNUMBER(F14),IF(E14>F14,E14-F14,0),0)) -> 0 | L14: Active | M14: =IF(A14="","—",A14&" ("&TEXT(B14,"MM/DD/YYYY")&")") -> —
C15: =IF(B15="","",TEXT(B15,"mmmm")) | E15: =IF(D15="","",D15*'Exchange Rate'!$E$5) | G15: =IF(F15="","",F15*'Exchange Rate'!$B$5) | H15: =IF(L15="Inactive",0,IF(ISNUMBER(G15)*ISNUMBER(D15),IF(G15>D15,G15-D15,0),0)) -> 0 | I15: =IF(L15="Inactive",0,IF(ISNUMBER(F15)*ISNUMBER(E15),IF(F15>E15,F15-E15,0),0)) -> 0 | J15: =IF(L15="Inactive",0,IF(ISNUMBER(D15)*ISNUMBER(G15),IF(D15>G15,D15-G15,0),0)) -> 0 | K15: =IF(L15="Inactive",0,IF(ISNUMBER(E15)*ISNUMBER(F15),IF(E15>F15,E15-F15,0),0)) -> 0 | L15: Active | M15: =IF(A15="","—",A15&" ("&TEXT(B15,"MM/DD/YYYY")&")") -> —
C16: =IF(B16="","",TEXT(B16,"mmmm")) | E16: =IF(D16="","",D16*'Exchange Rate'!$E$5) | G16: =IF(F16="","",F16*'Exchange Rate'!$B$5) | H16: =IF(L16="Inactive",0,IF(ISNUMBER(G16)*ISNUMBER(D16),IF(G16>D16,G16-D16,0),0)) -> 0 | I16: =IF(L16="Inactive",0,IF(ISNUMBER(F16)*ISNUMBER(E16),IF(F16>E16,F16-E16,0),0)) -> 0 | J16: =IF(L16="Inactive",0,IF(ISNUMBER(D16)*ISNUMBER(G16),IF(D16>G16,D16-G16,0),0)) -> 0 | K16: =IF(L16="Inactive",0,IF(ISNUMBER(E16)*ISNUMBER(F16),IF(E16>F16,E16-F16,0),0)) -> 0 | L16: Active | M16: =IF(A16="","—",A16&" ("&TEXT(B16,"MM/DD/YYYY")&")") -> —
C17: =IF(B17="","",TEXT(B17,"mmmm")) | E17: =IF(D17="","",D17*'Exchange Rate'!$E$5) | G17: =IF(F17="","",F17*'Exchange Rate'!$B$5) | H17: =IF(L17="Inactive",0,IF(ISNUMBER(G17)*ISNUMBER(D17),IF(G17>D17,G17-D17,0),0)) -> 0 | I17: =IF(L17="Inactive",0,IF(ISNUMBER(F17)*ISNUMBER(E17),IF(F17>E17,F17-E17,0),0)) -> 0 | J17: =IF(L17="Inactive",0,IF(ISNUMBER(D17)*ISNUMBER(G17),IF(D17>G17,D17-G17,0),0)) -> 0 | K17: =IF(L17="Inactive",0,IF(ISNUMBER(E17)*ISNUMBER(F17),IF(E17>F17,E17-F17,0),0)) -> 0 | L17: Active | M17: =IF(A17="","—",A17&" ("&TEXT(B17,"MM/DD/YYYY")&")") -> —
C18: =IF(B18="","",TEXT(B18,"mmmm")) | E18: =IF(D18="","",D18*'Exchange Rate'!$E$5) | G18: =IF(F18="","",F18*'Exchange Rate'!$B$5) | H18: =IF(L18="Inactive",0,IF(ISNUMBER(G18)*ISNUMBER(D18),IF(G18>D18,G18-D18,0),0)) -> 0 | I18: =IF(L18="Inactive",0,IF(ISNUMBER(F18)*ISNUMBER(E18),IF(F18>E18,F18-E18,0),0)) -> 0 | J18: =IF(L18="Inactive",0,IF(ISNUMBER(D18)*ISNUMBER(G18),IF(D18>G18,D18-G18,0),0)) -> 0 | K18: =IF(L18="Inactive",0,IF(ISNUMBER(E18)*ISNUMBER(F18),IF(E18>F18,E18-F18,0),0)) -> 0 | L18: Active | M18: =IF(A18="","—",A18&" ("&TEXT(B18,"MM/DD/YYYY")&")") -> —
C19: =IF(B19="","",TEXT(B19,"mmmm")) | E19: =IF(D19="","",D19*'Exchange Rate'!$E$5) | G19: =IF(F19="","",F19*'Exchange Rate'!$B$5) | H19: =IF(L19="Inactive",0,IF(ISNUMBER(G19)*ISNUMBER(D19),IF(G19>D19,G19-D19,0),0)) -> 0 | I19: =IF(L19="Inactive",0,IF(ISNUMBER(F19)*ISNUMBER(E19),IF(F19>E19,F19-E19,0),0)) -> 0 | J19: =IF(L19="Inactive",0,IF(ISNUMBER(D19)*ISNUMBER(G19),IF(D19>G19,D19-G19,0),0)) -> 0 | K19: =IF(L19="Inactive",0,IF(ISNUMBER(E19)*ISNUMBER(F19),IF(E19>F19,E19-F19,0),0)) -> 0 | L19: Active | M19: =IF(A19="","—",A19&" ("&TEXT(B19,"MM/DD/YYYY")&")") -> —
... C107: =IF(B107="","",TEXT(B107,"mmmm")) | E107: =IF(D107="","",D107*'Exchange Rate'!$E$5) | G107: =IF(F107="","",F107*'Exchange Rate'!$B$5) | H107: =IF(L107="Inactive",0,IF(ISNUMBER(G107)*ISNUMBER(D107),IF(G107>D107,G107-D107,0),0)) -> 0 | I107: =IF(L107="Inactive",0,IF(ISNUMBER(F107)*ISNUMBER(E107),IF(F107>E107,F107-E107,0),0)) -> 0 | J107: =IF(L107="Inactive",0,IF(ISNUMBER(D107)*ISNUMBER(G107),IF(D107>G107,D107-G107,0),0)) -> 0 | K107: =IF(L107="Inactive",0,IF(ISNUMBER(E107)*ISNUMBER(F107),IF(E107>F107,E107-F107,0),0)) -> 0 | L107: Active | M107: =IF(A107="","—",A107&" ("&TEXT(B107,"MM/DD/YYYY")&")") -> —
A108: TOTAL CATEGORY VALUE | D108: =SUM(D8:D107) -> 0 | E108: =SUM(E8:E107) -> 0 | F108: =SUM(F8:F107) -> 0 | G108: =SUM(G8:G107) -> 0 | H108: =SUM(H8:H107) -> 0 | I108: =SUM(I8:I107) -> 0 | J108: =SUM(J8:J107) -> 0 | K108: =SUM(K8:K107) -> 0 | L108: =SUM(L8:L107) -> 0
A110: 📋 USER GUIDE & OPERATIONAL INSTRUCTIONS
A111: Step 1 — DATA ENTRY
A112: Input rows sequentially. Type directly into Col D (Purchase JPY) and Col F (Selling PHP) ONLY. All other columns auto-calculate. Yellow cells = manual entry. White cells = formulas.
A113: Step 2 — DUPLICATE IDs
A114: If tracking duplicate items, check the QUICK-VIEW bar (Row 5). A ⚠️ alert fires when the same Product ID appears more than once. Use the 'Date of Entry' (Col B) timestamp in the lookup to immediately distinguish which entry is which.
A115: Step 3 — ANALYTICS FILTER
A116: Toggle the Analytics view on the '9. Overall Analytics' sheet using the timeframe filter (D2) to review Weekly, Monthly, or Annual financial health variations.
A117: Step 4 — EXCHANGE RATES
A118: Never manually edit currency columns. To update rates, go to the 'Exchange Rate' sheet and edit ONLY cells B5 (PHP→JPY) or E5 (JPY→PHP). All values across the workbook update instantly.
A119: Step 5 — STOCK STATUS
A120: Use Column L dropdown (Active/Inactive) to toggle items. Inactive rows contribute ZERO to profit, loss, and analytics totals — ideal for recalled, damaged, or discontinued stock.

Sheet 7. Overseas orders
A1: KEN JP ANIME FIGURES SHOP
A4: 📦 7. OVERSEAS ORDERS | Rates: 'Exchange Rate'!B5 (PHP→JPY) & E5 (JPY→PHP)
A5: 🔍 FUZZY SEARCH | B5: ⬇ type partial name or ID: | D5: =IF($C$5="","← type above",IFERROR(ROWS(filter($M$8:$M$107,ISNUMBER(SEARCH($C$5,$M$8:$M$107))))&" match(es) found","❌ 0 found")) -> ← type above | E5: View match #: | F5: 1 | G5: =IF($C$5="","— no active search —",IFERROR(INDEX(filter($M$8:$M$107,ISNUMBER(SEARCH($C$5,$M$8:$M$107)),"❌ No Data Found"),VALUE($F$5)),"❌ No Data Found")) -> — no active search — | H5: =IFERROR(IF($G$5="❌ No Data Found","—",IF($G$5="— no active search —","—",INDEX($D$8:$D$107,MATCH($G$5,$M$8:$M$107,0)))),"—") -> — | I5: =IFERROR(IF($G$5="❌ No Data Found","—",IF($G$5="— no active search —","—",INDEX($F$8:$F$107,MATCH($G$5,$M$8:$M$107,0)))),"—") -> — | J5: =IFERROR(IF($G$5="❌ No Data Found","—",IF($G$5="— no active search —","—",INDEX($H$8:$H$107,MATCH($G$5,$M$8:$M$107,0)))),"—") -> — | K5: =IFERROR(IF($G$5="❌ No Data Found","—",IF($G$5="— no active search —","—",INDEX($J$8:$J$107,MATCH($G$5,$M$8:$M$107,0)))),"—") -> — | L5: =IFERROR(IF($G$5="❌ No Data Found","—",IF($G$5="— no active search —","—",INDEX($L$8:$L$107,MATCH($G$5,$M$8:$M$107,0)))),"—") -> —
A7: Product ID | B7: Date of Entry | C7: Transaction Month | D7: Purchase Price (JPY) | E7: Purchase Price (PHP) | F7: Selling Price (PHP) | G7: Selling Price (JPY) | H7: Net Profit (JPY) | I7: Net Profit (PHP) | J7: Net Loss (JPY) | K7: Net Loss (PHP) | L7: Stock Status | M7: SEARCH_KEY (hidden)
C8: =IF(B8="","",TEXT(B8,"mmmm")) | E8: =IF(D8="","",D8*'Exchange Rate'!$E$5) | G8: =IF(F8="","",F8*'Exchange Rate'!$B$5) | H8: =IF(L8="Inactive",0,IF(ISNUMBER(G8)*ISNUMBER(D8),IF(G8>D8,G8-D8,0),0)) -> 0 | I8: =IF(L8="Inactive",0,IF(ISNUMBER(F8)*ISNUMBER(E8),IF(F8>E8,F8-E8,0),0)) -> 0 | J8: =IF(L8="Inactive",0,IF(ISNUMBER(D8)*ISNUMBER(G8),IF(D8>G8,D8-G8,0),0)) -> 0 | K8: =IF(L8="Inactive",0,IF(ISNUMBER(E8)*ISNUMBER(F8),IF(E8>F8,E8-F8,0),0)) -> 0 | L8: Active | M8: =IF(A8="","—",A8&" ("&TEXT(B8,"MM/DD/YYYY")&")") -> —
C9: =IF(B9="","",TEXT(B9,"mmmm")) | E9: =IF(D9="","",D9*'Exchange Rate'!$E$5) | G9: =IF(F9="","",F9*'Exchange Rate'!$B$5) | H9: =IF(L9="Inactive",0,IF(ISNUMBER(G9)*ISNUMBER(D9),IF(G9>D9,G9-D9,0),0)) -> 0 | I9: =IF(L9="Inactive",0,IF(ISNUMBER(F9)*ISNUMBER(E9),IF(F9>E9,F9-E9,0),0)) -> 0 | J9: =IF(L9="Inactive",0,IF(ISNUMBER(D9)*ISNUMBER(G9),IF(D9>G9,D9-G9,0),0)) -> 0 | K9: =IF(L9="Inactive",0,IF(ISNUMBER(E9)*ISNUMBER(F9),IF(E9>F9,E9-F9,0),0)) -> 0 | L9: Active | M9: =IF(A9="","—",A9&" ("&TEXT(B9,"MM/DD/YYYY")&")") -> —
C10: =IF(B10="","",TEXT(B10,"mmmm")) | E10: =IF(D10="","",D10*'Exchange Rate'!$E$5) | G10: =IF(F10="","",F10*'Exchange Rate'!$B$5) | H10: =IF(L10="Inactive",0,IF(ISNUMBER(G10)*ISNUMBER(D10),IF(G10>D10,G10-D10,0),0)) -> 0 | I10: =IF(L10="Inactive",0,IF(ISNUMBER(F10)*ISNUMBER(E10),IF(F10>E10,F10-E10,0),0)) -> 0 | J10: =IF(L10="Inactive",0,IF(ISNUMBER(D10)*ISNUMBER(G10),IF(D10>G10,D10-G10,0),0)) -> 0 | K10: =IF(L10="Inactive",0,IF(ISNUMBER(E10)*ISNUMBER(F10),IF(E10>F10,E10-F10,0),0)) -> 0 | L10: Active | M10: =IF(A10="","—",A10&" ("&TEXT(B10,"MM/DD/YYYY")&")") -> —
C11: =IF(B11="","",TEXT(B11,"mmmm")) | E11: =IF(D11="","",D11*'Exchange Rate'!$E$5) | G11: =IF(F11="","",F11*'Exchange Rate'!$B$5) | H11: =IF(L11="Inactive",0,IF(ISNUMBER(G11)*ISNUMBER(D11),IF(G11>D11,G11-D11,0),0)) -> 0 | I11: =IF(L11="Inactive",0,IF(ISNUMBER(F11)*ISNUMBER(E11),IF(F11>E11,F11-E11,0),0)) -> 0 | J11: =IF(L11="Inactive",0,IF(ISNUMBER(D11)*ISNUMBER(G11),IF(D11>G11,D11-G11,0),0)) -> 0 | K11: =IF(L11="Inactive",0,IF(ISNUMBER(E11)*ISNUMBER(F11),IF(E11>F11,E11-F11,0),0)) -> 0 | L11: Active | M11: =IF(A11="","—",A11&" ("&TEXT(B11,"MM/DD/YYYY")&")") -> —
C12: =IF(B12="","",TEXT(B12,"mmmm")) | E12: =IF(D12="","",D12*'Exchange Rate'!$E$5) | G12: =IF(F12="","",F12*'Exchange Rate'!$B$5) | H12: =IF(L12="Inactive",0,IF(ISNUMBER(G12)*ISNUMBER(D12),IF(G12>D12,G12-D12,0),0)) -> 0 | I12: =IF(L12="Inactive",0,IF(ISNUMBER(F12)*ISNUMBER(E12),IF(F12>E12,F12-E12,0),0)) -> 0 | J12: =IF(L12="Inactive",0,IF(ISNUMBER(D12)*ISNUMBER(G12),IF(D12>G12,D12-G12,0),0)) -> 0 | K12: =IF(L12="Inactive",0,IF(ISNUMBER(E12)*ISNUMBER(F12),IF(E12>F12,E12-F12,0),0)) -> 0 | L12: Active | M12: =IF(A12="","—",A12&" ("&TEXT(B12,"MM/DD/YYYY")&")") -> —
C13: =IF(B13="","",TEXT(B13,"mmmm")) | E13: =IF(D13="","",D13*'Exchange Rate'!$E$5) | G13: =IF(F13="","",F13*'Exchange Rate'!$B$5) | H13: =IF(L13="Inactive",0,IF(ISNUMBER(G13)*ISNUMBER(D13),IF(G13>D13,G13-D13,0),0)) -> 0 | I13: =IF(L13="Inactive",0,IF(ISNUMBER(F13)*ISNUMBER(E13),IF(F13>E13,F13-E13,0),0)) -> 0 | J13: =IF(L13="Inactive",0,IF(ISNUMBER(D13)*ISNUMBER(G13),IF(D13>G13,D13-G13,0),0)) -> 0 | K13: =IF(L13="Inactive",0,IF(ISNUMBER(E13)*ISNUMBER(F13),IF(E13>F13,E13-F13,0),0)) -> 0 | L13: Active | M13: =IF(A13="","—",A13&" ("&TEXT(B13,"MM/DD/YYYY")&")") -> —
C14: =IF(B14="","",TEXT(B14,"mmmm")) | E14: =IF(D14="","",D14*'Exchange Rate'!$E$5) | G14: =IF(F14="","",F14*'Exchange Rate'!$B$5) | H14: =IF(L14="Inactive",0,IF(ISNUMBER(G14)*ISNUMBER(D14),IF(G14>D14,G14-D14,0),0)) -> 0 | I14: =IF(L14="Inactive",0,IF(ISNUMBER(F14)*ISNUMBER(E14),IF(F14>E14,F14-E14,0),0)) -> 0 | J14: =IF(L14="Inactive",0,IF(ISNUMBER(D14)*ISNUMBER(G14),IF(D14>G14,D14-G14,0),0)) -> 0 | K14: =IF(L14="Inactive",0,IF(ISNUMBER(E14)*ISNUMBER(F14),IF(E14>F14,E14-F14,0),0)) -> 0 | L14: Active | M14: =IF(A14="","—",A14&" ("&TEXT(B14,"MM/DD/YYYY")&")") -> —
C15: =IF(B15="","",TEXT(B15,"mmmm")) | E15: =IF(D15="","",D15*'Exchange Rate'!$E$5) | G15: =IF(F15="","",F15*'Exchange Rate'!$B$5) | H15: =IF(L15="Inactive",0,IF(ISNUMBER(G15)*ISNUMBER(D15),IF(G15>D15,G15-D15,0),0)) -> 0 | I15: =IF(L15="Inactive",0,IF(ISNUMBER(F15)*ISNUMBER(E15),IF(F15>E15,F15-E15,0),0)) -> 0 | J15: =IF(L15="Inactive",0,IF(ISNUMBER(D15)*ISNUMBER(G15),IF(D15>G15,D15-G15,0),0)) -> 0 | K15: =IF(L15="Inactive",0,IF(ISNUMBER(E15)*ISNUMBER(F15),IF(E15>F15,E15-F15,0),0)) -> 0 | L15: Active | M15: =IF(A15="","—",A15&" ("&TEXT(B15,"MM/DD/YYYY")&")") -> —
C16: =IF(B16="","",TEXT(B16,"mmmm")) | E16: =IF(D16="","",D16*'Exchange Rate'!$E$5) | G16: =IF(F16="","",F16*'Exchange Rate'!$B$5) | H16: =IF(L16="Inactive",0,IF(ISNUMBER(G16)*ISNUMBER(D16),IF(G16>D16,G16-D16,0),0)) -> 0 | I16: =IF(L16="Inactive",0,IF(ISNUMBER(F16)*ISNUMBER(E16),IF(F16>E16,F16-E16,0),0)) -> 0 | J16: =IF(L16="Inactive",0,IF(ISNUMBER(D16)*ISNUMBER(G16),IF(D16>G16,D16-G16,0),0)) -> 0 | K16: =IF(L16="Inactive",0,IF(ISNUMBER(E16)*ISNUMBER(F16),IF(E16>F16,E16-F16,0),0)) -> 0 | L16: Active | M16: =IF(A16="","—",A16&" ("&TEXT(B16,"MM/DD/YYYY")&")") -> —
C17: =IF(B17="","",TEXT(B17,"mmmm")) | E17: =IF(D17="","",D17*'Exchange Rate'!$E$5) | G17: =IF(F17="","",F17*'Exchange Rate'!$B$5) | H17: =IF(L17="Inactive",0,IF(ISNUMBER(G17)*ISNUMBER(D17),IF(G17>D17,G17-D17,0),0)) -> 0 | I17: =IF(L17="Inactive",0,IF(ISNUMBER(F17)*ISNUMBER(E17),IF(F17>E17,F17-E17,0),0)) -> 0 | J17: =IF(L17="Inactive",0,IF(ISNUMBER(D17)*ISNUMBER(G17),IF(D17>G17,D17-G17,0),0)) -> 0 | K17: =IF(L17="Inactive",0,IF(ISNUMBER(E17)*ISNUMBER(F17),IF(E17>F17,E17-F17,0),0)) -> 0 | L17: Active | M17: =IF(A17="","—",A17&" ("&TEXT(B17,"MM/DD/YYYY")&")") -> —
C18: =IF(B18="","",TEXT(B18,"mmmm")) | E18: =IF(D18="","",D18*'Exchange Rate'!$E$5) | G18: =IF(F18="","",F18*'Exchange Rate'!$B$5) | H18: =IF(L18="Inactive",0,IF(ISNUMBER(G18)*ISNUMBER(D18),IF(G18>D18,G18-D18,0),0)) -> 0 | I18: =IF(L18="Inactive",0,IF(ISNUMBER(F18)*ISNUMBER(E18),IF(F18>E18,F18-E18,0),0)) -> 0 | J18: =IF(L18="Inactive",0,IF(ISNUMBER(D18)*ISNUMBER(G18),IF(D18>G18,D18-G18,0),0)) -> 0 | K18: =IF(L18="Inactive",0,IF(ISNUMBER(E18)*ISNUMBER(F18),IF(E18>F18,E18-F18,0),0)) -> 0 | L18: Active | M18: =IF(A18="","—",A18&" ("&TEXT(B18,"MM/DD/YYYY")&")") -> —
C19: =IF(B19="","",TEXT(B19,"mmmm")) | E19: =IF(D19="","",D19*'Exchange Rate'!$E$5) | G19: =IF(F19="","",F19*'Exchange Rate'!$B$5) | H19: =IF(L19="Inactive",0,IF(ISNUMBER(G19)*ISNUMBER(D19),IF(G19>D19,G19-D19,0),0)) -> 0 | I19: =IF(L19="Inactive",0,IF(ISNUMBER(F19)*ISNUMBER(E19),IF(F19>E19,F19-E19,0),0)) -> 0 | J19: =IF(L19="Inactive",0,IF(ISNUMBER(D19)*ISNUMBER(G19),IF(D19>G19,D19-G19,0),0)) -> 0 | K19: =IF(L19="Inactive",0,IF(ISNUMBER(E19)*ISNUMBER(F19),IF(E19>F19,E19-F19,0),0)) -> 0 | L19: Active | M19: =IF(A19="","—",A19&" ("&TEXT(B19,"MM/DD/YYYY")&")") -> —
... C107: =IF(B107="","",TEXT(B107,"mmmm")) | E107: =IF(D107="","",D107*'Exchange Rate'!$E$5) | G107: =IF(F107="","",F107*'Exchange Rate'!$B$5) | H107: =IF(L107="Inactive",0,IF(ISNUMBER(G107)*ISNUMBER(D107),IF(G107>D107,G107-D107,0),0)) -> 0 | I107: =IF(L107="Inactive",0,IF(ISNUMBER(F107)*ISNUMBER(E107),IF(F107>E107,F107-E107,0),0)) -> 0 | J107: =IF(L107="Inactive",0,IF(ISNUMBER(D107)*ISNUMBER(G107),IF(D107>G107,D107-G107,0),0)) -> 0 | K107: =IF(L107="Inactive",0,IF(ISNUMBER(E107)*ISNUMBER(F107),IF(E107>F107,E107-F107,0),0)) -> 0 | L107: Active | M107: =IF(A107="","—",A107&" ("&TEXT(B107,"MM/DD/YYYY")&")") -> —
A108: TOTAL CATEGORY VALUE | D108: =SUM(D8:D107) -> 0 | E108: =SUM(E8:E107) -> 0 | F108: =SUM(F8:F107) -> 0 | G108: =SUM(G8:G107) -> 0 | H108: =SUM(H8:H107) -> 0 | I108: =SUM(I8:I107) -> 0 | J108: =SUM(J8:J107) -> 0 | K108: =SUM(K8:K107) -> 0 | L108: =SUM(L8:L107) -> 0
A110: 📋 USER GUIDE & OPERATIONAL INSTRUCTIONS
A111: Step 1 — DATA ENTRY
A112: Input rows sequentially. Type directly into Col D (Purchase JPY) and Col F (Selling PHP) ONLY. All other columns auto-calculate. Yellow cells = manual entry. White cells = formulas.
A113: Step 2 — DUPLICATE IDs
A114: If tracking duplicate items, check the QUICK-VIEW bar (Row 5). A ⚠️ alert fires when the same Product ID appears more than once. Use the 'Date of Entry' (Col B) timestamp in the lookup to immediately distinguish which entry is which.
A115: Step 3 — ANALYTICS FILTER
A116: Toggle the Analytics view on the '9. Overall Analytics' sheet using the timeframe filter (D2) to review Weekly, Monthly, or Annual financial health variations.
A117: Step 4 — EXCHANGE RATES
A118: Never manually edit currency columns. To update rates, go to the 'Exchange Rate' sheet and edit ONLY cells B5 (PHP→JPY) or E5 (JPY→PHP). All values across the workbook update instantly.
A119: Step 5 — STOCK STATUS
A120: Use Column L dropdown (Active/Inactive) to toggle items. Inactive rows contribute ZERO to profit, loss, and analytics totals — ideal for recalled, damaged, or discontinued stock.

Sheet 8. Overall Expense Sheet
A1: KEN JP ANIME FIGURES SHOP
A4: 💰 OVERALL EXPENSE SHEET | Tracks all operational costs across all channels
A5: 🔍 FUZZY SEARCH | B5: ⬇ type partial name or ID: | D5: =IF($C$5="","← type above",IFERROR(ROWS(filter($K$8:$K$107,ISNUMBER(SEARCH($C$5,$K$8:$K$107))))&" match(es) found","❌ 0 found")) -> ← type above | E5: View match #: | F5: 1 | G5: =IF($C$5="","— no active search —",IFERROR(INDEX(filter($K$8:$K$107,ISNUMBER(SEARCH($C$5,$K$8:$K$107)),"❌ No Data Found"),VALUE($F$5)),"❌ No Data Found")) -> — no active search — | H5: =IFERROR(IF($G$5="❌ No Data Found","—",IF($G$5="— no active search —","—",INDEX($F$8:$F$107,MATCH($G$5,$K$8:$K$107,0)))),"—") -> — | I5: =IFERROR(IF($G$5="❌ No Data Found","—",IF($G$5="— no active search —","—",INDEX($G$8:$G$107,MATCH($G$5,$K$8:$K$107,0)))),"—") -> — | J5: =IFERROR(IF($G$5="❌ No Data Found","—",IF($G$5="— no active search —","—",INDEX($H$8:$H$107,MATCH($G$5,$K$8:$K$107,0)))),"—") -> — | K5: =IFERROR(IF($G$5="❌ No Data Found","—",IF($G$5="— no active search —","—",INDEX($I$8:$I$107,MATCH($G$5,$K$8:$K$107,0)))),"—") -> —
A7: Expense ID | B7: Date | C7: Month | D7: Category | E7: Description | F7: Amount (JPY) | G7: Amount (PHP) | H7: Payment Method | I7: Status | J7: Notes | K7: SEARCH_KEY (hidden)
C8: =IF(B8="","",TEXT(B8,"mmmm")) | G8: =IF(F8="","",F8*'Exchange Rate'!$E$5) | K8: =IF(A8="","—",A8&" ("&TEXT(B8,"MM/DD/YYYY")&")") -> —
C9: =IF(B9="","",TEXT(B9,"mmmm")) | G9: =IF(F9="","",F9*'Exchange Rate'!$E$5) | K9: =IF(A9="","—",A9&" ("&TEXT(B9,"MM/DD/YYYY")&")") -> —
C10: =IF(B10="","",TEXT(B10,"mmmm")) | G10: =IF(F10="","",F10*'Exchange Rate'!$E$5) | K10: =IF(A10="","—",A10&" ("&TEXT(B10,"MM/DD/YYYY")&")") -> —
C11: =IF(B11="","",TEXT(B11,"mmmm")) | G11: =IF(F11="","",F11*'Exchange Rate'!$E$5) | K11: =IF(A11="","—",A11&" ("&TEXT(B11,"MM/DD/YYYY")&")") -> —
C12: =IF(B12="","",TEXT(B12,"mmmm")) | G12: =IF(F12="","",F12*'Exchange Rate'!$E$5) | K12: =IF(A12="","—",A12&" ("&TEXT(B12,"MM/DD/YYYY")&")") -> —
C13: =IF(B13="","",TEXT(B13,"mmmm")) | G13: =IF(F13="","",F13*'Exchange Rate'!$E$5) | K13: =IF(A13="","—",A13&" ("&TEXT(B13,"MM/DD/YYYY")&")") -> —
C14: =IF(B14="","",TEXT(B14,"mmmm")) | G14: =IF(F14="","",F14*'Exchange Rate'!$E$5) | K14: =IF(A14="","—",A14&" ("&TEXT(B14,"MM/DD/YYYY")&")") -> —
C15: =IF(B15="","",TEXT(B15,"mmmm")) | G15: =IF(F15="","",F15*'Exchange Rate'!$E$5) | K15: =IF(A15="","—",A15&" ("&TEXT(B15,"MM/DD/YYYY")&")") -> —
C16: =IF(B16="","",TEXT(B16,"mmmm")) | G16: =IF(F16="","",F16*'Exchange Rate'!$E$5) | K16: =IF(A16="","—",A16&" ("&TEXT(B16,"MM/DD/YYYY")&")") -> —
C17: =IF(B17="","",TEXT(B17,"mmmm")) | G17: =IF(F17="","",F17*'Exchange Rate'!$E$5) | K17: =IF(A17="","—",A17&" ("&TEXT(B17,"MM/DD/YYYY")&")") -> —
C18: =IF(B18="","",TEXT(B18,"mmmm")) | G18: =IF(F18="","",F18*'Exchange Rate'!$E$5) | K18: =IF(A18="","—",A18&" ("&TEXT(B18,"MM/DD/YYYY")&")") -> —
C19: =IF(B19="","",TEXT(B19,"mmmm")) | G19: =IF(F19="","",F19*'Exchange Rate'!$E$5) | K19: =IF(A19="","—",A19&" ("&TEXT(B19,"MM/DD/YYYY")&")") -> —
... C107: =IF(B107="","",TEXT(B107,"mmmm")) | G107: =IF(F107="","",F107*'Exchange Rate'!$E$5) | K107: =IF(A107="","—",A107&" ("&TEXT(B107,"MM/DD/YYYY")&")") -> —
A108: TOTAL EXPENSES | F108: =SUM(F8:F107) -> 0 | G108: =SUM(G8:G107) -> 0

Sheet 9. Overall Analytics
A1: KEN JP ANIME FIGURES SHOP — EXECUTIVE ANALYTICS DASHBOARD
A2: 📅 Analytics Reporting Month: | B2: Full Year Summary | D2: 📊 Analytics Timeframe: | E2: Monthly View
A4: 📊 CONSOLIDATED KPI MATRIX — SHEET-BY-SHEET PERFORMANCE (via INDIRECT) | F4: 🎯 REAL-TIME BUSINESS INTELLIGENCE METRICS
A5: Sheet / Category | B5: Purchase Vol (JPY) | C5: Net Profit (JPY) | D5: Net Losses (JPY) | F5: CARD A — Overall Business Profit Margin (%)
A6: 1. Anime Figures | B6: =IFERROR(IF($B$2="Full Year Summary",INDIRECT("'"&$A6&"'!D108"),IFERROR(SUMIFS(INDIRECT("'"&$A6&"'!D8:D107"),INDIRECT("'"&$A6&"'!C8:C107"),$B$2),0)),0) -> 0 | C6: =IFERROR(IF($B$2="Full Year Summary",INDIRECT("'"&$A6&"'!H108"),IFERROR(SUMIFS(INDIRECT("'"&$A6&"'!H8:H107"),INDIRECT("'"&$A6&"'!C8:C107"),$B$2),0)),0) -> 0 | D6: =IFERROR(IF($B$2="Full Year Summary",INDIRECT("'"&$A6&"'!J108"),IFERROR(SUMIFS(INDIRECT("'"&$A6&"'!J8:J107"),INDIRECT("'"&$A6&"'!C8:C107"),$B$2),0)),0) -> 0 | F6: =IFERROR(C15/(B15+C15),"No Data") -> No Data
A7: 2. Mercari and Online store | B7: =IFERROR(IF($B$2="Full Year Summary",INDIRECT("'"&$A7&"'!D108"),IFERROR(SUMIFS(INDIRECT("'"&$A7&"'!D8:D107"),INDIRECT("'"&$A7&"'!C8:C107"),$B$2),0)),0) -> 0 | C7: =IFERROR(IF($B$2="Full Year Summary",INDIRECT("'"&$A7&"'!H108"),IFERROR(SUMIFS(INDIRECT("'"&$A7&"'!H8:H107"),INDIRECT("'"&$A7&"'!C8:C107"),$B$2),0)),0) -> 0 | D7: =IFERROR(IF($B$2="Full Year Summary",INDIRECT("'"&$A7&"'!J108"),IFERROR(SUMIFS(INDIRECT("'"&$A7&"'!J8:J107"),INDIRECT("'"&$A7&"'!C8:C107"),$B$2),0)),0) -> 0
A8: 3. Onhand orders JPY | B8: =IFERROR(IF($B$2="Full Year Summary",INDIRECT("'"&$A8&"'!D108"),IFERROR(SUMIFS(INDIRECT("'"&$A8&"'!D8:D107"),INDIRECT("'"&$A8&"'!C8:C107"),$B$2),0)),0) -> 0 | C8: =IFERROR(IF($B$2="Full Year Summary",INDIRECT("'"&$A8&"'!H108"),IFERROR(SUMIFS(INDIRECT("'"&$A8&"'!H8:H107"),INDIRECT("'"&$A8&"'!C8:C107"),$B$2),0)),0) -> 0 | D8: =IFERROR(IF($B$2="Full Year Summary",INDIRECT("'"&$A8&"'!J108"),IFERROR(SUMIFS(INDIRECT("'"&$A8&"'!J8:J107"),INDIRECT("'"&$A8&"'!C8:C107"),$B$2),0)),0) -> 0
A9: 4. Live Selling Orders | B9: =IFERROR(IF($B$2="Full Year Summary",INDIRECT("'"&$A9&"'!D108"),IFERROR(SUMIFS(INDIRECT("'"&$A9&"'!D8:D107"),INDIRECT("'"&$A9&"'!C8:C107"),$B$2),0)),0) -> 0 | C9: =IFERROR(IF($B$2="Full Year Summary",INDIRECT("'"&$A9&"'!H108"),IFERROR(SUMIFS(INDIRECT("'"&$A9&"'!H8:H107"),INDIRECT("'"&$A9&"'!C8:C107"),$B$2),0)),0) -> 0 | D9: =IFERROR(IF($B$2="Full Year Summary",INDIRECT("'"&$A9&"'!J108"),IFERROR(SUMIFS(INDIRECT("'"&$A9&"'!J8:J107"),INDIRECT("'"&$A9&"'!C8:C107"),$B$2),0)),0) -> 0 | F9: Formula: Total Profit ÷ (Total Purchase + Total Profit)
A10: 5. On hand orders PHP | B10: =IFERROR(IF($B$2="Full Year Summary",INDIRECT("'"&$A10&"'!D108"),IFERROR(SUMIFS(INDIRECT("'"&$A10&"'!D8:D107"),INDIRECT("'"&$A10&"'!C8:C107"),$B$2),0)),0) -> 0 | C10: =IFERROR(IF($B$2="Full Year Summary",INDIRECT("'"&$A10&"'!H108"),IFERROR(SUMIFS(INDIRECT("'"&$A10&"'!H8:H107"),INDIRECT("'"&$A10&"'!C8:C107"),$B$2),0)),0) -> 0 | D10: =IFERROR(IF($B$2="Full Year Summary",INDIRECT("'"&$A10&"'!J108"),IFERROR(SUMIFS(INDIRECT("'"&$A10&"'!J8:J107"),INDIRECT("'"&$A10&"'!C8:C107"),$B$2),0)),0) -> 0 | F10: CARD B — Highest-Performing Category (by Net Profit)
A11: 6. Pre Orders | B11: =IFERROR(IF($B$2="Full Year Summary",INDIRECT("'"&$A11&"'!D108"),IFERROR(SUMIFS(INDIRECT("'"&$A11&"'!D8:D107"),INDIRECT("'"&$A11&"'!C8:C107"),$B$2),0)),0) -> 0 | C11: =IFERROR(IF($B$2="Full Year Summary",INDIRECT("'"&$A11&"'!H108"),IFERROR(SUMIFS(INDIRECT("'"&$A11&"'!H8:H107"),INDIRECT("'"&$A11&"'!C8:C107"),$B$2),0)),0) -> 0 | D11: =IFERROR(IF($B$2="Full Year Summary",INDIRECT("'"&$A11&"'!J108"),IFERROR(SUMIFS(INDIRECT("'"&$A11&"'!J8:J107"),INDIRECT("'"&$A11&"'!C8:C107"),$B$2),0)),0) -> 0 | F11: =IFERROR(INDEX($A$6:$A$14,MATCH(MAX($C$6:$C$14),$C$6:$C$14,0)),"No Data") -> 1. Anime Figures
A12: 7. Overseas orders | B12: =IFERROR(IF($B$2="Full Year Summary",INDIRECT("'"&$A12&"'!D108"),IFERROR(SUMIFS(INDIRECT("'"&$A12&"'!D8:D107"),INDIRECT("'"&$A12&"'!C8:C107"),$B$2),0)),0) -> 0 | C12: =IFERROR(IF($B$2="Full Year Summary",INDIRECT("'"&$A12&"'!H108"),IFERROR(SUMIFS(INDIRECT("'"&$A12&"'!H8:H107"),INDIRECT("'"&$A12&"'!C8:C107"),$B$2),0)),0) -> 0 | D12: =IFERROR(IF($B$2="Full Year Summary",INDIRECT("'"&$A12&"'!J108"),IFERROR(SUMIFS(INDIRECT("'"&$A12&"'!J8:J107"),INDIRECT("'"&$A12&"'!C8:C107"),$B$2),0)),0) -> 0
A13: 8. Overall Expense Sheet | B13: =IFERROR(IF($B$2="Full Year Summary",INDIRECT("'"&$A13&"'!F108"),IFERROR(SUMIFS(INDIRECT("'"&$A13&"'!F8:F107"),INDIRECT("'"&$A13&"'!C8:C107"),$B$2),0)),0) -> 0 | C13: =IFERROR(IF($B$2="Full Year Summary",INDIRECT("'"&$A13&"'!F108"),IFERROR(SUMIFS(INDIRECT("'"&$A13&"'!F8:F107"),INDIRECT("'"&$A13&"'!C8:C107"),$B$2),0)),0) -> 0 | D13: =IFERROR(IF($B$2="Full Year Summary",INDIRECT("'"&$A13&"'!F108"),IFERROR(SUMIFS(INDIRECT("'"&$A13&"'!F8:F107"),INDIRECT("'"&$A13&"'!C8:C107"),$B$2),0)),0) -> 0
A14: 10. Restock | B14: =IFERROR(IF($B$2="Full Year Summary",INDIRECT("'"&$A14&"'!D108"),IFERROR(SUMIFS(INDIRECT("'"&$A14&"'!D8:D107"),INDIRECT("'"&$A14&"'!C8:C107"),$B$2),0)),0) -> 0 | C14: =IFERROR(IF($B$2="Full Year Summary",INDIRECT("'"&$A14&"'!H108"),IFERROR(SUMIFS(INDIRECT("'"&$A14&"'!H8:H107"),INDIRECT("'"&$A14&"'!C8:C107"),$B$2),0)),0) -> 0 | D14: =IFERROR(IF($B$2="Full Year Summary",INDIRECT("'"&$A14&"'!J108"),IFERROR(SUMIFS(INDIRECT("'"&$A14&"'!J8:J107"),INDIRECT("'"&$A14&"'!C8:C107"),$B$2),0)),0) -> 0 | F14: Formula: INDEX/MATCH on MAX profit across all tracked categories
A15: GRAND TOTAL | B15: =SUM(B6:B14) -> 0 | C15: =SUM(C6:C14) -> 0 | D15: =SUM(D6:D14) -> 0 | F15: CARD C — Overall Net P&L Position (JPY)
F16: =C15-D15 -> 0
A19: 📈 DYNAMIC CHART FEED TABLE — Drives Visual Below (Timeframe-Controlled via E2)
A20: Period Label | B20: Purchase Vol (JPY) ← Col D | C20: Net Profit (JPY) ← Col H | D20: Net Losses (JPY) ← Col J
A21: =IF($E$2="Monthly View","January",IF($E$2="Weekly View","Week "&(ROW()-20),YEAR(TODAY())-12+ROW()-19)) -> January | B21: =IF($E$2="Monthly View",IFERROR(SUMIFS('1. Anime Figures'!D$8:D$107,'1. Anime Figures'!C$8:C$107,A21),0)+IFERROR(SUMIFS('2. Mercari and Online store'!D$8:D$107,'2. Mercari and Online store'!C$8:C$107,A21),0)+IFERROR(SUMIFS('3. Onhand orders JPY'!D$8:D$107,'3. Onhand orders JPY'!C$8:C$107,A21),0)+IFERROR(SUMIFS('4. Live Selling Orders'!D$8:D$107,'4. Live Selling Orders'!C$8:C$107,A21),0)+IFERROR(SUMIFS('5. On hand orders PHP'!D$8:D$107,'5. On hand orders PHP'!C$8:C$107,A21),0)+IFERROR(SUMIFS('6. Pre Orders'!D$8:D$107,'6. Pre Orders'!C$8:C$107,A21),0)+IFERROR(SUMIFS('7. Overseas orders'!D$8:D$107,'7. Overseas orders'!C$8:C$107,A21),0)+IFERROR(SUMIFS('10. Restock'!D$8:D$107,'10. Restock'!C$8:C$107,A21),0),IF($E$2="Weekly View",IFERROR(SUMPRODUCT(('1. Anime Figures'!D$8:D$107)*(IFERROR(WEEKNUM('1. Anime Figures'!B$8:B$107,1),0)=ROW()-19)),0)+IFERROR(SUMPRODUCT(('2. Mercari and Online store'!D$8:D$107)*(IFERROR(WEEKNUM('2. Mercari and Online store'!B$8:B$107,1),0)=ROW()-19)),0)+IFERROR(SUMPRODUCT(('3. Onhand orders JPY'!D$8:D$107)*(IFERROR(WEEKNUM('3. Onhand orders JPY'!B$8:B$107,1),0)=ROW()-19)),0)+IFERROR(SUMPRODUCT(('4. Live Selling Orders'!D$8:D$107)*(IFERROR(WEEKNUM('4. Live Selling Orders'!B$8:B$107,1),0)=ROW()-19)),0)+IFERROR(SUMPRODUCT(('5. On hand orders PHP'!D$8:D$107)*(IFERROR(WEEKNUM('5. On hand orders PHP'!B$8:B$107,1),0)=ROW()-19)),0)+IFERROR(SUMPRODUCT(('6. Pre Orders'!D$8:D$107)*(IFERROR(WEEKNUM('6. Pre Orders'!B$8:B$107,1),0)=ROW()-19)),0)+IFERROR(SUMPRODUCT(('7. Overseas orders'!D$8:D$107)*(IFERROR(WEEKNUM('7. Overseas orders'!B$8:B$107,1),0)=ROW()-19)),0)+IFERROR(SUMPRODUCT(('10. Restock'!D$8:D$107)*(IFERROR(WEEKNUM('10. Restock'!B$8:B$107,1),0)=ROW()-19)),0),IFERROR(SUMPRODUCT(('1. Anime Figures'!D$8:D$107)*(IFERROR(YEAR('1. Anime Figures'!B$8:B$107),0)=(YEAR(TODAY())-12+ROW()-19))),0)+IFERROR(SUMPRODUCT(('2. Mercari and Online store'!D$8:D$107)*(IFERROR(YEAR('2. Mercari and Online store'!B$8:B$107),0)=(YEAR(TODAY())-12+ROW()-19))),0)+IFERROR(SUMPRODUCT(('3. Onhand orders JPY'!D$8:D$107)*(IFERROR(YEAR('3. Onhand orders JPY'!B$8:B$107),0)=(YEAR(TODAY())-12+ROW()-19))),0)+IFERROR(SUMPRODUCT(('4. Live Selling Orders'!D$8:D$107)*(IFERROR(YEAR('4. Live Selling Orders'!B$8:B$107),0)=(YEAR(TODAY())-12+ROW()-19))),0)+IFERROR(SUMPRODUCT(('5. On hand orders PHP'!D$8:D$107)*(IFERROR(YEAR('5. On hand orders PHP'!B$8:B$107),0)=(YEAR(TODAY())-12+ROW()-19))),0)+IFERROR(SUMPRODUCT(('6. Pre Orders'!D$8:D$107)*(IFERROR(YEAR('6. Pre Orders'!B$8:B$107),0)=(YEAR(TODAY())-12+ROW()-19))),0)+IFERROR(SUMPRODUCT(('7. Overseas orders'!D$8:D$107)*(IFERROR(YEAR('7. Overseas orders'!B$8:B$107),0)=(YEAR(TODAY())-12+ROW()-19))),0)+IFERROR(SUMPRODUCT(('10. Restock'!D$8:D$107)*(IFERROR(YEAR('10. Restock'!B$8:B$107),0)=(YEAR(TODAY())-12+ROW()-19))),0))) -> 0 | C21: =IF($E$2="Monthly View",IFERROR(SUMIFS('1. Anime Figures'!H$8:H$107,'1. Anime Figures'!C$8:C$107,A21),0)+IFERROR(SUMIFS('2. Mercari and Online store'!H$8:H$107,'2. Mercari and Online store'!C$8:C$107,A21),0)+IFERROR(SUMIFS('3. Onhand orders JPY'!H$8:H$107,'3. Onhand orders JPY'!C$8:C$107,A21),0)+IFERROR(SUMIFS('4. Live Selling Orders'!H$8:H$107,'4. Live Selling Orders'!C$8:C$107,A21),0)+IFERROR(SUMIFS('5. On hand orders PHP'!H$8:H$107,'5. On hand orders PHP'!C$8:C$107,A21),0)+IFERROR(SUMIFS('6. Pre Orders'!H$8:H$107,'6. Pre Orders'!C$8:C$107,A21),0)+IFERROR(SUMIFS('7. Overseas orders'!H$8:H$107,'7. Overseas orders'!C$8:C$107,A21),0)+IFERROR(SUMIFS('10. Restock'!H$8:H$107,'10. Restock'!C$8:C$107,A21),0),IF($E$2="Weekly View",IFERROR(SUMPRODUCT(('1. Anime Figures'!H$8:H$107)*(IFERROR(WEEKNUM('1. Anime Figures'!B$8:B$107,1),0)=ROW()-19)),0)+IFERROR(SUMPRODUCT(('2. Mercari and Online store'!H$8:H$107)*(IFERROR(WEEKNUM('2. Mercari and Online store'!B$8:B$107,1),0)=ROW()-19)),0)+IFERROR(SUMPRODUCT(('3. Onhand orders JPY'!H$8:H$107)*(IFERROR(WEEKNUM('3. Onhand orders JPY'!B$8:B$107,1),0)=ROW()-19)),0)+IFERROR(SUMPRODUCT(('4. Live Selling Orders'!H$8:H$107)*(IFERROR(WEEKNUM('4. Live Selling Orders'!B$8:B$107,1),0)=ROW()-19)),0)+IFERROR(SUMPRODUCT(('5. On hand orders PHP'!H$8:H$107)*(IFERROR(WEEKNUM('5. On hand orders PHP'!B$8:B$107,1),0)=ROW()-19)),0)+IFERROR(SUMPRODUCT(('6. Pre Orders'!H$8:H$107)*(IFERROR(WEEKNUM('6. Pre Orders'!B$8:B$107,1),0)=ROW()-19)),0)+IFERROR(SUMPRODUCT(('7. Overseas orders'!H$8:H$107)*(IFERROR(WEEKNUM('7. Overseas orders'!B$8:B$107,1),0)=ROW()-19)),0)+IFERROR(SUMPRODUCT(('10. Restock'!H$8:H$107)*(IFERROR(WEEKNUM('10. Restock'!B$8:B$107,1),0)=ROW()-19)),0),IFERROR(SUMPRODUCT(('1. Anime Figures'!H$8:H$107)*(IFERROR(YEAR('1. Anime Figures'!B$8:B$107),0)=(YEAR(TODAY())-12+ROW()-19))),0)+IFERROR(SUMPRODUCT(('2. Mercari and Online store'!H$8:H$107)*(IFERROR(YEAR('2. Mercari and Online store'!B$8:B$107),0)=(YEAR(TODAY())-12+ROW()-19))),0)+IFERROR(SUMPRODUCT(('3. Onhand orders JPY'!H$8:H$107)*(IFERROR(YEAR('3. Onhand orders JPY'!B$8:B$107),0)=(YEAR(TODAY())-12+ROW()-19))),0)+IFERROR(SUMPRODUCT(('4. Live Selling Orders'!H$8:H$107)*(IFERROR(YEAR('4. Live Selling Orders'!B$8:B$107),0)=(YEAR(TODAY())-12+ROW()-19))),0)+IFERROR(SUMPRODUCT(('5. On hand orders PHP'!H$8:H$107)*(IFERROR(YEAR('5. On hand orders PHP'!B$8:B$107),0)=(YEAR(TODAY())-12+ROW()-19))),0)+IFERROR(SUMPRODUCT(('6. Pre Orders'!H$8:H$107)*(IFERROR(YEAR('6. Pre Orders'!B$8:B$107),0)=(YEAR(TODAY())-12+ROW()-19))),0)+IFERROR(SUMPRODUCT(('7. Overseas orders'!H$8:H$107)*(IFERROR(YEAR('7. Overseas orders'!B$8:B$107),0)=(YEAR(TODAY())-12+ROW()-19))),0)+IFERROR(SUMPRODUCT(('10. Restock'!H$8:H$107)*(IFERROR(YEAR('10. Restock'!B$8:B$107),0)=(YEAR(TODAY())-12+ROW()-19))),0))) -> 0 | D21: =IF($E$2="Monthly View",IFERROR(SUMIFS('1. Anime Figures'!J$8:J$107,'1. Anime Figures'!C$8:C$107,A21),0)+IFERROR(SUMIFS('2. Mercari and Online store'!J$8:J$107,'2. Mercari and Online store'!C$8:C$107,A21),0)+IFERROR(SUMIFS('3. Onhand orders JPY'!J$8:J$107,'3. Onhand orders JPY'!C$8:C$107,A21),0)+IFERROR(SUMIFS('4. Live Selling Orders'!J$8:J$107,'4. Live Selling Orders'!C$8:C$107,A21),0)+IFERROR(SUMIFS('5. On hand orders PHP'!J$8:J$107,'5. On hand orders PHP'!C$8:C$107,A21),0)+IFERROR(SUMIFS('6. Pre Orders'!J$8:J$107,'6. Pre Orders'!C$8:C$107,A21),0)+IFERROR(SUMIFS('7. Overseas orders'!J$8:J$107,'7. Overseas orders'!C$8:C$107,A21),0)+IFERROR(SUMIFS('10. Restock'!J$8:J$107,'10. Restock'!C$8:C$107,A21),0),IF($E$2="Weekly View",IFERROR(SUMPRODUCT(('1. Anime Figures'!J$8:J$107)*(IFERROR(WEEKNUM('1. Anime Figures'!B$8:B$107,1),0)=ROW()-19)),0)+IFERROR(SUMPRODUCT(('2. Mercari and Online store'!J$8:J$107)*(IFERROR(WEEKNUM('2. Mercari and Online store'!B$8:B$107,1),0)=ROW()-19)),0)+IFERROR(SUMPRODUCT(('3. Onhand orders JPY'!J$8:J$107)*(IFERROR(WEEKNUM('3. Onhand orders JPY'!B$8:B$107,1),0)=ROW()-19)),0)+IFERROR(SUMPRODUCT(('4. Live Selling Orders'!J$8:J$107)*(IFERROR(WEEKNUM('4. Live Selling Orders'!B$8:B$107,1),0)=ROW()-19)),0)+IFERROR(SUMPRODUCT(('5. On hand orders PHP'!J$8:J$107)*(IFERROR(WEEKNUM('5. On hand orders PHP'!B$8:B$107,1),0)=ROW()-19)),0)+IFERROR(SUMPRODUCT(('6. Pre Orders'!J$8:J$107)*(IFERROR(WEEKNUM('6. Pre Orders'!B$8:B$107,1),0)=ROW()-19)),0)+IFERROR(SUMPRODUCT(('7. Overseas orders'!J$8:J$107)*(IFERROR(WEEKNUM('7. Overseas orders'!B$8:B$107,1),0)=ROW()-19)),0)+IFERROR(SUMPRODUCT(('10. Restock'!J$8:J$107)*(IFERROR(WEEKNUM('10. Restock'!B$8:B$107,1),0)=ROW()-19)),0),IFERROR(SUMPRODUCT(('1. Anime Figures'!J$8:J$107)*(IFERROR(YEAR('1. Anime Figures'!B$8:B$107),0)=(YEAR(TODAY())-12+ROW()-19))),0)+IFERROR(SUMPRODUCT(('2. Mercari and Online store'!J$8:J$107)*(IFERROR(YEAR('2. Mercari and Online store'!B$8:B$107),0)=(YEAR(TODAY())-12+ROW()-19))),0)+IFERROR(SUMPRODUCT(('3. Onhand orders JPY'!J$8:J$107)*(IFERROR(YEAR('3. Onhand orders JPY'!B$8:B$107),0)=(YEAR(TODAY())-12+ROW()-19))),0)+IFERROR(SUMPRODUCT(('4. Live Selling Orders'!J$8:J$107)*(IFERROR(YEAR('4. Live Selling Orders'!B$8:B$107),0)=(YEAR(TODAY())-12+ROW()-19))),0)+IFERROR(SUMPRODUCT(('5. On hand orders PHP'!J$8:J$107)*(IFERROR(YEAR('5. On hand orders PHP'!B$8:B$107),0)=(YEAR(TODAY())-12+ROW()-19))),0)+IFERROR(SUMPRODUCT(('6. Pre Orders'!J$8:J$107)*(IFERROR(YEAR('6. Pre Orders'!B$8:B$107),0)=(YEAR(TODAY())-12+ROW()-19))),0)+IFERROR(SUMPRODUCT(('7. Overseas orders'!J$8:J$107)*(IFERROR(YEAR('7. Overseas orders'!B$8:B$107),0)=(YEAR(TODAY())-12+ROW()-19))),0)+IFERROR(SUMPRODUCT(('10. Restock'!J$8:J$107)*(IFERROR(YEAR('10. Restock'!B$8:B$107),0)=(YEAR(TODAY())-12+ROW()-19))),0))) -> 0
A22: =IF($E$2="Monthly View","February",IF($E$2="Weekly View","Week "&(ROW()-20),YEAR(TODAY())-12+ROW()-19)) -> February | B22: =IF($E$2="Monthly View",IFERROR(SUMIFS('1. Anime Figures'!D$8:D$107,'1. Anime Figures'!C$8:C$107,A22),0)+IFERROR(SUMIFS('2. Mercari and Online store'!D$8:D$107,'2. Mercari and Online store'!C$8:C$107,A22),0)+IFERROR(SUMIFS('3. Onhand orders JPY'!D$8:D$107,'3. Onhand orders JPY'!C$8:C$107,A22),0)+IFERROR(SUMIFS('4. Live Selling Orders'!D$8:D$107,'4. Live Selling Orders'!C$8:C$107,A22),0)+IFERROR(SUMIFS('5. On hand orders PHP'!D$8:D$107,'5. On hand orders PHP'!C$8:C$107,A22),0)+IFERROR(SUMIFS('6. Pre Orders'!D$8:D$107,'6. Pre Orders'!C$8:C$107,A22),0)+IFERROR(SUMIFS('7. Overseas orders'!D$8:D$107,'7. Overseas orders'!C$8:C$107,A22),0)+IFERROR(SUMIFS('10. Restock'!D$8:D$107,'10. Restock'!C$8:C$107,A22),0),IF($E$2="Weekly View",IFERROR(SUMPRODUCT(('1. Anime Figures'!D$8:D$107)*(IFERROR(WEEKNUM('1. Anime Figures'!B$8:B$107,1),0)=ROW()-19)),0)+IFERROR(SUMPRODUCT(('2. Mercari and Online store'!D$8:D$107)*(IFERROR(WEEKNUM('2. Mercari and Online store'!B$8:B$107,1),0)=ROW()-19)),0)+IFERROR(SUMPRODUCT(('3. Onhand orders JPY'!D$8:D$107)*(IFERROR(WEEKNUM('3. Onhand orders JPY'!B$8:B$107,1),0)=ROW()-19)),0)+IFERROR(SUMPRODUCT(('4. Live Selling Orders'!D$8:D$107)*(IFERROR(WEEKNUM('4. Live Selling Orders'!B$8:B$107,1),0)=ROW()-19)),0)+IFERROR(SUMPRODUCT(('5. On hand orders PHP'!D$8:D$107)*(IFERROR(WEEKNUM('5. On hand orders PHP'!B$8:B$107,1),0)=ROW()-19)),0)+IFERROR(SUMPRODUCT(('6. Pre Orders'!D$8:D$107)*(IFERROR(WEEKNUM('6. Pre Orders'!B$8:B$107,1),0)=ROW()-19)),0)+IFERROR(SUMPRODUCT(('7. Overseas orders'!D$8:D$107)*(IFERROR(WEEKNUM('7. Overseas orders'!B$8:B$107,1),0)=ROW()-19)),0)+IFERROR(SUMPRODUCT(('10. Restock'!D$8:D$107)*(IFERROR(WEEKNUM('10. Restock'!B$8:B$107,1),0)=ROW()-19)),0),IFERROR(SUMPRODUCT(('1. Anime Figures'!D$8:D$107)*(IFERROR(YEAR('1. Anime Figures'!B$8:B$107),0)=(YEAR(TODAY())-12+ROW()-19))),0)+IFERROR(SUMPRODUCT(('2. Mercari and Online store'!D$8:D$107)*(IFERROR(YEAR('2. Mercari and Online store'!B$8:B$107),0)=(YEAR(TODAY())-12+ROW()-19))),0)+IFERROR(SUMPRODUCT(('3. Onhand orders JPY'!D$8:D$107)*(IFERROR(YEAR('3. Onhand orders JPY'!B$8:B$107),0)=(YEAR(TODAY())-12+ROW()-19))),0)+IFERROR(SUMPRODUCT(('4. Live Selling Orders'!D$8:D$107)*(IFERROR(YEAR('4. Live Selling Orders'!B$8:B$107),0)=(YEAR(TODAY())-12+ROW()-19))),0)+IFERROR(SUMPRODUCT(('5. On hand orders PHP'!D$8:D$107)*(IFERROR(YEAR('5. On hand orders PHP'!B$8:B$107),0)=(YEAR(TODAY())-12+ROW()-19))),0)+IFERROR(SUMPRODUCT(('6. Pre Orders'!D$8:D$107)*(IFERROR(YEAR('6. Pre Orders'!B$8:B$107),0)=(YEAR(TODAY())-12+ROW()-19))),0)+IFERROR(SUMPRODUCT(('7. Overseas orders'!D$8:D$107)*(IFERROR(YEAR('7. Overseas orders'!B$8:B$107),0)=(YEAR(TODAY())-12+ROW()-19))),0)+IFERROR(SUMPRODUCT(('10. Restock'!D$8:D$107)*(IFERROR(YEAR('10. Restock'!B$8:B$107),0)=(YEAR(TODAY())-12+ROW()-19))),0))) -> 0 | C22: =IF($E$2="Monthly View",IFERROR(SUMIFS('1. Anime Figures'!H$8:H$107,'1. Anime Figures'!C$8:C$107,A22),0)+IFERROR(SUMIFS('2. Mercari and Online store'!H$8:H$107,'2. Mercari and Online store'!C$8:C$107,A22),0)+IFERROR(SUMIFS('3. Onhand orders JPY'!H$8:H$107,'3. Onhand orders JPY'!C$8:C$107,A22),0)+IFERROR(SUMIFS('4. Live Selling Orders'!H$8:H$107,'4. Live Selling Orders'!C$8:C$107,A22),0)+IFERROR(SUMIFS('5. On hand orders PHP'!H$8:H$107,'5. On hand orders PHP'!C$8:C$107,A22),0)+IFERROR(SUMIFS('6. Pre Orders'!H$8:H$107,'6. Pre Orders'!C$8:C$107,A22),0)+IFERROR(SUMIFS('7. Overseas orders'!H$8:H$107,'7. Overseas orders'!C$8:C$107,A22),0)+IFERROR(SUMIFS('10. Restock'!H$8:H$107,'10. Restock'!C$8:C$107,A22),0),IF($E$2="Weekly View",IFERROR(SUMPRODUCT(('1. Anime Figures'!H$8:H$107)*(IFERROR(WEEKNUM('1. Anime Figures'!B$8:B$107,1),0)=ROW()-19)),0)+IFERROR(SUMPRODUCT(('2. Mercari and Online store'!H$8:H$107)*(IFERROR(WEEKNUM('2. Mercari and Online store'!B$8:B$107,1),0)=ROW()-19)),0)+IFERROR(SUMPRODUCT(('3. Onhand orders JPY'!H$8:H$107)*(IFERROR(WEEKNUM('3. Onhand orders JPY'!B$8:B$107,1),0)=ROW()-19)),0)+IFERROR(SUMPRODUCT(('4. Live Selling Orders'!H$8:H$107)*(IFERROR(WEEKNUM('4. Live Selling Orders'!B$8:B$107,1),0)=ROW()-19)),0)+IFERROR(SUMPRODUCT(('5. On hand orders PHP'!H$8:H$107)*(IFERROR(WEEKNUM('5. On hand orders PHP'!B$8:B$107,1),0)=ROW()-19)),0)+IFERROR(SUMPRODUCT(('6. Pre Orders'!H$8:H$107)*(IFERROR(WEEKNUM('6. Pre Orders'!B$8:B$107,1),0)=ROW()-19)),0)+IFERROR(SUMPRODUCT(('7. Overseas orders'!H$8:H$107)*(IFERROR(WEEKNUM('7. Overseas orders'!B$8:B$107,1),0)=ROW()-19)),0)+IFERROR(SUMPRODUCT(('10. Restock'!H$8:H$107)*(IFERROR(WEEKNUM('10. Restock'!B$8:B$107,1),0)=ROW()-19)),0),IFERROR(SUMPRODUCT(('1. Anime Figures'!H$8:H$107)*(IFERROR(YEAR('1. Anime Figures'!B$8:B$107),0)=(YEAR(TODAY())-12+ROW()-19))),0)+IFERROR(SUMPRODUCT(('2. Mercari and Online store'!H$8:H$107)*(IFERROR(YEAR('2. Mercari and Online store'!B$8:B$107),0)=(YEAR(TODAY())-12+ROW()-19))),0)+IFERROR(SUMPRODUCT(('3. Onhand orders JPY'!H$8:H$107)*(IFERROR(YEAR('3. Onhand orders JPY'!B$8:B$107),0)=(YEAR(TODAY())-12+ROW()-19))),0)+IFERROR(SUMPRODUCT(('4. Live Selling Orders'!H$8:H$107)*(IFERROR(YEAR('4. Live Selling Orders'!B$8:B$107),0)=(YEAR(TODAY())-12+ROW()-19))),0)+IFERROR(SUMPRODUCT(('5. On hand orders PHP'!H$8:H$107)*(IFERROR(YEAR('5. On hand orders PHP'!B$8:B$107),0)=(YEAR(TODAY())-12+ROW()-19))),0)+IFERROR(SUMPRODUCT(('6. Pre Orders'!H$8:H$107)*(IFERROR(YEAR('6. Pre Orders'!B$8:B$107),0)=(YEAR(TODAY())-12+ROW()-19))),0)+IFERROR(SUMPRODUCT(('7. Overseas orders'!H$8:H$107)*(IFERROR(YEAR('7. Overseas orders'!B$8:B$107),0)=(YEAR(TODAY())-12+ROW()-19))),0)+IFERROR(SUMPRODUCT(('10. Restock'!H$8:H$107)*(IFERROR(YEAR('10. Restock'!B$8:B$107),0)=(YEAR(TODAY())-12+ROW()-19))),0))) -> 0 | D22: =IF($E$2="Monthly View",IFERROR(SUMIFS('1. Anime Figures'!J$8:J$107,'1. Anime Figures'!C$8:C$107,A22),0)+IFERROR(SUMIFS('2. Mercari and Online store'!J$8:J$107,'2. Mercari and Online store'!C$8:C$107,A22),0)+IFERROR(SUMIFS('3. Onhand orders JPY'!J$8:J$107,'3. Onhand orders JPY'!C$8:C$107,A22),0)+IFERROR(SUMIFS('4. Live Selling Orders'!J$8:J$107,'4. Live Selling Orders'!C$8:C$107,A22),0)+IFERROR(SUMIFS('5. On hand orders PHP'!J$8:J$107,'5. On hand orders PHP'!C$8:C$107,A22),0)+IFERROR(SUMIFS('6. Pre Orders'!J$8:J$107,'6. Pre Orders'!C$8:C$107,A22),0)+IFERROR(SUMIFS('7. Overseas orders'!J$8:J$107,'7. Overseas orders'!C$8:C$107,A22),0)+IFERROR(SUMIFS('10. Restock'!J$8:J$107,'10. Restock'!C$8:C$107,A22),0),IF($E$2="Weekly View",IFERROR(SUMPRODUCT(('1. Anime Figures'!J$8:J$107)*(IFERROR(WEEKNUM('1. Anime Figures'!B$8:B$107,1),0)=ROW()-19)),0)+IFERROR(SUMPRODUCT(('2. Mercari and Online store'!J$8:J$107)*(IFERROR(WEEKNUM('2. Mercari and Online store'!B$8:B$107,1),0)=ROW()-19)),0)+IFERROR(SUMPRODUCT(('3. Onhand orders JPY'!J$8:J$107)*(IFERROR(WEEKNUM('3. Onhand orders JPY'!B$8:B$107,1),0)=ROW()-19)),0)+IFERROR(SUMPRODUCT(('4. Live Selling Orders'!J$8:J$107)*(IFERROR(WEEKNUM('4. Live Selling Orders'!B$8:B$107,1),0)=ROW()-19)),0)+IFERROR(SUMPRODUCT(('5. On hand orders PHP'!J$8:J$107)*(IFERROR(WEEKNUM('5. On hand orders PHP'!B$8:B$107,1),0)=ROW()-19)),0)+IFERROR(SUMPRODUCT(('6. Pre Orders'!J$8:J$107)*(IFERROR(WEEKNUM('6. Pre Orders'!B$8:B$107,1),0)=ROW()-19)),0)+IFERROR(SUMPRODUCT(('7. Overseas orders'!J$8:J$107)*(IFERROR(WEEKNUM('7. Overseas orders'!B$8:B$107,1),0)=ROW()-19)),0)+IFERROR(SUMPRODUCT(('10. Restock'!J$8:J$107)*(IFERROR(WEEKNUM('10. Restock'!B$8:B$107,1),0)=ROW()-19)),0),IFERROR(SUMPRODUCT(('1. Anime Figures'!J$8:J$107)*(IFERROR(YEAR('1. Anime Figures'!B$8:B$107),0)=(YEAR(TODAY())-12+ROW()-19))),0)+IFERROR(SUMPRODUCT(('2. Mercari and Online store'!J$8:J$107)*(IFERROR(YEAR('2. Mercari and Online store'!B$8:B$107),0)=(YEAR(TODAY())-12+ROW()-19))),0)+IFERROR(SUMPRODUCT(('3. Onhand orders JPY'!J$8:J$107)*(IFERROR(YEAR('3. Onhand orders JPY'!B$8:B$107),0)=(YEAR(TODAY())-12+ROW()-19))),0)+IFERROR(SUMPRODUCT(('4. Live Selling Orders'!J$8:J$107)*(IFERROR(YEAR('4. Live Selling Orders'!B$8:B$107),0)=(YEAR(TODAY())-12+ROW()-19))),0)+IFERROR(SUMPRODUCT(('5. On hand orders PHP'!J$8:J$107)*(IFERROR(YEAR('5. On hand orders PHP'!B$8:B$107),0)=(YEAR(TODAY())-12+ROW()-19))),0)+IFERROR(SUMPRODUCT(('6. Pre Orders'!J$8:J$107)*(IFERROR(YEAR('6. Pre Orders'!B$8:B$107),0)=(YEAR(TODAY())-12+ROW()-19))),0)+IFERROR(SUMPRODUCT(('7. Overseas orders'!J$8:J$107)*(IFERROR(YEAR('7. Overseas orders'!B$8:B$107),0)=(YEAR(TODAY())-12+ROW()-19))),0)+IFERROR(SUMPRODUCT(('10. Restock'!J$8:J$107)*(IFERROR(YEAR('10. Restock'!B$8:B$107),0)=(YEAR(TODAY())-12+ROW()-19))),0))) -> 0
A23: =IF($E$2="Monthly View","March",IF($E$2="Weekly View","Week "&(ROW()-20),YEAR(TODAY())-12+ROW()-19)) -> March | B23: =IF($E$2="Monthly View",IFERROR(SUMIFS('1. Anime Figures'!D$8:D$107,'1. Anime Figures'!C$8:C$107,A23),0)+IFERROR(SUMIFS('2. Mercari and Online store'!D$8:D$107,'2. Mercari and Online store'!C$8:C$107,A23),0)+IFERROR(SUMIFS('3. Onhand orders JPY'!D$8:D$107,'3. Onhand orders JPY'!C$8:C$107,A23),0)+IFERROR(SUMIFS('4. Live Selling Orders'!D$8:D$107,'4. Live Selling Orders'!C$8:C$107,A23),0)+IFERROR(SUMIFS('5. On hand orders PHP'!D$8:D$107,'5. On hand orders PHP'!C$8:C$107,A23),0)+IFERROR(SUMIFS('6. Pre Orders'!D$8:D$107,'6. Pre Orders'!C$8:C$107,A23),0)+IFERROR(SUMIFS('7. Overseas orders'!D$8:D$107,'7. Overseas orders'!C$8:C$107,A23),0)+IFERROR(SUMIFS('10. Restock'!D$8:D$107,'10. Restock'!C$8:C$107,A23),0),IF($E$2="Weekly View",IFERROR(SUMPRODUCT(('1. Anime Figures'!D$8:D$107)*(IFERROR(WEEKNUM('1. Anime Figures'!B$8:B$107,1),0)=ROW()-19)),0)+IFERROR(SUMPRODUCT(('2. Mercari and Online store'!D$8:D$107)*(IFERROR(WEEKNUM('2. Mercari and Online store'!B$8:B$107,1),0)=ROW()-19)),0)+IFERROR(SUMPRODUCT(('3. Onhand orders JPY'!D$8:D$107)*(IFERROR(WEEKNUM('3. Onhand orders JPY'!B$8:B$107,1),0)=ROW()-19)),0)+IFERROR(SUMPRODUCT(('4. Live Selling Orders'!D$8:D$107)*(IFERROR(WEEKNUM('4. Live Selling Orders'!B$8:B$107,1),0)=ROW()-19)),0)+IFERROR(SUMPRODUCT(('5. On hand orders PHP'!D$8:D$107)*(IFERROR(WEEKNUM('5. On hand orders PHP'!B$8:B$107,1),0)=ROW()-19)),0)+IFERROR(SUMPRODUCT(('6. Pre Orders'!D$8:D$107)*(IFERROR(WEEKNUM('6. Pre Orders'!B$8:B$107,1),0)=ROW()-19)),0)+IFERROR(SUMPRODUCT(('7. Overseas orders'!D$8:D$107)*(IFERROR(WEEKNUM('7. Overseas orders'!B$8:B$107,1),0)=ROW()-19)),0)+IFERROR(SUMPRODUCT(('10. Restock'!D$8:D$107)*(IFERROR(WEEKNUM('10. Restock'!B$8:B$107,1),0)=ROW()-19)),0),IFERROR(SUMPRODUCT(('1. Anime Figures'!D$8:D$107)*(IFERROR(YEAR('1. Anime Figures'!B$8:B$107),0)=(YEAR(TODAY())-12+ROW()-19))),0)+IFERROR(SUMPRODUCT(('2. Mercari and Online store'!D$8:D$107)*(IFERROR(YEAR('2. Mercari and Online store'!B$8:B$107),0)=(YEAR(TODAY())-12+ROW()-19))),0)+IFERROR(SUMPRODUCT(('3. Onhand orders JPY'!D$8:D$107)*(IFERROR(YEAR('3. Onhand orders JPY'!B$8:B$107),0)=(YEAR(TODAY())-12+ROW()-19))),0)+IFERROR(SUMPRODUCT(('4. Live Selling Orders'!D$8:D$107)*(IFERROR(YEAR('4. Live Selling Orders'!B$8:B$107),0)=(YEAR(TODAY())-12+ROW()-19))),0)+IFERROR(SUMPRODUCT(('5. On hand orders PHP'!D$8:D$107)*(IFERROR(YEAR('5. On hand orders PHP'!B$8:B$107),0)=(YEAR(TODAY())-12+ROW()-19))),0)+IFERROR(SUMPRODUCT(('6. Pre Orders'!D$8:D$107)*(IFERROR(YEAR('6. Pre Orders'!B$8:B$107),0)=(YEAR(TODAY())-12+ROW()-19))),0)+IFERROR(SUMPRODUCT(('7. Overseas orders'!D$8:D$107)*(IFERROR(YEAR('7. Overseas orders'!B$8:B$107),0)=(YEAR(TODAY())-12+ROW()-19))),0)+IFERROR(SUMPRODUCT(('10. Restock'!D$8:D$107)*(IFERROR(YEAR('10. Restock'!B$8:B$107),0)=(YEAR(TODAY())-12+ROW()-19))),0))) -> 0 | C23: =IF($E$2="Monthly View",IFERROR(SUMIFS('1. Anime Figures'!H$8:H$107,'1. Anime Figures'!C$8:C$107,A23),0)+IFERROR(SUMIFS('2. Mercari and Online store'!H$8:H$107,'2. Mercari and Online store'!C$8:C$107,A23),0)+IFERROR(SUMIFS('3. Onhand orders JPY'!H$8:H$107,'3. Onhand orders JPY'!C$8:C$107,A23),0)+IFERROR(SUMIFS('4. Live Selling Orders'!H$8:H$107,'4. Live Selling Orders'!C$8:C$107,A23),0)+IFERROR(SUMIFS('5. On hand orders PHP'!H$8:H$107,'5. On hand orders PHP'!C$8:C$107,A23),0)+IFERROR(SUMIFS('6. Pre Orders'!H$8:H$107,'6. Pre Orders'!C$8:C$107,A23),0)+IFERROR(SUMIFS('7. Overseas orders'!H$8:H$107,'7. Overseas orders'!C$8:C$107,A23),0)+IFERROR(SUMIFS('10. Restock'!H$8:H$107,'10. Restock'!C$8:C$107,A23),0),IF($E$2="Weekly View",IFERROR(SUMPRODUCT(('1. Anime Figures'!H$8:H$107)*(IFERROR(WEEKNUM('1. Anime Figures'!B$8:B$107,1),0)=ROW()-19)),0)+IFERROR(SUMPRODUCT(('2. Mercari and Online store'!H$8:H$107)*(IFERROR(WEEKNUM('2. Mercari and Online store'!B$8:B$107,1),0)=ROW()-19)),0)+IFERROR(SUMPRODUCT(('3. Onhand orders JPY'!H$8:H$107)*(IFERROR(WEEKNUM('3. Onhand orders JPY'!B$8:B$107,1),0)=ROW()-19)),0)+IFERROR(SUMPRODUCT(('4. Live Selling Orders'!H$8:H$107)*(IFERROR(WEEKNUM('4. Live Selling Orders'!B$8:B$107,1),0)=ROW()-19)),0)+IFERROR(SUMPRODUCT(('5. On hand orders PHP'!H$8:H$107)*(IFERROR(WEEKNUM('5. On hand orders PHP'!B$8:B$107,1),0)=ROW()-19)),0)+IFERROR(SUMPRODUCT(('6. Pre Orders'!H$8:H$107)*(IFERROR(WEEKNUM('6. Pre Orders'!B$8:B$107,1),0)=ROW()-19)),0)+IFERROR(SUMPRODUCT(('7. Overseas orders'!H$8:H$107)*(IFERROR(WEEKNUM('7. Overseas orders'!B$8:B$107,1),0)=ROW()-19)),0)+IFERROR(SUMPRODUCT(('10. Restock'!H$8:H$107)*(IFERROR(WEEKNUM('10. Restock'!B$8:B$107,1),0)=ROW()-19)),0),IFERROR(SUMPRODUCT(('1. Anime Figures'!H$8:H$107)*(IFERROR(YEAR('1. Anime Figures'!B$8:B$107),0)=(YEAR(TODAY())-12+ROW()-19))),0)+IFERROR(SUMPRODUCT(('2. Mercari and Online store'!H$8:H$107)*(IFERROR(YEAR('2. Mercari and Online store'!B$8:B$107),0)=(YEAR(TODAY())-12+ROW()-19))),0)+IFERROR(SUMPRODUCT(('3. Onhand orders JPY'!H$8:H$107)*(IFERROR(YEAR('3. Onhand orders JPY'!B$8:B$107),0)=(YEAR(TODAY())-12+ROW()-19))),0)+IFERROR(SUMPRODUCT(('4. Live Selling Orders'!H$8:H$107)*(IFERROR(YEAR('4. Live Selling Orders'!B$8:B$107),0)=(YEAR(TODAY())-12+ROW()-19))),0)+IFERROR(SUMPRODUCT(('5. On hand orders PHP'!H$8:H$107)*(IFERROR(YEAR('5. On hand orders PHP'!B$8:B$107),0)=(YEAR(TODAY())-12+ROW()-19))),0)+IFERROR(SUMPRODUCT(('6. Pre Orders'!H$8:H$107)*(IFERROR(YEAR('6. Pre Orders'!B$8:B$107),0)=(YEAR(TODAY())-12+ROW()-19))),0)+IFERROR(SUMPRODUCT(('7. Overseas orders'!H$8:H$107)*(IFERROR(YEAR('7. Overseas orders'!B$8:B$107),0)=(YEAR(TODAY())-12+ROW()-19))),0)+IFERROR(SUMPRODUCT(('10. Restock'!H$8:H$107)*(IFERROR(YEAR('10. Restock'!B$8:B$107),0)=(YEAR(TODAY())-12+ROW()-19))),0))) -> 0 | D23: =IF($E$2="Monthly View",IFERROR(SUMIFS('1. Anime Figures'!J$8:J$107,'1. Anime Figures'!C$8:C$107,A23),0)+IFERROR(SUMIFS('2. Mercari and Online store'!J$8:J$107,'2. Mercari and Online store'!C$8:C$107,A23),0)+IFERROR(SUMIFS('3. Onhand orders JPY'!J$8:J$107,'3. Onhand orders JPY'!C$8:C$107,A23),0)+IFERROR(SUMIFS('4. Live Selling Orders'!J$8:J$107,'4. Live Selling Orders'!C$8:C$107,A23),0)+IFERROR(SUMIFS('5. On hand orders PHP'!J$8:J$107,'5. On hand orders PHP'!C$8:C$107,A23),0)+IFERROR(SUMIFS('6. Pre Orders'!J$8:J$107,'6. Pre Orders'!C$8:C$107,A23),0)+IFERROR(SUMIFS('7. Overseas orders'!J$8:J$107,'7. Overseas orders'!C$8:C$107,A23),0)+IFERROR(SUMIFS('10. Restock'!J$8:J$107,'10. Restock'!C$8:C$107,A23),0),IF($E$2="Weekly View",IFERROR(SUMPRODUCT(('1. Anime Figures'!J$8:J$107)*(IFERROR(WEEKNUM('1. Anime Figures'!B$8:B$107,1),0)=ROW()-19)),0)+IFERROR(SUMPRODUCT(('2. Mercari and Online store'!J$8:J$107)*(IFERROR(WEEKNUM('2. Mercari and Online store'!B$8:B$107,1),0)=ROW()-19)),0)+IFERROR(SUMPRODUCT(('3. Onhand orders JPY'!J$8:J$107)*(IFERROR(WEEKNUM('3. Onhand orders JPY'!B$8:B$107,1),0)=ROW()-19)),0)+IFERROR(SUMPRODUCT(('4. Live Selling Orders'!J$8:J$107)*(IFERROR(WEEKNUM('4. Live Selling Orders'!B$8:B$107,1),0)=ROW()-19)),0)+IFERROR(SUMPRODUCT(('5. On hand orders PHP'!J$8:J$107)*(IFERROR(WEEKNUM('5. On hand orders PHP'!B$8:B$107,1),0)=ROW()-19)),0)+IFERROR(SUMPRODUCT(('6. Pre Orders'!J$8:J$107)*(IFERROR(WEEKNUM('6. Pre Orders'!B$8:B$107,1),0)=ROW()-19)),0)+IFERROR(SUMPRODUCT(('7. Overseas orders'!J$8:J$107)*(IFERROR(WEEKNUM('7. Overseas orders'!B$8:B$107,1),0)=ROW()-19)),0)+IFERROR(SUMPRODUCT(('10. Restock'!J$8:J$107)*(IFERROR(WEEKNUM('10. Restock'!B$8:B$107,1),0)=ROW()-19)),0),IFERROR(SUMPRODUCT(('1. Anime Figures'!J$8:J$107)*(IFERROR(YEAR('1. Anime Figures'!B$8:B$107),0)=(YEAR(TODAY())-12+ROW()-19))),0)+IFERROR(SUMPRODUCT(('2. Mercari and Online store'!J$8:J$107)*(IFERROR(YEAR('2. Mercari and Online store'!B$8:B$107),0)=(YEAR(TODAY())-12+ROW()-19))),0)+IFERROR(SUMPRODUCT(('3. Onhand orders JPY'!J$8:J$107)*(IFERROR(YEAR('3. Onhand orders JPY'!B$8:B$107),0)=(YEAR(TODAY())-12+ROW()-19))),0)+IFERROR(SUMPRODUCT(('4. Live Selling Orders'!J$8:J$107)*(IFERROR(YEAR('4. Live Selling Orders'!B$8:B$107),0)=(YEAR(TODAY())-12+ROW()-19))),0)+IFERROR(SUMPRODUCT(('5. On hand orders PHP'!J$8:J$107)*(IFERROR(YEAR('5. On hand orders PHP'!B$8:B$107),0)=(YEAR(TODAY())-12+ROW()-19))),0)+IFERROR(SUMPRODUCT(('6. Pre Orders'!J$8:J$107)*(IFERROR(YEAR('6. Pre Orders'!B$8:B$107),0)=(YEAR(TODAY())-12+ROW()-19))),0)+IFERROR(SUMPRODUCT(('7. Overseas orders'!J$8:J$107)*(IFERROR(YEAR('7. Overseas orders'!B$8:B$107),0)=(YEAR(TODAY())-12+ROW()-19))),0)+IFERROR(SUMPRODUCT(('10. Restock'!J$8:J$107)*(IFERROR(YEAR('10. Restock'!B$8:B$107),0)=(YEAR(TODAY())-12+ROW()-19))),0))) -> 0
A24: =IF($E$2="Monthly View","April",IF($E$2="Weekly View","Week "&(ROW()-20),YEAR(TODAY())-12+ROW()-19)) -> April | B24: =IF($E$2="Monthly View",IFERROR(SUMIFS('1. Anime Figures'!D$8:D$107,'1. Anime Figures'!C$8:C$107,A24),0)+IFERROR(SUMIFS('2. Mercari and Online store'!D$8:D$107,'2. Mercari and Online store'!C$8:C$107,A24),0)+IFERROR(SUMIFS('3. Onhand orders JPY'!D$8:D$107,'3. Onhand orders JPY'!C$8:C$107,A24),0)+IFERROR(SUMIFS('4. Live Selling Orders'!D$8:D$107,'4. Live Selling Orders'!C$8:C$107,A24),0)+IFERROR(SUMIFS('5. On hand orders PHP'!D$8:D$107,'5. On hand orders PHP'!C$8:C$107,A24),0)+IFERROR(SUMIFS('6. Pre Orders'!D$8:D$107,'6. Pre Orders'!C$8:C$107,A24),0)+IFERROR(SUMIFS('7. Overseas orders'!D$8:D$107,'7. Overseas orders'!C$8:C$107,A24),0)+IFERROR(SUMIFS('10. Restock'!D$8:D$107,'10. Restock'!C$8:C$107,A24),0),IF($E$2="Weekly View",IFERROR(SUMPRODUCT(('1. Anime Figures'!D$8:D$107)*(IFERROR(WEEKNUM('1. Anime Figures'!B$8:B$107,1),0)=ROW()-19)),0)+IFERROR(SUMPRODUCT(('2. Mercari and Online store'!D$8:D$107)*(IFERROR(WEEKNUM('2. Mercari and Online store'!B$8:B$107,1),0)=ROW()-19)),0)+IFERROR(SUMPRODUCT(('3. Onhand orders JPY'!D$8:D$107)*(IFERROR(WEEKNUM('3. Onhand orders JPY'!B$8:B$107,1),0)=ROW()-19)),0)+IFERROR(SUMPRODUCT(('4. Live Selling Orders'!D$8:D$107)*(IFERROR(WEEKNUM('4. Live Selling Orders'!B$8:B$107,1),0)=ROW()-19)),0)+IFERROR(SUMPRODUCT(('5. On hand orders PHP'!D$8:D$107)*(IFERROR(WEEKNUM('5. On hand orders PHP'!B$8:B$107,1),0)=ROW()-19)),0)+IFERROR(SUMPRODUCT(('6. Pre Orders'!D$8:D$107)*(IFERROR(WEEKNUM('6. Pre Orders'!B$8:B$107,1),0)=ROW()-19)),0)+IFERROR(SUMPRODUCT(('7. Overseas orders'!D$8:D$107)*(IFERROR(WEEKNUM('7. Overseas orders'!B$8:B$107,1),0)=ROW()-19)),0)+IFERROR(SUMPRODUCT(('10. Restock'!D$8:D$107)*(IFERROR(WEEKNUM('10. Restock'!B$8:B$107,1),0)=ROW()-19)),0),IFERROR(SUMPRODUCT(('1. Anime Figures'!D$8:D$107)*(IFERROR(YEAR('1. Anime Figures'!B$8:B$107),0)=(YEAR(TODAY())-12+ROW()-19))),0)+IFERROR(SUMPRODUCT(('2. Mercari and Online store'!D$8:D$107)*(IFERROR(YEAR('2. Mercari and Online store'!B$8:B$107),0)=(YEAR(TODAY())-12+ROW()-19))),0)+IFERROR(SUMPRODUCT(('3. Onhand orders JPY'!D$8:D$107)*(IFERROR(YEAR('3. Onhand orders JPY'!B$8:B$107),0)=(YEAR(TODAY())-12+ROW()-19))),0)+IFERROR(SUMPRODUCT(('4. Live Selling Orders'!D$8:D$107)*(IFERROR(YEAR('4. Live Selling Orders'!B$8:B$107),0)=(YEAR(TODAY())-12+ROW()-19))),0)+IFERROR(SUMPRODUCT(('5. On hand orders PHP'!D$8:D$107)*(IFERROR(YEAR('5. On hand orders PHP'!B$8:B$107),0)=(YEAR(TODAY())-12+ROW()-19))),0)+IFERROR(SUMPRODUCT(('6. Pre Orders'!D$8:D$107)*(IFERROR(YEAR('6. Pre Orders'!B$8:B$107),0)=(YEAR(TODAY())-12+ROW()-19))),0)+IFERROR(SUMPRODUCT(('7. Overseas orders'!D$8:D$107)*(IFERROR(YEAR('7. Overseas orders'!B$8:B$107),0)=(YEAR(TODAY())-12+ROW()-19))),0)+IFERROR(SUMPRODUCT(('10. Restock'!D$8:D$107)*(IFERROR(YEAR('10. Restock'!B$8:B$107),0)=(YEAR(TODAY())-12+ROW()-19))),0))) -> 0 | C24: =IF($E$2="Monthly View",IFERROR(SUMIFS('1. Anime Figures'!H$8:H$107,'1. Anime Figures'!C$8:C$107,A24),0)+IFERROR(SUMIFS('2. Mercari and Online store'!H$8:H$107,'2. Mercari and Online store'!C$8:C$107,A24),0)+IFERROR(SUMIFS('3. Onhand orders JPY'!H$8:H$107,'3. Onhand orders JPY'!C$8:C$107,A24),0)+IFERROR(SUMIFS('4. Live Selling Orders'!H$8:H$107,'4. Live Selling Orders'!C$8:C$107,A24),0)+IFERROR(SUMIFS('5. On hand orders PHP'!H$8:H$107,'5. On hand orders PHP'!C$8:C$107,A24),0)+IFERROR(SUMIFS('6. Pre Orders'!H$8:H$107,'6. Pre Orders'!C$8:C$107,A24),0)+IFERROR(SUMIFS('7. Overseas orders'!H$8:H$107,'7. Overseas orders'!C$8:C$107,A24),0)+IFERROR(SUMIFS('10. Restock'!H$8:H$107,'10. Restock'!C$8:C$107,A24),0),IF($E$2="Weekly View",IFERROR(SUMPRODUCT(('1. Anime Figures'!H$8:H$107)*(IFERROR(WEEKNUM('1. Anime Figures'!B$8:B$107,1),0)=ROW()-19)),0)+IFERROR(SUMPRODUCT(('2. Mercari and Online store'!H$8:H$107)*(IFERROR(WEEKNUM('2. Mercari and Online store'!B$8:B$107,1),0)=ROW()-19)),0)+IFERROR(SUMPRODUCT(('3. Onhand orders JPY'!H$8:H$107)*(IFERROR(WEEKNUM('3. Onhand orders JPY'!B$8:B$107,1),0)=ROW()-19)),0)+IFERROR(SUMPRODUCT(('4. Live Selling Orders'!H$8:H$107)*(IFERROR(WEEKNUM('4. Live Selling Orders'!B$8:B$107,1),0)=ROW()-19)),0)+IFERROR(SUMPRODUCT(('5. On hand orders PHP'!H$8:H$107)*(IFERROR(WEEKNUM('5. On hand orders PHP'!B$8:B$107,1),0)=ROW()-19)),0)+IFERROR(SUMPRODUCT(('6. Pre Orders'!H$8:H$107)*(IFERROR(WEEKNUM('6. Pre Orders'!B$8:B$107,1),0)=ROW()-19)),0)+IFERROR(SUMPRODUCT(('7. Overseas orders'!H$8:H$107)*(IFERROR(WEEKNUM('7. Overseas orders'!B$8:B$107,1),0)=ROW()-19)),0)+IFERROR(SUMPRODUCT(('10. Restock'!H$8:H$107)*(IFERROR(WEEKNUM('10. Restock'!B$8:B$107,1),0)=ROW()-19)),0),IFERROR(SUMPRODUCT(('1. Anime Figures'!H$8:H$107)*(IFERROR(YEAR('1. Anime Figures'!B$8:B$107),0)=(YEAR(TODAY())-12+ROW()-19))),0)+IFERROR(SUMPRODUCT(('2. Mercari and Online store'!H$8:H$107)*(IFERROR(YEAR('2. Mercari and Online store'!B$8:B$107),0)=(YEAR(TODAY())-12+ROW()-19))),0)+IFERROR(SUMPRODUCT(('3. Onhand orders JPY'!H$8:H$107)*(IFERROR(YEAR('3. Onhand orders JPY'!B$8:B$107),0)=(YEAR(TODAY())-12+ROW()-19))),0)+IFERROR(SUMPRODUCT(('4. Live Selling Orders'!H$8:H$107)*(IFERROR(YEAR('4. Live Selling Orders'!B$8:B$107),0)=(YEAR(TODAY())-12+ROW()-19))),0)+IFERROR(SUMPRODUCT(('5. On hand orders PHP'!H$8:H$107)*(IFERROR(YEAR('5. On hand orders PHP'!B$8:B$107),0)=(YEAR(TODAY())-12+ROW()-19))),0)+IFERROR(SUMPRODUCT(('6. Pre Orders'!H$8:H$107)*(IFERROR(YEAR('6. Pre Orders'!B$8:B$107),0)=(YEAR(TODAY())-12+ROW()-19))),0)+IFERROR(SUMPRODUCT(('7. Overseas orders'!H$8:H$107)*(IFERROR(YEAR('7. Overseas orders'!B$8:B$107),0)=(YEAR(TODAY())-12+ROW()-19))),0)+IFERROR(SUMPRODUCT(('10. Restock'!H$8:H$107)*(IFERROR(YEAR('10. Restock'!B$8:B$107),0)=(YEAR(TODAY())-12+ROW()-19))),0))) -> 0 | D24: =IF($E$2="Monthly View",IFERROR(SUMIFS('1. Anime Figures'!J$8:J$107,'1. Anime Figures'!C$8:C$107,A24),0)+IFERROR(SUMIFS('2. Mercari and Online store'!J$8:J$107,'2. Mercari and Online store'!C$8:C$107,A24),0)+IFERROR(SUMIFS('3. Onhand orders JPY'!J$8:J$107,'3. Onhand orders JPY'!C$8:C$107,A24),0)+IFERROR(SUMIFS('4. Live Selling Orders'!J$8:J$107,'4. Live Selling Orders'!C$8:C$107,A24),0)+IFERROR(SUMIFS('5. On hand orders PHP'!J$8:J$107,'5. On hand orders PHP'!C$8:C$107,A24),0)+IFERROR(SUMIFS('6. Pre Orders'!J$8:J$107,'6. Pre Orders'!C$8:C$107,A24),0)+IFERROR(SUMIFS('7. Overseas orders'!J$8:J$107,'7. Overseas orders'!C$8:C$107,A24),0)+IFERROR(SUMIFS('10. Restock'!J$8:J$107,'10. Restock'!C$8:C$107,A24),0),IF($E$2="Weekly View",IFERROR(SUMPRODUCT(('1. Anime Figures'!J$8:J$107)*(IFERROR(WEEKNUM('1. Anime Figures'!B$8:B$107,1),0)=ROW()-19)),0)+IFERROR(SUMPRODUCT(('2. Mercari and Online store'!J$8:J$107)*(IFERROR(WEEKNUM('2. Mercari and Online store'!B$8:B$107,1),0)=ROW()-19)),0)+IFERROR(SUMPRODUCT(('3. Onhand orders JPY'!J$8:J$107)*(IFERROR(WEEKNUM('3. Onhand orders JPY'!B$8:B$107,1),0)=ROW()-19)),0)+IFERROR(SUMPRODUCT(('4. Live Selling Orders'!J$8:J$107)*(IFERROR(WEEKNUM('4. Live Selling Orders'!B$8:B$107,1),0)=ROW()-19)),0)+IFERROR(SUMPRODUCT(('5. On hand orders PHP'!J$8:J$107)*(IFERROR(WEEKNUM('5. On hand orders PHP'!B$8:B$107,1),0)=ROW()-19)),0)+IFERROR(SUMPRODUCT(('6. Pre Orders'!J$8:J$107)*(IFERROR(WEEKNUM('6. Pre Orders'!B$8:B$107,1),0)=ROW()-19)),0)+IFERROR(SUMPRODUCT(('7. Overseas orders'!J$8:J$107)*(IFERROR(WEEKNUM('7. Overseas orders'!B$8:B$107,1),0)=ROW()-19)),0)+IFERROR(SUMPRODUCT(('10. Restock'!J$8:J$107)*(IFERROR(WEEKNUM('10. Restock'!B$8:B$107,1),0)=ROW()-19)),0),IFERROR(SUMPRODUCT(('1. Anime Figures'!J$8:J$107)*(IFERROR(YEAR('1. Anime Figures'!B$8:B$107),0)=(YEAR(TODAY())-12+ROW()-19))),0)+IFERROR(SUMPRODUCT(('2. Mercari and Online store'!J$8:J$107)*(IFERROR(YEAR('2. Mercari and Online store'!B$8:B$107),0)=(YEAR(TODAY())-12+ROW()-19))),0)+IFERROR(SUMPRODUCT(('3. Onhand orders JPY'!J$8:J$107)*(IFERROR(YEAR('3. Onhand orders JPY'!B$8:B$107),0)=(YEAR(TODAY())-12+ROW()-19))),0)+IFERROR(SUMPRODUCT(('4. Live Selling Orders'!J$8:J$107)*(IFERROR(YEAR('4. Live Selling Orders'!B$8:B$107),0)=(YEAR(TODAY())-12+ROW()-19))),0)+IFERROR(SUMPRODUCT(('5. On hand orders PHP'!J$8:J$107)*(IFERROR(YEAR('5. On hand orders PHP'!B$8:B$107),0)=(YEAR(TODAY())-12+ROW()-19))),0)+IFERROR(SUMPRODUCT(('6. Pre Orders'!J$8:J$107)*(IFERROR(YEAR('6. Pre Orders'!B$8:B$107),0)=(YEAR(TODAY())-12+ROW()-19))),0)+IFERROR(SUMPRODUCT(('7. Overseas orders'!J$8:J$107)*(IFERROR(YEAR('7. Overseas orders'!B$8:B$107),0)=(YEAR(TODAY())-12+ROW()-19))),0)+IFERROR(SUMPRODUCT(('10. Restock'!J$8:J$107)*(IFERROR(YEAR('10. Restock'!B$8:B$107),0)=(YEAR(TODAY())-12+ROW()-19))),0))) -> 0
A25: =IF($E$2="Monthly View","May",IF($E$2="Weekly View","Week "&(ROW()-20),YEAR(TODAY())-12+ROW()-19)) -> May | B25: =IF($E$2="Monthly View",IFERROR(SUMIFS('1. Anime Figures'!D$8:D$107,'1. Anime Figures'!C$8:C$107,A25),0)+IFERROR(SUMIFS('2. Mercari and Online store'!D$8:D$107,'2. Mercari and Online store'!C$8:C$107,A25),0)+IFERROR(SUMIFS('3. Onhand orders JPY'!D$8:D$107,'3. Onhand orders JPY'!C$8:C$107,A25),0)+IFERROR(SUMIFS('4. Live Selling Orders'!D$8:D$107,'4. Live Selling Orders'!C$8:C$107,A25),0)+IFERROR(SUMIFS('5. On hand orders PHP'!D$8:D$107,'5. On hand orders PHP'!C$8:C$107,A25),0)+IFERROR(SUMIFS('6. Pre Orders'!D$8:D$107,'6. Pre Orders'!C$8:C$107,A25),0)+IFERROR(SUMIFS('7. Overseas orders'!D$8:D$107,'7. Overseas orders'!C$8:C$107,A25),0)+IFERROR(SUMIFS('10. Restock'!D$8:D$107,'10. Restock'!C$8:C$107,A25),0),IF($E$2="Weekly View",IFERROR(SUMPRODUCT(('1. Anime Figures'!D$8:D$107)*(IFERROR(WEEKNUM('1. Anime Figures'!B$8:B$107,1),0)=ROW()-19)),0)+IFERROR(SUMPRODUCT(('2. Mercari and Online store'!D$8:D$107)*(IFERROR(WEEKNUM('2. Mercari and Online store'!B$8:B$107,1),0)=ROW()-19)),0)+IFERROR(SUMPRODUCT(('3. Onhand orders JPY'!D$8:D$107)*(IFERROR(WEEKNUM('3. Onhand orders JPY'!B$8:B$107,1),0)=ROW()-19)),0)+IFERROR(SUMPRODUCT(('4. Live Selling Orders'!D$8:D$107)*(IFERROR(WEEKNUM('4. Live Selling Orders'!B$8:B$107,1),0)=ROW()-19)),0)+IFERROR(SUMPRODUCT(('5. On hand orders PHP'!D$8:D$107)*(IFERROR(WEEKNUM('5. On hand orders PHP'!B$8:B$107,1),0)=ROW()-19)),0)+IFERROR(SUMPRODUCT(('6. Pre Orders'!D$8:D$107)*(IFERROR(WEEKNUM('6. Pre Orders'!B$8:B$107,1),0)=ROW()-19)),0)+IFERROR(SUMPRODUCT(('7. Overseas orders'!D$8:D$107)*(IFERROR(WEEKNUM('7. Overseas orders'!B$8:B$107,1),0)=ROW()-19)),0)+IFERROR(SUMPRODUCT(('10. Restock'!D$8:D$107)*(IFERROR(WEEKNUM('10. Restock'!B$8:B$107,1),0)=ROW()-19)),0),IFERROR(SUMPRODUCT(('1. Anime Figures'!D$8:D$107)*(IFERROR(YEAR('1. Anime Figures'!B$8:B$107),0)=(YEAR(TODAY())-12+ROW()-19))),0)+IFERROR(SUMPRODUCT(('2. Mercari and Online store'!D$8:D$107)*(IFERROR(YEAR('2. Mercari and Online store'!B$8:B$107),0)=(YEAR(TODAY())-12+ROW()-19))),0)+IFERROR(SUMPRODUCT(('3. Onhand orders JPY'!D$8:D$107)*(IFERROR(YEAR('3. Onhand orders JPY'!B$8:B$107),0)=(YEAR(TODAY())-12+ROW()-19))),0)+IFERROR(SUMPRODUCT(('4. Live Selling Orders'!D$8:D$107)*(IFERROR(YEAR('4. Live Selling Orders'!B$8:B$107),0)=(YEAR(TODAY())-12+ROW()-19))),0)+IFERROR(SUMPRODUCT(('5. On hand orders PHP'!D$8:D$107)*(IFERROR(YEAR('5. On hand orders PHP'!B$8:B$107),0)=(YEAR(TODAY())-12+ROW()-19))),0)+IFERROR(SUMPRODUCT(('6. Pre Orders'!D$8:D$107)*(IFERROR(YEAR('6. Pre Orders'!B$8:B$107),0)=(YEAR(TODAY())-12+ROW()-19))),0)+IFERROR(SUMPRODUCT(('7. Overseas orders'!D$8:D$107)*(IFERROR(YEAR('7. Overseas orders'!B$8:B$107),0)=(YEAR(TODAY())-12+ROW()-19))),0)+IFERROR(SUMPRODUCT(('10. Restock'!D$8:D$107)*(IFERROR(YEAR('10. Restock'!B$8:B$107),0)=(YEAR(TODAY())-12+ROW()-19))),0))) -> 0 | C25: =IF($E$2="Monthly View",IFERROR(SUMIFS('1. Anime Figures'!H$8:H$107,'1. Anime Figures'!C$8:C$107,A25),0)+IFERROR(SUMIFS('2. Mercari and Online store'!H$8:H$107,'2. Mercari and Online store'!C$8:C$107,A25),0)+IFERROR(SUMIFS('3. Onhand orders JPY'!H$8:H$107,'3. Onhand orders JPY'!C$8:C$107,A25),0)+IFERROR(SUMIFS('4. Live Selling Orders'!H$8:H$107,'4. Live Selling Orders'!C$8:C$107,A25),0)+IFERROR(SUMIFS('5. On hand orders PHP'!H$8:H$107,'5. On hand orders PHP'!C$8:C$107,A25),0)+IFERROR(SUMIFS('6. Pre Orders'!H$8:H$107,'6. Pre Orders'!C$8:C$107,A25),0)+IFERROR(SUMIFS('7. Overseas orders'!H$8:H$107,'7. Overseas orders'!C$8:C$107,A25),0)+IFERROR(SUMIFS('10. Restock'!H$8:H$107,'10. Restock'!C$8:C$107,A25),0),IF($E$2="Weekly View",IFERROR(SUMPRODUCT(('1. Anime Figures'!H$8:H$107)*(IFERROR(WEEKNUM('1. Anime Figures'!B$8:B$107,1),0)=ROW()-19)),0)+IFERROR(SUMPRODUCT(('2. Mercari and Online store'!H$8:H$107)*(IFERROR(WEEKNUM('2. Mercari and Online store'!B$8:B$107,1),0)=ROW()-19)),0)+IFERROR(SUMPRODUCT(('3. Onhand orders JPY'!H$8:H$107)*(IFERROR(WEEKNUM('3. Onhand orders JPY'!B$8:B$107,1),0)=ROW()-19)),0)+IFERROR(SUMPRODUCT(('4. Live Selling Orders'!H$8:H$107)*(IFERROR(WEEKNUM('4. Live Selling Orders'!B$8:B$107,1),0)=ROW()-19)),0)+IFERROR(SUMPRODUCT(('5. On hand orders PHP'!H$8:H$107)*(IFERROR(WEEKNUM('5. On hand orders PHP'!B$8:B$107,1),0)=ROW()-19)),0)+IFERROR(SUMPRODUCT(('6. Pre Orders'!H$8:H$107)*(IFERROR(WEEKNUM('6. Pre Orders'!B$8:B$107,1),0)=ROW()-19)),0)+IFERROR(SUMPRODUCT(('7. Overseas orders'!H$8:H$107)*(IFERROR(WEEKNUM('7. Overseas orders'!B$8:B$107,1),0)=ROW()-19)),0)+IFERROR(SUMPRODUCT(('10. Restock'!H$8:H$107)*(IFERROR(WEEKNUM('10. Restock'!B$8:B$107,1),0)=ROW()-19)),0),IFERROR(SUMPRODUCT(('1. Anime Figures'!H$8:H$107)*(IFERROR(YEAR('1. Anime Figures'!B$8:B$107),0)=(YEAR(TODAY())-12+ROW()-19))),0)+IFERROR(SUMPRODUCT(('2. Mercari and Online store'!H$8:H$107)*(IFERROR(YEAR('2. Mercari and Online store'!B$8:B$107),0)=(YEAR(TODAY())-12+ROW()-19))),0)+IFERROR(SUMPRODUCT(('3. Onhand orders JPY'!H$8:H$107)*(IFERROR(YEAR('3. Onhand orders JPY'!B$8:B$107),0)=(YEAR(TODAY())-12+ROW()-19))),0)+IFERROR(SUMPRODUCT(('4. Live Selling Orders'!H$8:H$107)*(IFERROR(YEAR('4. Live Selling Orders'!B$8:B$107),0)=(YEAR(TODAY())-12+ROW()-19))),0)+IFERROR(SUMPRODUCT(('5. On hand orders PHP'!H$8:H$107)*(IFERROR(YEAR('5. On hand orders PHP'!B$8:B$107),0)=(YEAR(TODAY())-12+ROW()-19))),0)+IFERROR(SUMPRODUCT(('6. Pre Orders'!H$8:H$107)*(IFERROR(YEAR('6. Pre Orders'!B$8:B$107),0)=(YEAR(TODAY())-12+ROW()-19))),0)+IFERROR(SUMPRODUCT(('7. Overseas orders'!H$8:H$107)*(IFERROR(YEAR('7. Overseas orders'!B$8:B$107),0)=(YEAR(TODAY())-12+ROW()-19))),0)+IFERROR(SUMPRODUCT(('10. Restock'!H$8:H$107)*(IFERROR(YEAR('10. Restock'!B$8:B$107),0)=(YEAR(TODAY())-12+ROW()-19))),0))) -> 0 | D25: =IF($E$2="Monthly View",IFERROR(SUMIFS('1. Anime Figures'!J$8:J$107,'1. Anime Figures'!C$8:C$107,A25),0)+IFERROR(SUMIFS('2. Mercari and Online store'!J$8:J$107,'2. Mercari and Online store'!C$8:C$107,A25),0)+IFERROR(SUMIFS('3. Onhand orders JPY'!J$8:J$107,'3. Onhand orders JPY'!C$8:C$107,A25),0)+IFERROR(SUMIFS('4. Live Selling Orders'!J$8:J$107,'4. Live Selling Orders'!C$8:C$107,A25),0)+IFERROR(SUMIFS('5. On hand orders PHP'!J$8:J$107,'5. On hand orders PHP'!C$8:C$107,A25),0)+IFERROR(SUMIFS('6. Pre Orders'!J$8:J$107,'6. Pre Orders'!C$8:C$107,A25),0)+IFERROR(SUMIFS('7. Overseas orders'!J$8:J$107,'7. Overseas orders'!C$8:C$107,A25),0)+IFERROR(SUMIFS('10. Restock'!J$8:J$107,'10. Restock'!C$8:C$107,A25),0),IF($E$2="Weekly View",IFERROR(SUMPRODUCT(('1. Anime Figures'!J$8:J$107)*(IFERROR(WEEKNUM('1. Anime Figures'!B$8:B$107,1),0)=ROW()-19)),0)+IFERROR(SUMPRODUCT(('2. Mercari and Online store'!J$8:J$107)*(IFERROR(WEEKNUM('2. Mercari and Online store'!B$8:B$107,1),0)=ROW()-19)),0)+IFERROR(SUMPRODUCT(('3. Onhand orders JPY'!J$8:J$107)*(IFERROR(WEEKNUM('3. Onhand orders JPY'!B$8:B$107,1),0)=ROW()-19)),0)+IFERROR(SUMPRODUCT(('4. Live Selling Orders'!J$8:J$107)*(IFERROR(WEEKNUM('4. Live Selling Orders'!B$8:B$107,1),0)=ROW()-19)),0)+IFERROR(SUMPRODUCT(('5. On hand orders PHP'!J$8:J$107)*(IFERROR(WEEKNUM('5. On hand orders PHP'!B$8:B$107,1),0)=ROW()-19)),0)+IFERROR(SUMPRODUCT(('6. Pre Orders'!J$8:J$107)*(IFERROR(WEEKNUM('6. Pre Orders'!B$8:B$107,1),0)=ROW()-19)),0)+IFERROR(SUMPRODUCT(('7. Overseas orders'!J$8:J$107)*(IFERROR(WEEKNUM('7. Overseas orders'!B$8:B$107,1),0)=ROW()-19)),0)+IFERROR(SUMPRODUCT(('10. Restock'!J$8:J$107)*(IFERROR(WEEKNUM('10. Restock'!B$8:B$107,1),0)=ROW()-19)),0),IFERROR(SUMPRODUCT(('1. Anime Figures'!J$8:J$107)*(IFERROR(YEAR('1. Anime Figures'!B$8:B$107),0)=(YEAR(TODAY())-12+ROW()-19))),0)+IFERROR(SUMPRODUCT(('2. Mercari and Online store'!J$8:J$107)*(IFERROR(YEAR('2. Mercari and Online store'!B$8:B$107),0)=(YEAR(TODAY())-12+ROW()-19))),0)+IFERROR(SUMPRODUCT(('3. Onhand orders JPY'!J$8:J$107)*(IFERROR(YEAR('3. Onhand orders JPY'!B$8:B$107),0)=(YEAR(TODAY())-12+ROW()-19))),0)+IFERROR(SUMPRODUCT(('4. Live Selling Orders'!J$8:J$107)*(IFERROR(YEAR('4. Live Selling Orders'!B$8:B$107),0)=(YEAR(TODAY())-12+ROW()-19))),0)+IFERROR(SUMPRODUCT(('5. On hand orders PHP'!J$8:J$107)*(IFERROR(YEAR('5. On hand orders PHP'!B$8:B$107),0)=(YEAR(TODAY())-12+ROW()-19))),0)+IFERROR(SUMPRODUCT(('6. Pre Orders'!J$8:J$107)*(IFERROR(YEAR('6. Pre Orders'!B$8:B$107),0)=(YEAR(TODAY())-12+ROW()-19))),0)+IFERROR(SUMPRODUCT(('7. Overseas orders'!J$8:J$107)*(IFERROR(YEAR('7. Overseas orders'!B$8:B$107),0)=(YEAR(TODAY())-12+ROW()-19))),0)+IFERROR(SUMPRODUCT(('10. Restock'!J$8:J$107)*(IFERROR(YEAR('10. Restock'!B$8:B$107),0)=(YEAR(TODAY())-12+ROW()-19))),0))) -> 0
A26: =IF($E$2="Monthly View","June",IF($E$2="Weekly View","Week "&(ROW()-20),YEAR(TODAY())-12+ROW()-19)) -> June | B26: =IF($E$2="Monthly View",IFERROR(SUMIFS('1. Anime Figures'!D$8:D$107,'1. Anime Figures'!C$8:C$107,A26),0)+IFERROR(SUMIFS('2. Mercari and Online store'!D$8:D$107,'2. Mercari and Online store'!C$8:C$107,A26),0)+IFERROR(SUMIFS('3. Onhand orders JPY'!D$8:D$107,'3. Onhand orders JPY'!C$8:C$107,A26),0)+IFERROR(SUMIFS('4. Live Selling Orders'!D$8:D$107,'4. Live Selling Orders'!C$8:C$107,A26),0)+IFERROR(SUMIFS('5. On hand orders PHP'!D$8:D$107,'5. On hand orders PHP'!C$8:C$107,A26),0)+IFERROR(SUMIFS('6. Pre Orders'!D$8:D$107,'6. Pre Orders'!C$8:C$107,A26),0)+IFERROR(SUMIFS('7. Overseas orders'!D$8:D$107,'7. Overseas orders'!C$8:C$107,A26),0)+IFERROR(SUMIFS('10. Restock'!D$8:D$107,'10. Restock'!C$8:C$107,A26),0),IF($E$2="Weekly View",IFERROR(SUMPRODUCT(('1. Anime Figures'!D$8:D$107)*(IFERROR(WEEKNUM('1. Anime Figures'!B$8:B$107,1),0)=ROW()-19)),0)+IFERROR(SUMPRODUCT(('2. Mercari and Online store'!D$8:D$107)*(IFERROR(WEEKNUM('2. Mercari and Online store'!B$8:B$107,1),0)=ROW()-19)),0)+IFERROR(SUMPRODUCT(('3. Onhand orders JPY'!D$8:D$107)*(IFERROR(WEEKNUM('3. Onhand orders JPY'!B$8:B$107,1),0)=ROW()-19)),0)+IFERROR(SUMPRODUCT(('4. Live Selling Orders'!D$8:D$107)*(IFERROR(WEEKNUM('4. Live Selling Orders'!B$8:B$107,1),0)=ROW()-19)),0)+IFERROR(SUMPRODUCT(('5. On hand orders PHP'!D$8:D$107)*(IFERROR(WEEKNUM('5. On hand orders PHP'!B$8:B$107,1),0)=ROW()-19)),0)+IFERROR(SUMPRODUCT(('6. Pre Orders'!D$8:D$107)*(IFERROR(WEEKNUM('6. Pre Orders'!B$8:B$107,1),0)=ROW()-19)),0)+IFERROR(SUMPRODUCT(('7. Overseas orders'!D$8:D$107)*(IFERROR(WEEKNUM('7. Overseas orders'!B$8:B$107,1),0)=ROW()-19)),0)+IFERROR(SUMPRODUCT(('10. Restock'!D$8:D$107)*(IFERROR(WEEKNUM('10. Restock'!B$8:B$107,1),0)=ROW()-19)),0),IFERROR(SUMPRODUCT(('1. Anime Figures'!D$8:D$107)*(IFERROR(YEAR('1. Anime Figures'!B$8:B$107),0)=(YEAR(TODAY())-12+ROW()-19))),0)+IFERROR(SUMPRODUCT(('2. Mercari and Online store'!D$8:D$107)*(IFERROR(YEAR('2. Mercari and Online store'!B$8:B$107),0)=(YEAR(TODAY())-12+ROW()-19))),0)+IFERROR(SUMPRODUCT(('3. Onhand orders JPY'!D$8:D$107)*(IFERROR(YEAR('3. Onhand orders JPY'!B$8:B$107),0)=(YEAR(TODAY())-12+ROW()-19))),0)+IFERROR(SUMPRODUCT(('4. Live Selling Orders'!D$8:D$107)*(IFERROR(YEAR('4. Live Selling Orders'!B$8:B$107),0)=(YEAR(TODAY())-12+ROW()-19))),0)+IFERROR(SUMPRODUCT(('5. On hand orders PHP'!D$8:D$107)*(IFERROR(YEAR('5. On hand orders PHP'!B$8:B$107),0)=(YEAR(TODAY())-12+ROW()-19))),0)+IFERROR(SUMPRODUCT(('6. Pre Orders'!D$8:D$107)*(IFERROR(YEAR('6. Pre Orders'!B$8:B$107),0)=(YEAR(TODAY())-12+ROW()-19))),0)+IFERROR(SUMPRODUCT(('7. Overseas orders'!D$8:D$107)*(IFERROR(YEAR('7. Overseas orders'!B$8:B$107),0)=(YEAR(TODAY())-12+ROW()-19))),0)+IFERROR(SUMPRODUCT(('10. Restock'!D$8:D$107)*(IFERROR(YEAR('10. Restock'!B$8:B$107),0)=(YEAR(TODAY())-12+ROW()-19))),0))) -> 0 | C26: =IF($E$2="Monthly View",IFERROR(SUMIFS('1. Anime Figures'!H$8:H$107,'1. Anime Figures'!C$8:C$107,A26),0)+IFERROR(SUMIFS('2. Mercari and Online store'!H$8:H$107,'2. Mercari and Online store'!C$8:C$107,A26),0)+IFERROR(SUMIFS('3. Onhand orders JPY'!H$8:H$107,'3. Onhand orders JPY'!C$8:C$107,A26),0)+IFERROR(SUMIFS('4. Live Selling Orders'!H$8:H$107,'4. Live Selling Orders'!C$8:C$107,A26),0)+IFERROR(SUMIFS('5. On hand orders PHP'!H$8:H$107,'5. On hand orders PHP'!C$8:C$107,A26),0)+IFERROR(SUMIFS('6. Pre Orders'!H$8:H$107,'6. Pre Orders'!C$8:C$107,A26),0)+IFERROR(SUMIFS('7. Overseas orders'!H$8:H$107,'7. Overseas orders'!C$8:C$107,A26),0)+IFERROR(SUMIFS('10. Restock'!H$8:H$107,'10. Restock'!C$8:C$107,A26),0),IF($E$2="Weekly View",IFERROR(SUMPRODUCT(('1. Anime Figures'!H$8:H$107)*(IFERROR(WEEKNUM('1. Anime Figures'!B$8:B$107,1),0)=ROW()-19)),0)+IFERROR(SUMPRODUCT(('2. Mercari and Online store'!H$8:H$107)*(IFERROR(WEEKNUM('2. Mercari and Online store'!B$8:B$107,1),0)=ROW()-19)),0)+IFERROR(SUMPRODUCT(('3. Onhand orders JPY'!H$8:H$107)*(IFERROR(WEEKNUM('3. Onhand orders JPY'!B$8:B$107,1),0)=ROW()-19)),0)+IFERROR(SUMPRODUCT(('4. Live Selling Orders'!H$8:H$107)*(IFERROR(WEEKNUM('4. Live Selling Orders'!B$8:B$107,1),0)=ROW()-19)),0)+IFERROR(SUMPRODUCT(('5. On hand orders PHP'!H$8:H$107)*(IFERROR(WEEKNUM('5. On hand orders PHP'!B$8:B$107,1),0)=ROW()-19)),0)+IFERROR(SUMPRODUCT(('6. Pre Orders'!H$8:H$107)*(IFERROR(WEEKNUM('6. Pre Orders'!B$8:B$107,1),0)=ROW()-19)),0)+IFERROR(SUMPRODUCT(('7. Overseas orders'!H$8:H$107)*(IFERROR(WEEKNUM('7. Overseas orders'!B$8:B$107,1),0)=ROW()-19)),0)+IFERROR(SUMPRODUCT(('10. Restock'!H$8:H$107)*(IFERROR(WEEKNUM('10. Restock'!B$8:B$107,1),0)=ROW()-19)),0),IFERROR(SUMPRODUCT(('1. Anime Figures'!H$8:H$107)*(IFERROR(YEAR('1. Anime Figures'!B$8:B$107),0)=(YEAR(TODAY())-12+ROW()-19))),0)+IFERROR(SUMPRODUCT(('2. Mercari and Online store'!H$8:H$107)*(IFERROR(YEAR('2. Mercari and Online store'!B$8:B$107),0)=(YEAR(TODAY())-12+ROW()-19))),0)+IFERROR(SUMPRODUCT(('3. Onhand orders JPY'!H$8:H$107)*(IFERROR(YEAR('3. Onhand orders JPY'!B$8:B$107),0)=(YEAR(TODAY())-12+ROW()-19))),0)+IFERROR(SUMPRODUCT(('4. Live Selling Orders'!H$8:H$107)*(IFERROR(YEAR('4. Live Selling Orders'!B$8:B$107),0)=(YEAR(TODAY())-12+ROW()-19))),0)+IFERROR(SUMPRODUCT(('5. On hand orders PHP'!H$8:H$107)*(IFERROR(YEAR('5. On hand orders PHP'!B$8:B$107),0)=(YEAR(TODAY())-12+ROW()-19))),0)+IFERROR(SUMPRODUCT(('6. Pre Orders'!H$8:H$107)*(IFERROR(YEAR('6. Pre Orders'!B$8:B$107),0)=(YEAR(TODAY())-12+ROW()-19))),0)+IFERROR(SUMPRODUCT(('7. Overseas orders'!H$8:H$107)*(IFERROR(YEAR('7. Overseas orders'!B$8:B$107),0)=(YEAR(TODAY())-12+ROW()-19))),0)+IFERROR(SUMPRODUCT(('10. Restock'!H$8:H$107)*(IFERROR(YEAR('10. Restock'!B$8:B$107),0)=(YEAR(TODAY())-12+ROW()-19))),0))) -> 0 | D26: =IF($E$2="Monthly View",IFERROR(SUMIFS('1. Anime Figures'!J$8:J$107,'1. Anime Figures'!C$8:C$107,A26),0)+IFERROR(SUMIFS('2. Mercari and Online store'!J$8:J$107,'2. Mercari and Online store'!C$8:C$107,A26),0)+IFERROR(SUMIFS('3. Onhand orders JPY'!J$8:J$107,'3. Onhand orders JPY'!C$8:C$107,A26),0)+IFERROR(SUMIFS('4. Live Selling Orders'!J$8:J$107,'4. Live Selling Orders'!C$8:C$107,A26),0)+IFERROR(SUMIFS('5. On hand orders PHP'!J$8:J$107,'5. On hand orders PHP'!C$8:C$107,A26),0)+IFERROR(SUMIFS('6. Pre Orders'!J$8:J$107,'6. Pre Orders'!C$8:C$107,A26),0)+IFERROR(SUMIFS('7. Overseas orders'!J$8:J$107,'7. Overseas orders'!C$8:C$107,A26),0)+IFERROR(SUMIFS('10. Restock'!J$8:J$107,'10. Restock'!C$8:C$107,A26),0),IF($E$2="Weekly View",IFERROR(SUMPRODUCT(('1. Anime Figures'!J$8:J$107)*(IFERROR(WEEKNUM('1. Anime Figures'!B$8:B$107,1),0)=ROW()-19)),0)+IFERROR(SUMPRODUCT(('2. Mercari and Online store'!J$8:J$107)*(IFERROR(WEEKNUM('2. Mercari and Online store'!B$8:B$107,1),0)=ROW()-19)),0)+IFERROR(SUMPRODUCT(('3. Onhand orders JPY'!J$8:J$107)*(IFERROR(WEEKNUM('3. Onhand orders JPY'!B$8:B$107,1),0)=ROW()-19)),0)+IFERROR(SUMPRODUCT(('4. Live Selling Orders'!J$8:J$107)*(IFERROR(WEEKNUM('4. Live Selling Orders'!B$8:B$107,1),0)=ROW()-19)),0)+IFERROR(SUMPRODUCT(('5. On hand orders PHP'!J$8:J$107)*(IFERROR(WEEKNUM('5. On hand orders PHP'!B$8:B$107,1),0)=ROW()-19)),0)+IFERROR(SUMPRODUCT(('6. Pre Orders'!J$8:J$107)*(IFERROR(WEEKNUM('6. Pre Orders'!B$8:B$107,1),0)=ROW()-19)),0)+IFERROR(SUMPRODUCT(('7. Overseas orders'!J$8:J$107)*(IFERROR(WEEKNUM('7. Overseas orders'!B$8:B$107,1),0)=ROW()-19)),0)+IFERROR(SUMPRODUCT(('10. Restock'!J$8:J$107)*(IFERROR(WEEKNUM('10. Restock'!B$8:B$107,1),0)=ROW()-19)),0),IFERROR(SUMPRODUCT(('1. Anime Figures'!J$8:J$107)*(IFERROR(YEAR('1. Anime Figures'!B$8:B$107),0)=(YEAR(TODAY())-12+ROW()-19))),0)+IFERROR(SUMPRODUCT(('2. Mercari and Online store'!J$8:J$107)*(IFERROR(YEAR('2. Mercari and Online store'!B$8:B$107),0)=(YEAR(TODAY())-12+ROW()-19))),0)+IFERROR(SUMPRODUCT(('3. Onhand orders JPY'!J$8:J$107)*(IFERROR(YEAR('3. Onhand orders JPY'!B$8:B$107),0)=(YEAR(TODAY())-12+ROW()-19))),0)+IFERROR(SUMPRODUCT(('4. Live Selling Orders'!J$8:J$107)*(IFERROR(YEAR('4. Live Selling Orders'!B$8:B$107),0)=(YEAR(TODAY())-12+ROW()-19))),0)+IFERROR(SUMPRODUCT(('5. On hand orders PHP'!J$8:J$107)*(IFERROR(YEAR('5. On hand orders PHP'!B$8:B$107),0)=(YEAR(TODAY())-12+ROW()-19))),0)+IFERROR(SUMPRODUCT(('6. Pre Orders'!J$8:J$107)*(IFERROR(YEAR('6. Pre Orders'!B$8:B$107),0)=(YEAR(TODAY())-12+ROW()-19))),0)+IFERROR(SUMPRODUCT(('7. Overseas orders'!J$8:J$107)*(IFERROR(YEAR('7. Overseas orders'!B$8:B$107),0)=(YEAR(TODAY())-12+ROW()-19))),0)+IFERROR(SUMPRODUCT(('10. Restock'!J$8:J$107)*(IFERROR(YEAR('10. Restock'!B$8:B$107),0)=(YEAR(TODAY())-12+ROW()-19))),0))) -> 0
A27: =IF($E$2="Monthly View","July",IF($E$2="Weekly View","Week "&(ROW()-20),YEAR(TODAY())-12+ROW()-19)) -> July | B27: =IF($E$2="Monthly View",IFERROR(SUMIFS('1. Anime Figures'!D$8:D$107,'1. Anime Figures'!C$8:C$107,A27),0)+IFERROR(SUMIFS('2. Mercari and Online store'!D$8:D$107,'2. Mercari and Online store'!C$8:C$107,A27),0)+IFERROR(SUMIFS('3. Onhand orders JPY'!D$8:D$107,'3. Onhand orders JPY'!C$8:C$107,A27),0)+IFERROR(SUMIFS('4. Live Selling Orders'!D$8:D$107,'4. Live Selling Orders'!C$8:C$107,A27),0)+IFERROR(SUMIFS('5. On hand orders PHP'!D$8:D$107,'5. On hand orders PHP'!C$8:C$107,A27),0)+IFERROR(SUMIFS('6. Pre Orders'!D$8:D$107,'6. Pre Orders'!C$8:C$107,A27),0)+IFERROR(SUMIFS('7. Overseas orders'!D$8:D$107,'7. Overseas orders'!C$8:C$107,A27),0)+IFERROR(SUMIFS('10. Restock'!D$8:D$107,'10. Restock'!C$8:C$107,A27),0),IF($E$2="Weekly View",IFERROR(SUMPRODUCT(('1. Anime Figures'!D$8:D$107)*(IFERROR(WEEKNUM('1. Anime Figures'!B$8:B$107,1),0)=ROW()-19)),0)+IFERROR(SUMPRODUCT(('2. Mercari and Online store'!D$8:D$107)*(IFERROR(WEEKNUM('2. Mercari and Online store'!B$8:B$107,1),0)=ROW()-19)),0)+IFERROR(SUMPRODUCT(('3. Onhand orders JPY'!D$8:D$107)*(IFERROR(WEEKNUM('3. Onhand orders JPY'!B$8:B$107,1),0)=ROW()-19)),0)+IFERROR(SUMPRODUCT(('4. Live Selling Orders'!D$8:D$107)*(IFERROR(WEEKNUM('4. Live Selling Orders'!B$8:B$107,1),0)=ROW()-19)),0)+IFERROR(SUMPRODUCT(('5. On hand orders PHP'!D$8:D$107)*(IFERROR(WEEKNUM('5. On hand orders PHP'!B$8:B$107,1),0)=ROW()-19)),0)+IFERROR(SUMPRODUCT(('6. Pre Orders'!D$8:D$107)*(IFERROR(WEEKNUM('6. Pre Orders'!B$8:B$107,1),0)=ROW()-19)),0)+IFERROR(SUMPRODUCT(('7. Overseas orders'!D$8:D$107)*(IFERROR(WEEKNUM('7. Overseas orders'!B$8:B$107,1),0)=ROW()-19)),0)+IFERROR(SUMPRODUCT(('10. Restock'!D$8:D$107)*(IFERROR(WEEKNUM('10. Restock'!B$8:B$107,1),0)=ROW()-19)),0),IFERROR(SUMPRODUCT(('1. Anime Figures'!D$8:D$107)*(IFERROR(YEAR('1. Anime Figures'!B$8:B$107),0)=(YEAR(TODAY())-12+ROW()-19))),0)+IFERROR(SUMPRODUCT(('2. Mercari and Online store'!D$8:D$107)*(IFERROR(YEAR('2. Mercari and Online store'!B$8:B$107),0)=(YEAR(TODAY())-12+ROW()-19))),0)+IFERROR(SUMPRODUCT(('3. Onhand orders JPY'!D$8:D$107)*(IFERROR(YEAR('3. Onhand orders JPY'!B$8:B$107),0)=(YEAR(TODAY())-12+ROW()-19))),0)+IFERROR(SUMPRODUCT(('4. Live Selling Orders'!D$8:D$107)*(IFERROR(YEAR('4. Live Selling Orders'!B$8:B$107),0)=(YEAR(TODAY())-12+ROW()-19))),0)+IFERROR(SUMPRODUCT(('5. On hand orders PHP'!D$8:D$107)*(IFERROR(YEAR('5. On hand orders PHP'!B$8:B$107),0)=(YEAR(TODAY())-12+ROW()-19))),0)+IFERROR(SUMPRODUCT(('6. Pre Orders'!D$8:D$107)*(IFERROR(YEAR('6. Pre Orders'!B$8:B$107),0)=(YEAR(TODAY())-12+ROW()-19))),0)+IFERROR(SUMPRODUCT(('7. Overseas orders'!D$8:D$107)*(IFERROR(YEAR('7. Overseas orders'!B$8:B$107),0)=(YEAR(TODAY())-12+ROW()-19))),0)+IFERROR(SUMPRODUCT(('10. Restock'!D$8:D$107)*(IFERROR(YEAR('10. Restock'!B$8:B$107),0)=(YEAR(TODAY())-12+ROW()-19))),0))) -> 0 | C27: =IF($E$2="Monthly View",IFERROR(SUMIFS('1. Anime Figures'!H$8:H$107,'1. Anime Figures'!C$8:C$107,A27),0)+IFERROR(SUMIFS('2. Mercari and Online store'!H$8:H$107,'2. Mercari and Online store'!C$8:C$107,A27),0)+IFERROR(SUMIFS('3. Onhand orders JPY'!H$8:H$107,'3. Onhand orders JPY'!C$8:C$107,A27),0)+IFERROR(SUMIFS('4. Live Selling Orders'!H$8:H$107,'4. Live Selling Orders'!C$8:C$107,A27),0)+IFERROR(SUMIFS('5. On hand orders PHP'!H$8:H$107,'5. On hand orders PHP'!C$8:C$107,A27),0)+IFERROR(SUMIFS('6. Pre Orders'!H$8:H$107,'6. Pre Orders'!C$8:C$107,A27),0)+IFERROR(SUMIFS('7. Overseas orders'!H$8:H$107,'7. Overseas orders'!C$8:C$107,A27),0)+IFERROR(SUMIFS('10. Restock'!H$8:H$107,'10. Restock'!C$8:C$107,A27),0),IF($E$2="Weekly View",IFERROR(SUMPRODUCT(('1. Anime Figures'!H$8:H$107)*(IFERROR(WEEKNUM('1. Anime Figures'!B$8:B$107,1),0)=ROW()-19)),0)+IFERROR(SUMPRODUCT(('2. Mercari and Online store'!H$8:H$107)*(IFERROR(WEEKNUM('2. Mercari and Online store'!B$8:B$107,1),0)=ROW()-19)),0)+IFERROR(SUMPRODUCT(('3. Onhand orders JPY'!H$8:H$107)*(IFERROR(WEEKNUM('3. Onhand orders JPY'!B$8:B$107,1),0)=ROW()-19)),0)+IFERROR(SUMPRODUCT(('4. Live Selling Orders'!H$8:H$107)*(IFERROR(WEEKNUM('4. Live Selling Orders'!B$8:B$107,1),0)=ROW()-19)),0)+IFERROR(SUMPRODUCT(('5. On hand orders PHP'!H$8:H$107)*(IFERROR(WEEKNUM('5. On hand orders PHP'!B$8:B$107,1),0)=ROW()-19)),0)+IFERROR(SUMPRODUCT(('6. Pre Orders'!H$8:H$107)*(IFERROR(WEEKNUM('6. Pre Orders'!B$8:B$107,1),0)=ROW()-19)),0)+IFERROR(SUMPRODUCT(('7. Overseas orders'!H$8:H$107)*(IFERROR(WEEKNUM('7. Overseas orders'!B$8:B$107,1),0)=ROW()-19)),0)+IFERROR(SUMPRODUCT(('10. Restock'!H$8:H$107)*(IFERROR(WEEKNUM('10. Restock'!B$8:B$107,1),0)=ROW()-19)),0),IFERROR(SUMPRODUCT(('1. Anime Figures'!H$8:H$107)*(IFERROR(YEAR('1. Anime Figures'!B$8:B$107),0)=(YEAR(TODAY())-12+ROW()-19))),0)+IFERROR(SUMPRODUCT(('2. Mercari and Online store'!H$8:H$107)*(IFERROR(YEAR('2. Mercari and Online store'!B$8:B$107),0)=(YEAR(TODAY())-12+ROW()-19))),0)+IFERROR(SUMPRODUCT(('3. Onhand orders JPY'!H$8:H$107)*(IFERROR(YEAR('3. Onhand orders JPY'!B$8:B$107),0)=(YEAR(TODAY())-12+ROW()-19))),0)+IFERROR(SUMPRODUCT(('4. Live Selling Orders'!H$8:H$107)*(IFERROR(YEAR('4. Live Selling Orders'!B$8:B$107),0)=(YEAR(TODAY())-12+ROW()-19))),0)+IFERROR(SUMPRODUCT(('5. On hand orders PHP'!H$8:H$107)*(IFERROR(YEAR('5. On hand orders PHP'!B$8:B$107),0)=(YEAR(TODAY())-12+ROW()-19))),0)+IFERROR(SUMPRODUCT(('6. Pre Orders'!H$8:H$107)*(IFERROR(YEAR('6. Pre Orders'!B$8:B$107),0)=(YEAR(TODAY())-12+ROW()-19))),0)+IFERROR(SUMPRODUCT(('7. Overseas orders'!H$8:H$107)*(IFERROR(YEAR('7. Overseas orders'!B$8:B$107),0)=(YEAR(TODAY())-12+ROW()-19))),0)+IFERROR(SUMPRODUCT(('10. Restock'!H$8:H$107)*(IFERROR(YEAR('10. Restock'!B$8:B$107),0)=(YEAR(TODAY())-12+ROW()-19))),0))) -> 0 | D27: =IF($E$2="Monthly View",IFERROR(SUMIFS('1. Anime Figures'!J$8:J$107,'1. Anime Figures'!C$8:C$107,A27),0)+IFERROR(SUMIFS('2. Mercari and Online store'!J$8:J$107,'2. Mercari and Online store'!C$8:C$107,A27),0)+IFERROR(SUMIFS('3. Onhand orders JPY'!J$8:J$107,'3. Onhand orders JPY'!C$8:C$107,A27),0)+IFERROR(SUMIFS('4. Live Selling Orders'!J$8:J$107,'4. Live Selling Orders'!C$8:C$107,A27),0)+IFERROR(SUMIFS('5. On hand orders PHP'!J$8:J$107,'5. On hand orders PHP'!C$8:C$107,A27),0)+IFERROR(SUMIFS('6. Pre Orders'!J$8:J$107,'6. Pre Orders'!C$8:C$107,A27),0)+IFERROR(SUMIFS('7. Overseas orders'!J$8:J$107,'7. Overseas orders'!C$8:C$107,A27),0)+IFERROR(SUMIFS('10. Restock'!J$8:J$107,'10. Restock'!C$8:C$107,A27),0),IF($E$2="Weekly View",IFERROR(SUMPRODUCT(('1. Anime Figures'!J$8:J$107)*(IFERROR(WEEKNUM('1. Anime Figures'!B$8:B$107,1),0)=ROW()-19)),0)+IFERROR(SUMPRODUCT(('2. Mercari and Online store'!J$8:J$107)*(IFERROR(WEEKNUM('2. Mercari and Online store'!B$8:B$107,1),0)=ROW()-19)),0)+IFERROR(SUMPRODUCT(('3. Onhand orders JPY'!J$8:J$107)*(IFERROR(WEEKNUM('3. Onhand orders JPY'!B$8:B$107,1),0)=ROW()-19)),0)+IFERROR(SUMPRODUCT(('4. Live Selling Orders'!J$8:J$107)*(IFERROR(WEEKNUM('4. Live Selling Orders'!B$8:B$107,1),0)=ROW()-19)),0)+IFERROR(SUMPRODUCT(('5. On hand orders PHP'!J$8:J$107)*(IFERROR(WEEKNUM('5. On hand orders PHP'!B$8:B$107,1),0)=ROW()-19)),0)+IFERROR(SUMPRODUCT(('6. Pre Orders'!J$8:J$107)*(IFERROR(WEEKNUM('6. Pre Orders'!B$8:B$107,1),0)=ROW()-19)),0)+IFERROR(SUMPRODUCT(('7. Overseas orders'!J$8:J$107)*(IFERROR(WEEKNUM('7. Overseas orders'!B$8:B$107,1),0)=ROW()-19)),0)+IFERROR(SUMPRODUCT(('10. Restock'!J$8:J$107)*(IFERROR(WEEKNUM('10. Restock'!B$8:B$107,1),0)=ROW()-19)),0),IFERROR(SUMPRODUCT(('1. Anime Figures'!J$8:J$107)*(IFERROR(YEAR('1. Anime Figures'!B$8:B$107),0)=(YEAR(TODAY())-12+ROW()-19))),0)+IFERROR(SUMPRODUCT(('2. Mercari and Online store'!J$8:J$107)*(IFERROR(YEAR('2. Mercari and Online store'!B$8:B$107),0)=(YEAR(TODAY())-12+ROW()-19))),0)+IFERROR(SUMPRODUCT(('3. Onhand orders JPY'!J$8:J$107)*(IFERROR(YEAR('3. Onhand orders JPY'!B$8:B$107),0)=(YEAR(TODAY())-12+ROW()-19))),0)+IFERROR(SUMPRODUCT(('4. Live Selling Orders'!J$8:J$107)*(IFERROR(YEAR('4. Live Selling Orders'!B$8:B$107),0)=(YEAR(TODAY())-12+ROW()-19))),0)+IFERROR(SUMPRODUCT(('5. On hand orders PHP'!J$8:J$107)*(IFERROR(YEAR('5. On hand orders PHP'!B$8:B$107),0)=(YEAR(TODAY())-12+ROW()-19))),0)+IFERROR(SUMPRODUCT(('6. Pre Orders'!J$8:J$107)*(IFERROR(YEAR('6. Pre Orders'!B$8:B$107),0)=(YEAR(TODAY())-12+ROW()-19))),0)+IFERROR(SUMPRODUCT(('7. Overseas orders'!J$8:J$107)*(IFERROR(YEAR('7. Overseas orders'!B$8:B$107),0)=(YEAR(TODAY())-12+ROW()-19))),0)+IFERROR(SUMPRODUCT(('10. Restock'!J$8:J$107)*(IFERROR(YEAR('10. Restock'!B$8:B$107),0)=(YEAR(TODAY())-12+ROW()-19))),0))) -> 0
A28: =IF($E$2="Monthly View","August",IF($E$2="Weekly View","Week "&(ROW()-20),YEAR(TODAY())-12+ROW()-19)) -> August | B28: =IF($E$2="Monthly View",IFERROR(SUMIFS('1. Anime Figures'!D$8:D$107,'1. Anime Figures'!C$8:C$107,A28),0)+IFERROR(SUMIFS('2. Mercari and Online store'!D$8:D$107,'2. Mercari and Online store'!C$8:C$107,A28),0)+IFERROR(SUMIFS('3. Onhand orders JPY'!D$8:D$107,'3. Onhand orders JPY'!C$8:C$107,A28),0)+IFERROR(SUMIFS('4. Live Selling Orders'!D$8:D$107,'4. Live Selling Orders'!C$8:C$107,A28),0)+IFERROR(SUMIFS('5. On hand orders PHP'!D$8:D$107,'5. On hand orders PHP'!C$8:C$107,A28),0)+IFERROR(SUMIFS('6. Pre Orders'!D$8:D$107,'6. Pre Orders'!C$8:C$107,A28),0)+IFERROR(SUMIFS('7. Overseas orders'!D$8:D$107,'7. Overseas orders'!C$8:C$107,A28),0)+IFERROR(SUMIFS('10. Restock'!D$8:D$107,'10. Restock'!C$8:C$107,A28),0),IF($E$2="Weekly View",IFERROR(SUMPRODUCT(('1. Anime Figures'!D$8:D$107)*(IFERROR(WEEKNUM('1. Anime Figures'!B$8:B$107,1),0)=ROW()-19)),0)+IFERROR(SUMPRODUCT(('2. Mercari and Online store'!D$8:D$107)*(IFERROR(WEEKNUM('2. Mercari and Online store'!B$8:B$107,1),0)=ROW()-19)),0)+IFERROR(SUMPRODUCT(('3. Onhand orders JPY'!D$8:D$107)*(IFERROR(WEEKNUM('3. Onhand orders JPY'!B$8:B$107,1),0)=ROW()-19)),0)+IFERROR(SUMPRODUCT(('4. Live Selling Orders'!D$8:D$107)*(IFERROR(WEEKNUM('4. Live Selling Orders'!B$8:B$107,1),0)=ROW()-19)),0)+IFERROR(SUMPRODUCT(('5. On hand orders PHP'!D$8:D$107)*(IFERROR(WEEKNUM('5. On hand orders PHP'!B$8:B$107,1),0)=ROW()-19)),0)+IFERROR(SUMPRODUCT(('6. Pre Orders'!D$8:D$107)*(IFERROR(WEEKNUM('6. Pre Orders'!B$8:B$107,1),0)=ROW()-19)),0)+IFERROR(SUMPRODUCT(('7. Overseas orders'!D$8:D$107)*(IFERROR(WEEKNUM('7. Overseas orders'!B$8:B$107,1),0)=ROW()-19)),0)+IFERROR(SUMPRODUCT(('10. Restock'!D$8:D$107)*(IFERROR(WEEKNUM('10. Restock'!B$8:B$107,1),0)=ROW()-19)),0),IFERROR(SUMPRODUCT(('1. Anime Figures'!D$8:D$107)*(IFERROR(YEAR('1. Anime Figures'!B$8:B$107),0)=(YEAR(TODAY())-12+ROW()-19))),0)+IFERROR(SUMPRODUCT(('2. Mercari and Online store'!D$8:D$107)*(IFERROR(YEAR('2. Mercari and Online store'!B$8:B$107),0)=(YEAR(TODAY())-12+ROW()-19))),0)+IFERROR(SUMPRODUCT(('3. Onhand orders JPY'!D$8:D$107)*(IFERROR(YEAR('3. Onhand orders JPY'!B$8:B$107),0)=(YEAR(TODAY())-12+ROW()-19))),0)+IFERROR(SUMPRODUCT(('4. Live Selling Orders'!D$8:D$107)*(IFERROR(YEAR('4. Live Selling Orders'!B$8:B$107),0)=(YEAR(TODAY())-12+ROW()-19))),0)+IFERROR(SUMPRODUCT(('5. On hand orders PHP'!D$8:D$107)*(IFERROR(YEAR('5. On hand orders PHP'!B$8:B$107),0)=(YEAR(TODAY())-12+ROW()-19))),0)+IFERROR(SUMPRODUCT(('6. Pre Orders'!D$8:D$107)*(IFERROR(YEAR('6. Pre Orders'!B$8:B$107),0)=(YEAR(TODAY())-12+ROW()-19))),0)+IFERROR(SUMPRODUCT(('7. Overseas orders'!D$8:D$107)*(IFERROR(YEAR('7. Overseas orders'!B$8:B$107),0)=(YEAR(TODAY())-12+ROW()-19))),0)+IFERROR(SUMPRODUCT(('10. Restock'!D$8:D$107)*(IFERROR(YEAR('10. Restock'!B$8:B$107),0)=(YEAR(TODAY())-12+ROW()-19))),0))) -> 0 | C28: =IF($E$2="Monthly View",IFERROR(SUMIFS('1. Anime Figures'!H$8:H$107,'1. Anime Figures'!C$8:C$107,A28),0)+IFERROR(SUMIFS('2. Mercari and Online store'!H$8:H$107,'2. Mercari and Online store'!C$8:C$107,A28),0)+IFERROR(SUMIFS('3. Onhand orders JPY'!H$8:H$107,'3. Onhand orders JPY'!C$8:C$107,A28),0)+IFERROR(SUMIFS('4. Live Selling Orders'!H$8:H$107,'4. Live Selling Orders'!C$8:C$107,A28),0)+IFERROR(SUMIFS('5. On hand orders PHP'!H$8:H$107,'5. On hand orders PHP'!C$8:C$107,A28),0)+IFERROR(SUMIFS('6. Pre Orders'!H$8:H$107,'6. Pre Orders'!C$8:C$107,A28),0)+IFERROR(SUMIFS('7. Overseas orders'!H$8:H$107,'7. Overseas orders'!C$8:C$107,A28),0)+IFERROR(SUMIFS('10. Restock'!H$8:H$107,'10. Restock'!C$8:C$107,A28),0),IF($E$2="Weekly View",IFERROR(SUMPRODUCT(('1. Anime Figures'!H$8:H$107)*(IFERROR(WEEKNUM('1. Anime Figures'!B$8:B$107,1),0)=ROW()-19)),0)+IFERROR(SUMPRODUCT(('2. Mercari and Online store'!H$8:H$107)*(IFERROR(WEEKNUM('2. Mercari and Online store'!B$8:B$107,1),0)=ROW()-19)),0)+IFERROR(SUMPRODUCT(('3. Onhand orders JPY'!H$8:H$107)*(IFERROR(WEEKNUM('3. Onhand orders JPY'!B$8:B$107,1),0)=ROW()-19)),0)+IFERROR(SUMPRODUCT(('4. Live Selling Orders'!H$8:H$107)*(IFERROR(WEEKNUM('4. Live Selling Orders'!B$8:B$107,1),0)=ROW()-19)),0)+IFERROR(SUMPRODUCT(('5. On hand orders PHP'!H$8:H$107)*(IFERROR(WEEKNUM('5. On hand orders PHP'!B$8:B$107,1),0)=ROW()-19)),0)+IFERROR(SUMPRODUCT(('6. Pre Orders'!H$8:H$107)*(IFERROR(WEEKNUM('6. Pre Orders'!B$8:B$107,1),0)=ROW()-19)),0)+IFERROR(SUMPRODUCT(('7. Overseas orders'!H$8:H$107)*(IFERROR(WEEKNUM('7. Overseas orders'!B$8:B$107,1),0)=ROW()-19)),0)+IFERROR(SUMPRODUCT(('10. Restock'!H$8:H$107)*(IFERROR(WEEKNUM('10. Restock'!B$8:B$107,1),0)=ROW()-19)),0),IFERROR(SUMPRODUCT(('1. Anime Figures'!H$8:H$107)*(IFERROR(YEAR('1. Anime Figures'!B$8:B$107),0)=(YEAR(TODAY())-12+ROW()-19))),0)+IFERROR(SUMPRODUCT(('2. Mercari and Online store'!H$8:H$107)*(IFERROR(YEAR('2. Mercari and Online store'!B$8:B$107),0)=(YEAR(TODAY())-12+ROW()-19))),0)+IFERROR(SUMPRODUCT(('3. Onhand orders JPY'!H$8:H$107)*(IFERROR(YEAR('3. Onhand orders JPY'!B$8:B$107),0)=(YEAR(TODAY())-12+ROW()-19))),0)+IFERROR(SUMPRODUCT(('4. Live Selling Orders'!H$8:H$107)*(IFERROR(YEAR('4. Live Selling Orders'!B$8:B$107),0)=(YEAR(TODAY())-12+ROW()-19))),0)+IFERROR(SUMPRODUCT(('5. On hand orders PHP'!H$8:H$107)*(IFERROR(YEAR('5. On hand orders PHP'!B$8:B$107),0)=(YEAR(TODAY())-12+ROW()-19))),0)+IFERROR(SUMPRODUCT(('6. Pre Orders'!H$8:H$107)*(IFERROR(YEAR('6. Pre Orders'!B$8:B$107),0)=(YEAR(TODAY())-12+ROW()-19))),0)+IFERROR(SUMPRODUCT(('7. Overseas orders'!H$8:H$107)*(IFERROR(YEAR('7. Overseas orders'!B$8:B$107),0)=(YEAR(TODAY())-12+ROW()-19))),0)+IFERROR(SUMPRODUCT(('10. Restock'!H$8:H$107)*(IFERROR(YEAR('10. Restock'!B$8:B$107),0)=(YEAR(TODAY())-12+ROW()-19))),0))) -> 0 | D28: =IF($E$2="Monthly View",IFERROR(SUMIFS('1. Anime Figures'!J$8:J$107,'1. Anime Figures'!C$8:C$107,A28),0)+IFERROR(SUMIFS('2. Mercari and Online store'!J$8:J$107,'2. Mercari and Online store'!C$8:C$107,A28),0)+IFERROR(SUMIFS('3. Onhand orders JPY'!J$8:J$107,'3. Onhand orders JPY'!C$8:C$107,A28),0)+IFERROR(SUMIFS('4. Live Selling Orders'!J$8:J$107,'4. Live Selling Orders'!C$8:C$107,A28),0)+IFERROR(SUMIFS('5. On hand orders PHP'!J$8:J$107,'5. On hand orders PHP'!C$8:C$107,A28),0)+IFERROR(SUMIFS('6. Pre Orders'!J$8:J$107,'6. Pre Orders'!C$8:C$107,A28),0)+IFERROR(SUMIFS('7. Overseas orders'!J$8:J$107,'7. Overseas orders'!C$8:C$107,A28),0)+IFERROR(SUMIFS('10. Restock'!J$8:J$107,'10. Restock'!C$8:C$107,A28),0),IF($E$2="Weekly View",IFERROR(SUMPRODUCT(('1. Anime Figures'!J$8:J$107)*(IFERROR(WEEKNUM('1. Anime Figures'!B$8:B$107,1),0)=ROW()-19)),0)+IFERROR(SUMPRODUCT(('2. Mercari and Online store'!J$8:J$107)*(IFERROR(WEEKNUM('2. Mercari and Online store'!B$8:B$107,1),0)=ROW()-19)),0)+IFERROR(SUMPRODUCT(('3. Onhand orders JPY'!J$8:J$107)*(IFERROR(WEEKNUM('3. Onhand orders JPY'!B$8:B$107,1),0)=ROW()-19)),0)+IFERROR(SUMPRODUCT(('4. Live Selling Orders'!J$8:J$107)*(IFERROR(WEEKNUM('4. Live Selling Orders'!B$8:B$107,1),0)=ROW()-19)),0)+IFERROR(SUMPRODUCT(('5. On hand orders PHP'!J$8:J$107)*(IFERROR(WEEKNUM('5. On hand orders PHP'!B$8:B$107,1),0)=ROW()-19)),0)+IFERROR(SUMPRODUCT(('6. Pre Orders'!J$8:J$107)*(IFERROR(WEEKNUM('6. Pre Orders'!B$8:B$107,1),0)=ROW()-19)),0)+IFERROR(SUMPRODUCT(('7. Overseas orders'!J$8:J$107)*(IFERROR(WEEKNUM('7. Overseas orders'!B$8:B$107,1),0)=ROW()-19)),0)+IFERROR(SUMPRODUCT(('10. Restock'!J$8:J$107)*(IFERROR(WEEKNUM('10. Restock'!B$8:B$107,1),0)=ROW()-19)),0),IFERROR(SUMPRODUCT(('1. Anime Figures'!J$8:J$107)*(IFERROR(YEAR('1. Anime Figures'!B$8:B$107),0)=(YEAR(TODAY())-12+ROW()-19))),0)+IFERROR(SUMPRODUCT(('2. Mercari and Online store'!J$8:J$107)*(IFERROR(YEAR('2. Mercari and Online store'!B$8:B$107),0)=(YEAR(TODAY())-12+ROW()-19))),0)+IFERROR(SUMPRODUCT(('3. Onhand orders JPY'!J$8:J$107)*(IFERROR(YEAR('3. Onhand orders JPY'!B$8:B$107),0)=(YEAR(TODAY())-12+ROW()-19))),0)+IFERROR(SUMPRODUCT(('4. Live Selling Orders'!J$8:J$107)*(IFERROR(YEAR('4. Live Selling Orders'!B$8:B$107),0)=(YEAR(TODAY())-12+ROW()-19))),0)+IFERROR(SUMPRODUCT(('5. On hand orders PHP'!J$8:J$107)*(IFERROR(YEAR('5. On hand orders PHP'!B$8:B$107),0)=(YEAR(TODAY())-12+ROW()-19))),0)+IFERROR(SUMPRODUCT(('6. Pre Orders'!J$8:J$107)*(IFERROR(YEAR('6. Pre Orders'!B$8:B$107),0)=(YEAR(TODAY())-12+ROW()-19))),0)+IFERROR(SUMPRODUCT(('7. Overseas orders'!J$8:J$107)*(IFERROR(YEAR('7. Overseas orders'!B$8:B$107),0)=(YEAR(TODAY())-12+ROW()-19))),0)+IFERROR(SUMPRODUCT(('10. Restock'!J$8:J$107)*(IFERROR(YEAR('10. Restock'!B$8:B$107),0)=(YEAR(TODAY())-12+ROW()-19))),0))) -> 0
A29: =IF($E$2="Monthly View","September",IF($E$2="Weekly View","Week "&(ROW()-20),YEAR(TODAY())-12+ROW()-19)) -> September | B29: =IF($E$2="Monthly View",IFERROR(SUMIFS('1. Anime Figures'!D$8:D$107,'1. Anime Figures'!C$8:C$107,A29),0)+IFERROR(SUMIFS('2. Mercari and Online store'!D$8:D$107,'2. Mercari and Online store'!C$8:C$107,A29),0)+IFERROR(SUMIFS('3. Onhand orders JPY'!D$8:D$107,'3. Onhand orders JPY'!C$8:C$107,A29),0)+IFERROR(SUMIFS('4. Live Selling Orders'!D$8:D$107,'4. Live Selling Orders'!C$8:C$107,A29),0)+IFERROR(SUMIFS('5. On hand orders PHP'!D$8:D$107,'5. On hand orders PHP'!C$8:C$107,A29),0)+IFERROR(SUMIFS('6. Pre Orders'!D$8:D$107,'6. Pre Orders'!C$8:C$107,A29),0)+IFERROR(SUMIFS('7. Overseas orders'!D$8:D$107,'7. Overseas orders'!C$8:C$107,A29),0)+IFERROR(SUMIFS('10. Restock'!D$8:D$107,'10. Restock'!C$8:C$107,A29),0),IF($E$2="Weekly View",IFERROR(SUMPRODUCT(('1. Anime Figures'!D$8:D$107)*(IFERROR(WEEKNUM('1. Anime Figures'!B$8:B$107,1),0)=ROW()-19)),0)+IFERROR(SUMPRODUCT(('2. Mercari and Online store'!D$8:D$107)*(IFERROR(WEEKNUM('2. Mercari and Online store'!B$8:B$107,1),0)=ROW()-19)),0)+IFERROR(SUMPRODUCT(('3. Onhand orders JPY'!D$8:D$107)*(IFERROR(WEEKNUM('3. Onhand orders JPY'!B$8:B$107,1),0)=ROW()-19)),0)+IFERROR(SUMPRODUCT(('4. Live Selling Orders'!D$8:D$107)*(IFERROR(WEEKNUM('4. Live Selling Orders'!B$8:B$107,1),0)=ROW()-19)),0)+IFERROR(SUMPRODUCT(('5. On hand orders PHP'!D$8:D$107)*(IFERROR(WEEKNUM('5. On hand orders PHP'!B$8:B$107,1),0)=ROW()-19)),0)+IFERROR(SUMPRODUCT(('6. Pre Orders'!D$8:D$107)*(IFERROR(WEEKNUM('6. Pre Orders'!B$8:B$107,1),0)=ROW()-19)),0)+IFERROR(SUMPRODUCT(('7. Overseas orders'!D$8:D$107)*(IFERROR(WEEKNUM('7. Overseas orders'!B$8:B$107,1),0)=ROW()-19)),0)+IFERROR(SUMPRODUCT(('10. Restock'!D$8:D$107)*(IFERROR(WEEKNUM('10. Restock'!B$8:B$107,1),0)=ROW()-19)),0),IFERROR(SUMPRODUCT(('1. Anime Figures'!D$8:D$107)*(IFERROR(YEAR('1. Anime Figures'!B$8:B$107),0)=(YEAR(TODAY())-12+ROW()-19))),0)+IFERROR(SUMPRODUCT(('2. Mercari and Online store'!D$8:D$107)*(IFERROR(YEAR('2. Mercari and Online store'!B$8:B$107),0)=(YEAR(TODAY())-12+ROW()-19))),0)+IFERROR(SUMPRODUCT(('3. Onhand orders JPY'!D$8:D$107)*(IFERROR(YEAR('3. Onhand orders JPY'!B$8:B$107),0)=(YEAR(TODAY())-12+ROW()-19))),0)+IFERROR(SUMPRODUCT(('4. Live Selling Orders'!D$8:D$107)*(IFERROR(YEAR('4. Live Selling Orders'!B$8:B$107),0)=(YEAR(TODAY())-12+ROW()-19))),0)+IFERROR(SUMPRODUCT(('5. On hand orders PHP'!D$8:D$107)*(IFERROR(YEAR('5. On hand orders PHP'!B$8:B$107),0)=(YEAR(TODAY())-12+ROW()-19))),0)+IFERROR(SUMPRODUCT(('6. Pre Orders'!D$8:D$107)*(IFERROR(YEAR('6. Pre Orders'!B$8:B$107),0)=(YEAR(TODAY())-12+ROW()-19))),0)+IFERROR(SUMPRODUCT(('7. Overseas orders'!D$8:D$107)*(IFERROR(YEAR('7. Overseas orders'!B$8:B$107),0)=(YEAR(TODAY())-12+ROW()-19))),0)+IFERROR(SUMPRODUCT(('10. Restock'!D$8:D$107)*(IFERROR(YEAR('10. Restock'!B$8:B$107),0)=(YEAR(TODAY())-12+ROW()-19))),0))) -> 0 | C29: =IF($E$2="Monthly View",IFERROR(SUMIFS('1. Anime Figures'!H$8:H$107,'1. Anime Figures'!C$8:C$107,A29),0)+IFERROR(SUMIFS('2. Mercari and Online store'!H$8:H$107,'2. Mercari and Online store'!C$8:C$107,A29),0)+IFERROR(SUMIFS('3. Onhand orders JPY'!H$8:H$107,'3. Onhand orders JPY'!C$8:C$107,A29),0)+IFERROR(SUMIFS('4. Live Selling Orders'!H$8:H$107,'4. Live Selling Orders'!C$8:C$107,A29),0)+IFERROR(SUMIFS('5. On hand orders PHP'!H$8:H$107,'5. On hand orders PHP'!C$8:C$107,A29),0)+IFERROR(SUMIFS('6. Pre Orders'!H$8:H$107,'6. Pre Orders'!C$8:C$107,A29),0)+IFERROR(SUMIFS('7. Overseas orders'!H$8:H$107,'7. Overseas orders'!C$8:C$107,A29),0)+IFERROR(SUMIFS('10. Restock'!H$8:H$107,'10. Restock'!C$8:C$107,A29),0),IF($E$2="Weekly View",IFERROR(SUMPRODUCT(('1. Anime Figures'!H$8:H$107)*(IFERROR(WEEKNUM('1. Anime Figures'!B$8:B$107,1),0)=ROW()-19)),0)+IFERROR(SUMPRODUCT(('2. Mercari and Online store'!H$8:H$107)*(IFERROR(WEEKNUM('2. Mercari and Online store'!B$8:B$107,1),0)=ROW()-19)),0)+IFERROR(SUMPRODUCT(('3. Onhand orders JPY'!H$8:H$107)*(IFERROR(WEEKNUM('3. Onhand orders JPY'!B$8:B$107,1),0)=ROW()-19)),0)+IFERROR(SUMPRODUCT(('4. Live Selling Orders'!H$8:H$107)*(IFERROR(WEEKNUM('4. Live Selling Orders'!B$8:B$107,1),0)=ROW()-19)),0)+IFERROR(SUMPRODUCT(('5. On hand orders PHP'!H$8:H$107)*(IFERROR(WEEKNUM('5. On hand orders PHP'!B$8:B$107,1),0)=ROW()-19)),0)+IFERROR(SUMPRODUCT(('6. Pre Orders'!H$8:H$107)*(IFERROR(WEEKNUM('6. Pre Orders'!B$8:B$107,1),0)=ROW()-19)),0)+IFERROR(SUMPRODUCT(('7. Overseas orders'!H$8:H$107)*(IFERROR(WEEKNUM('7. Overseas orders'!B$8:B$107,1),0)=ROW()-19)),0)+IFERROR(SUMPRODUCT(('10. Restock'!H$8:H$107)*(IFERROR(WEEKNUM('10. Restock'!B$8:B$107,1),0)=ROW()-19)),0),IFERROR(SUMPRODUCT(('1. Anime Figures'!H$8:H$107)*(IFERROR(YEAR('1. Anime Figures'!B$8:B$107),0)=(YEAR(TODAY())-12+ROW()-19))),0)+IFERROR(SUMPRODUCT(('2. Mercari and Online store'!H$8:H$107)*(IFERROR(YEAR('2. Mercari and Online store'!B$8:B$107),0)=(YEAR(TODAY())-12+ROW()-19))),0)+IFERROR(SUMPRODUCT(('3. Onhand orders JPY'!H$8:H$107)*(IFERROR(YEAR('3. Onhand orders JPY'!B$8:B$107),0)=(YEAR(TODAY())-12+ROW()-19))),0)+IFERROR(SUMPRODUCT(('4. Live Selling Orders'!H$8:H$107)*(IFERROR(YEAR('4. Live Selling Orders'!B$8:B$107),0)=(YEAR(TODAY())-12+ROW()-19))),0)+IFERROR(SUMPRODUCT(('5. On hand orders PHP'!H$8:H$107)*(IFERROR(YEAR('5. On hand orders PHP'!B$8:B$107),0)=(YEAR(TODAY())-12+ROW()-19))),0)+IFERROR(SUMPRODUCT(('6. Pre Orders'!H$8:H$107)*(IFERROR(YEAR('6. Pre Orders'!B$8:B$107),0)=(YEAR(TODAY())-12+ROW()-19))),0)+IFERROR(SUMPRODUCT(('7. Overseas orders'!H$8:H$107)*(IFERROR(YEAR('7. Overseas orders'!B$8:B$107),0)=(YEAR(TODAY())-12+ROW()-19))),0)+IFERROR(SUMPRODUCT(('10. Restock'!H$8:H$107)*(IFERROR(YEAR('10. Restock'!B$8:B$107),0)=(YEAR(TODAY())-12+ROW()-19))),0))) -> 0 | D29: =IF($E$2="Monthly View",IFERROR(SUMIFS('1. Anime Figures'!J$8:J$107,'1. Anime Figures'!C$8:C$107,A29),0)+IFERROR(SUMIFS('2. Mercari and Online store'!J$8:J$107,'2. Mercari and Online store'!C$8:C$107,A29),0)+IFERROR(SUMIFS('3. Onhand orders JPY'!J$8:J$107,'3. Onhand orders JPY'!C$8:C$107,A29),0)+IFERROR(SUMIFS('4. Live Selling Orders'!J$8:J$107,'4. Live Selling Orders'!C$8:C$107,A29),0)+IFERROR(SUMIFS('5. On hand orders PHP'!J$8:J$107,'5. On hand orders PHP'!C$8:C$107,A29),0)+IFERROR(SUMIFS('6. Pre Orders'!J$8:J$107,'6. Pre Orders'!C$8:C$107,A29),0)+IFERROR(SUMIFS('7. Overseas orders'!J$8:J$107,'7. Overseas orders'!C$8:C$107,A29),0)+IFERROR(SUMIFS('10. Restock'!J$8:J$107,'10. Restock'!C$8:C$107,A29),0),IF($E$2="Weekly View",IFERROR(SUMPRODUCT(('1. Anime Figures'!J$8:J$107)*(IFERROR(WEEKNUM('1. Anime Figures'!B$8:B$107,1),0)=ROW()-19)),0)+IFERROR(SUMPRODUCT(('2. Mercari and Online store'!J$8:J$107)*(IFERROR(WEEKNUM('2. Mercari and Online store'!B$8:B$107,1),0)=ROW()-19)),0)+IFERROR(SUMPRODUCT(('3. Onhand orders JPY'!J$8:J$107)*(IFERROR(WEEKNUM('3. Onhand orders JPY'!B$8:B$107,1),0)=ROW()-19)),0)+IFERROR(SUMPRODUCT(('4. Live Selling Orders'!J$8:J$107)*(IFERROR(WEEKNUM('4. Live Selling Orders'!B$8:B$107,1),0)=ROW()-19)),0)+IFERROR(SUMPRODUCT(('5. On hand orders PHP'!J$8:J$107)*(IFERROR(WEEKNUM('5. On hand orders PHP'!B$8:B$107,1),0)=ROW()-19)),0)+IFERROR(SUMPRODUCT(('6. Pre Orders'!J$8:J$107)*(IFERROR(WEEKNUM('6. Pre Orders'!B$8:B$107,1),0)=ROW()-19)),0)+IFERROR(SUMPRODUCT(('7. Overseas orders'!J$8:J$107)*(IFERROR(WEEKNUM('7. Overseas orders'!B$8:B$107,1),0)=ROW()-19)),0)+IFERROR(SUMPRODUCT(('10. Restock'!J$8:J$107)*(IFERROR(WEEKNUM('10. Restock'!B$8:B$107,1),0)=ROW()-19)),0),IFERROR(SUMPRODUCT(('1. Anime Figures'!J$8:J$107)*(IFERROR(YEAR('1. Anime Figures'!B$8:B$107),0)=(YEAR(TODAY())-12+ROW()-19))),0)+IFERROR(SUMPRODUCT(('2. Mercari and Online store'!J$8:J$107)*(IFERROR(YEAR('2. Mercari and Online store'!B$8:B$107),0)=(YEAR(TODAY())-12+ROW()-19))),0)+IFERROR(SUMPRODUCT(('3. Onhand orders JPY'!J$8:J$107)*(IFERROR(YEAR('3. Onhand orders JPY'!B$8:B$107),0)=(YEAR(TODAY())-12+ROW()-19))),0)+IFERROR(SUMPRODUCT(('4. Live Selling Orders'!J$8:J$107)*(IFERROR(YEAR('4. Live Selling Orders'!B$8:B$107),0)=(YEAR(TODAY())-12+ROW()-19))),0)+IFERROR(SUMPRODUCT(('5. On hand orders PHP'!J$8:J$107)*(IFERROR(YEAR('5. On hand orders PHP'!B$8:B$107),0)=(YEAR(TODAY())-12+ROW()-19))),0)+IFERROR(SUMPRODUCT(('6. Pre Orders'!J$8:J$107)*(IFERROR(YEAR('6. Pre Orders'!B$8:B$107),0)=(YEAR(TODAY())-12+ROW()-19))),0)+IFERROR(SUMPRODUCT(('7. Overseas orders'!J$8:J$107)*(IFERROR(YEAR('7. Overseas orders'!B$8:B$107),0)=(YEAR(TODAY())-12+ROW()-19))),0)+IFERROR(SUMPRODUCT(('10. Restock'!J$8:J$107)*(IFERROR(YEAR('10. Restock'!B$8:B$107),0)=(YEAR(TODAY())-12+ROW()-19))),0))) -> 0
A30: =IF($E$2="Monthly View","October",IF($E$2="Weekly View","Week "&(ROW()-20),YEAR(TODAY())-12+ROW()-19)) -> October | B30: =IF($E$2="Monthly View",IFERROR(SUMIFS('1. Anime Figures'!D$8:D$107,'1. Anime Figures'!C$8:C$107,A30),0)+IFERROR(SUMIFS('2. Mercari and Online store'!D$8:D$107,'2. Mercari and Online store'!C$8:C$107,A30),0)+IFERROR(SUMIFS('3. Onhand orders JPY'!D$8:D$107,'3. Onhand orders JPY'!C$8:C$107,A30),0)+IFERROR(SUMIFS('4. Live Selling Orders'!D$8:D$107,'4. Live Selling Orders'!C$8:C$107,A30),0)+IFERROR(SUMIFS('5. On hand orders PHP'!D$8:D$107,'5. On hand orders PHP'!C$8:C$107,A30),0)+IFERROR(SUMIFS('6. Pre Orders'!D$8:D$107,'6. Pre Orders'!C$8:C$107,A30),0)+IFERROR(SUMIFS('7. Overseas orders'!D$8:D$107,'7. Overseas orders'!C$8:C$107,A30),0)+IFERROR(SUMIFS('10. Restock'!D$8:D$107,'10. Restock'!C$8:C$107,A30),0),IF($E$2="Weekly View",IFERROR(SUMPRODUCT(('1. Anime Figures'!D$8:D$107)*(IFERROR(WEEKNUM('1. Anime Figures'!B$8:B$107,1),0)=ROW()-19)),0)+IFERROR(SUMPRODUCT(('2. Mercari and Online store'!D$8:D$107)*(IFERROR(WEEKNUM('2. Mercari and Online store'!B$8:B$107,1),0)=ROW()-19)),0)+IFERROR(SUMPRODUCT(('3. Onhand orders JPY'!D$8:D$107)*(IFERROR(WEEKNUM('3. Onhand orders JPY'!B$8:B$107,1),0)=ROW()-19)),0)+IFERROR(SUMPRODUCT(('4. Live Selling Orders'!D$8:D$107)*(IFERROR(WEEKNUM('4. Live Selling Orders'!B$8:B$107,1),0)=ROW()-19)),0)+IFERROR(SUMPRODUCT(('5. On hand orders PHP'!D$8:D$107)*(IFERROR(WEEKNUM('5. On hand orders PHP'!B$8:B$107,1),0)=ROW()-19)),0)+IFERROR(SUMPRODUCT(('6. Pre Orders'!D$8:D$107)*(IFERROR(WEEKNUM('6. Pre Orders'!B$8:B$107,1),0)=ROW()-19)),0)+IFERROR(SUMPRODUCT(('7. Overseas orders'!D$8:D$107)*(IFERROR(WEEKNUM('7. Overseas orders'!B$8:B$107,1),0)=ROW()-19)),0)+IFERROR(SUMPRODUCT(('10. Restock'!D$8:D$107)*(IFERROR(WEEKNUM('10. Restock'!B$8:B$107,1),0)=ROW()-19)),0),IFERROR(SUMPRODUCT(('1. Anime Figures'!D$8:D$107)*(IFERROR(YEAR('1. Anime Figures'!B$8:B$107),0)=(YEAR(TODAY())-12+ROW()-19))),0)+IFERROR(SUMPRODUCT(('2. Mercari and Online store'!D$8:D$107)*(IFERROR(YEAR('2. Mercari and Online store'!B$8:B$107),0)=(YEAR(TODAY())-12+ROW()-19))),0)+IFERROR(SUMPRODUCT(('3. Onhand orders JPY'!D$8:D$107)*(IFERROR(YEAR('3. Onhand orders JPY'!B$8:B$107),0)=(YEAR(TODAY())-12+ROW()-19))),0)+IFERROR(SUMPRODUCT(('4. Live Selling Orders'!D$8:D$107)*(IFERROR(YEAR('4. Live Selling Orders'!B$8:B$107),0)=(YEAR(TODAY())-12+ROW()-19))),0)+IFERROR(SUMPRODUCT(('5. On hand orders PHP'!D$8:D$107)*(IFERROR(YEAR('5. On hand orders PHP'!B$8:B$107),0)=(YEAR(TODAY())-12+ROW()-19))),0)+IFERROR(SUMPRODUCT(('6. Pre Orders'!D$8:D$107)*(IFERROR(YEAR('6. Pre Orders'!B$8:B$107),0)=(YEAR(TODAY())-12+ROW()-19))),0)+IFERROR(SUMPRODUCT(('7. Overseas orders'!D$8:D$107)*(IFERROR(YEAR('7. Overseas orders'!B$8:B$107),0)=(YEAR(TODAY())-12+ROW()-19))),0)+IFERROR(SUMPRODUCT(('10. Restock'!D$8:D$107)*(IFERROR(YEAR('10. Restock'!B$8:B$107),0)=(YEAR(TODAY())-12+ROW()-19))),0))) -> 0 | C30: =IF($E$2="Monthly View",IFERROR(SUMIFS('1. Anime Figures'!H$8:H$107,'1. Anime Figures'!C$8:C$107,A30),0)+IFERROR(SUMIFS('2. Mercari and Online store'!H$8:H$107,'2. Mercari and Online store'!C$8:C$107,A30),0)+IFERROR(SUMIFS('3. Onhand orders JPY'!H$8:H$107,'3. Onhand orders JPY'!C$8:C$107,A30),0)+IFERROR(SUMIFS('4. Live Selling Orders'!H$8:H$107,'4. Live Selling Orders'!C$8:C$107,A30),0)+IFERROR(SUMIFS('5. On hand orders PHP'!H$8:H$107,'5. On hand orders PHP'!C$8:C$107,A30),0)+IFERROR(SUMIFS('6. Pre Orders'!H$8:H$107,'6. Pre Orders'!C$8:C$107,A30),0)+IFERROR(SUMIFS('7. Overseas orders'!H$8:H$107,'7. Overseas orders'!C$8:C$107,A30),0)+IFERROR(SUMIFS('10. Restock'!H$8:H$107,'10. Restock'!C$8:C$107,A30),0),IF($E$2="Weekly View",IFERROR(SUMPRODUCT(('1. Anime Figures'!H$8:H$107)*(IFERROR(WEEKNUM('1. Anime Figures'!B$8:B$107,1),0)=ROW()-19)),0)+IFERROR(SUMPRODUCT(('2. Mercari and Online store'!H$8:H$107)*(IFERROR(WEEKNUM('2. Mercari and Online store'!B$8:B$107,1),0)=ROW()-19)),0)+IFERROR(SUMPRODUCT(('3. Onhand orders JPY'!H$8:H$107)*(IFERROR(WEEKNUM('3. Onhand orders JPY'!B$8:B$107,1),0)=ROW()-19)),0)+IFERROR(SUMPRODUCT(('4. Live Selling Orders'!H$8:H$107)*(IFERROR(WEEKNUM('4. Live Selling Orders'!B$8:B$107,1),0)=ROW()-19)),0)+IFERROR(SUMPRODUCT(('5. On hand orders PHP'!H$8:H$107)*(IFERROR(WEEKNUM('5. On hand orders PHP'!B$8:B$107,1),0)=ROW()-19)),0)+IFERROR(SUMPRODUCT(('6. Pre Orders'!H$8:H$107)*(IFERROR(WEEKNUM('6. Pre Orders'!B$8:B$107,1),0)=ROW()-19)),0)+IFERROR(SUMPRODUCT(('7. Overseas orders'!H$8:H$107)*(IFERROR(WEEKNUM('7. Overseas orders'!B$8:B$107,1),0)=ROW()-19)),0)+IFERROR(SUMPRODUCT(('10. Restock'!H$8:H$107)*(IFERROR(WEEKNUM('10. Restock'!B$8:B$107,1),0)=ROW()-19)),0),IFERROR(SUMPRODUCT(('1. Anime Figures'!H$8:H$107)*(IFERROR(YEAR('1. Anime Figures'!B$8:B$107),0)=(YEAR(TODAY())-12+ROW()-19))),0)+IFERROR(SUMPRODUCT(('2. Mercari and Online store'!H$8:H$107)*(IFERROR(YEAR('2. Mercari and Online store'!B$8:B$107),0)=(YEAR(TODAY())-12+ROW()-19))),0)+IFERROR(SUMPRODUCT(('3. Onhand orders JPY'!H$8:H$107)*(IFERROR(YEAR('3. Onhand orders JPY'!B$8:B$107),0)=(YEAR(TODAY())-12+ROW()-19))),0)+IFERROR(SUMPRODUCT(('4. Live Selling Orders'!H$8:H$107)*(IFERROR(YEAR('4. Live Selling Orders'!B$8:B$107),0)=(YEAR(TODAY())-12+ROW()-19))),0)+IFERROR(SUMPRODUCT(('5. On hand orders PHP'!H$8:H$107)*(IFERROR(YEAR('5. On hand orders PHP'!B$8:B$107),0)=(YEAR(TODAY())-12+ROW()-19))),0)+IFERROR(SUMPRODUCT(('6. Pre Orders'!H$8:H$107)*(IFERROR(YEAR('6. Pre Orders'!B$8:B$107),0)=(YEAR(TODAY())-12+ROW()-19))),0)+IFERROR(SUMPRODUCT(('7. Overseas orders'!H$8:H$107)*(IFERROR(YEAR('7. Overseas orders'!B$8:B$107),0)=(YEAR(TODAY())-12+ROW()-19))),0)+IFERROR(SUMPRODUCT(('10. Restock'!H$8:H$107)*(IFERROR(YEAR('10. Restock'!B$8:B$107),0)=(YEAR(TODAY())-12+ROW()-19))),0))) -> 0 | D30: =IF($E$2="Monthly View",IFERROR(SUMIFS('1. Anime Figures'!J$8:J$107,'1. Anime Figures'!C$8:C$107,A30),0)+IFERROR(SUMIFS('2. Mercari and Online store'!J$8:J$107,'2. Mercari and Online store'!C$8:C$107,A30),0)+IFERROR(SUMIFS('3. Onhand orders JPY'!J$8:J$107,'3. Onhand orders JPY'!C$8:C$107,A30),0)+IFERROR(SUMIFS('4. Live Selling Orders'!J$8:J$107,'4. Live Selling Orders'!C$8:C$107,A30),0)+IFERROR(SUMIFS('5. On hand orders PHP'!J$8:J$107,'5. On hand orders PHP'!C$8:C$107,A30),0)+IFERROR(SUMIFS('6. Pre Orders'!J$8:J$107,'6. Pre Orders'!C$8:C$107,A30),0)+IFERROR(SUMIFS('7. Overseas orders'!J$8:J$107,'7. Overseas orders'!C$8:C$107,A30),0)+IFERROR(SUMIFS('10. Restock'!J$8:J$107,'10. Restock'!C$8:C$107,A30),0),IF($E$2="Weekly View",IFERROR(SUMPRODUCT(('1. Anime Figures'!J$8:J$107)*(IFERROR(WEEKNUM('1. Anime Figures'!B$8:B$107,1),0)=ROW()-19)),0)+IFERROR(SUMPRODUCT(('2. Mercari and Online store'!J$8:J$107)*(IFERROR(WEEKNUM('2. Mercari and Online store'!B$8:B$107,1),0)=ROW()-19)),0)+IFERROR(SUMPRODUCT(('3. Onhand orders JPY'!J$8:J$107)*(IFERROR(WEEKNUM('3. Onhand orders JPY'!B$8:B$107,1),0)=ROW()-19)),0)+IFERROR(SUMPRODUCT(('4. Live Selling Orders'!J$8:J$107)*(IFERROR(WEEKNUM('4. Live Selling Orders'!B$8:B$107,1),0)=ROW()-19)),0)+IFERROR(SUMPRODUCT(('5. On hand orders PHP'!J$8:J$107)*(IFERROR(WEEKNUM('5. On hand orders PHP'!B$8:B$107,1),0)=ROW()-19)),0)+IFERROR(SUMPRODUCT(('6. Pre Orders'!J$8:J$107)*(IFERROR(WEEKNUM('6. Pre Orders'!B$8:B$107,1),0)=ROW()-19)),0)+IFERROR(SUMPRODUCT(('7. Overseas orders'!J$8:J$107)*(IFERROR(WEEKNUM('7. Overseas orders'!B$8:B$107,1),0)=ROW()-19)),0)+IFERROR(SUMPRODUCT(('10. Restock'!J$8:J$107)*(IFERROR(WEEKNUM('10. Restock'!B$8:B$107,1),0)=ROW()-19)),0),IFERROR(SUMPRODUCT(('1. Anime Figures'!J$8:J$107)*(IFERROR(YEAR('1. Anime Figures'!B$8:B$107),0)=(YEAR(TODAY())-12+ROW()-19))),0)+IFERROR(SUMPRODUCT(('2. Mercari and Online store'!J$8:J$107)*(IFERROR(YEAR('2. Mercari and Online store'!B$8:B$107),0)=(YEAR(TODAY())-12+ROW()-19))),0)+IFERROR(SUMPRODUCT(('3. Onhand orders JPY'!J$8:J$107)*(IFERROR(YEAR('3. Onhand orders JPY'!B$8:B$107),0)=(YEAR(TODAY())-12+ROW()-19))),0)+IFERROR(SUMPRODUCT(('4. Live Selling Orders'!J$8:J$107)*(IFERROR(YEAR('4. Live Selling Orders'!B$8:B$107),0)=(YEAR(TODAY())-12+ROW()-19))),0)+IFERROR(SUMPRODUCT(('5. On hand orders PHP'!J$8:J$107)*(IFERROR(YEAR('5. On hand orders PHP'!B$8:B$107),0)=(YEAR(TODAY())-12+ROW()-19))),0)+IFERROR(SUMPRODUCT(('6. Pre Orders'!J$8:J$107)*(IFERROR(YEAR('6. Pre Orders'!B$8:B$107),0)=(YEAR(TODAY())-12+ROW()-19))),0)+IFERROR(SUMPRODUCT(('7. Overseas orders'!J$8:J$107)*(IFERROR(YEAR('7. Overseas orders'!B$8:B$107),0)=(YEAR(TODAY())-12+ROW()-19))),0)+IFERROR(SUMPRODUCT(('10. Restock'!J$8:J$107)*(IFERROR(YEAR('10. Restock'!B$8:B$107),0)=(YEAR(TODAY())-12+ROW()-19))),0))) -> 0
A31: =IF($E$2="Monthly View","November",IF($E$2="Weekly View","Week "&(ROW()-20),YEAR(TODAY())-12+ROW()-19)) -> November | B31: =IF($E$2="Monthly View",IFERROR(SUMIFS('1. Anime Figures'!D$8:D$107,'1. Anime Figures'!C$8:C$107,A31),0)+IFERROR(SUMIFS('2. Mercari and Online store'!D$8:D$107,'2. Mercari and Online store'!C$8:C$107,A31),0)+IFERROR(SUMIFS('3. Onhand orders JPY'!D$8:D$107,'3. Onhand orders JPY'!C$8:C$107,A31),0)+IFERROR(SUMIFS('4. Live Selling Orders'!D$8:D$107,'4. Live Selling Orders'!C$8:C$107,A31),0)+IFERROR(SUMIFS('5. On hand orders PHP'!D$8:D$107,'5. On hand orders PHP'!C$8:C$107,A31),0)+IFERROR(SUMIFS('6. Pre Orders'!D$8:D$107,'6. Pre Orders'!C$8:C$107,A31),0)+IFERROR(SUMIFS('7. Overseas orders'!D$8:D$107,'7. Overseas orders'!C$8:C$107,A31),0)+IFERROR(SUMIFS('10. Restock'!D$8:D$107,'10. Restock'!C$8:C$107,A31),0),IF($E$2="Weekly View",IFERROR(SUMPRODUCT(('1. Anime Figures'!D$8:D$107)*(IFERROR(WEEKNUM('1. Anime Figures'!B$8:B$107,1),0)=ROW()-19)),0)+IFERROR(SUMPRODUCT(('2. Mercari and Online store'!D$8:D$107)*(IFERROR(WEEKNUM('2. Mercari and Online store'!B$8:B$107,1),0)=ROW()-19)),0)+IFERROR(SUMPRODUCT(('3. Onhand orders JPY'!D$8:D$107)*(IFERROR(WEEKNUM('3. Onhand orders JPY'!B$8:B$107,1),0)=ROW()-19)),0)+IFERROR(SUMPRODUCT(('4. Live Selling Orders'!D$8:D$107)*(IFERROR(WEEKNUM('4. Live Selling Orders'!B$8:B$107,1),0)=ROW()-19)),0)+IFERROR(SUMPRODUCT(('5. On hand orders PHP'!D$8:D$107)*(IFERROR(WEEKNUM('5. On hand orders PHP'!B$8:B$107,1),0)=ROW()-19)),0)+IFERROR(SUMPRODUCT(('6. Pre Orders'!D$8:D$107)*(IFERROR(WEEKNUM('6. Pre Orders'!B$8:B$107,1),0)=ROW()-19)),0)+IFERROR(SUMPRODUCT(('7. Overseas orders'!D$8:D$107)*(IFERROR(WEEKNUM('7. Overseas orders'!B$8:B$107,1),0)=ROW()-19)),0)+IFERROR(SUMPRODUCT(('10. Restock'!D$8:D$107)*(IFERROR(WEEKNUM('10. Restock'!B$8:B$107,1),0)=ROW()-19)),0),IFERROR(SUMPRODUCT(('1. Anime Figures'!D$8:D$107)*(IFERROR(YEAR('1. Anime Figures'!B$8:B$107),0)=(YEAR(TODAY())-12+ROW()-19))),0)+IFERROR(SUMPRODUCT(('2. Mercari and Online store'!D$8:D$107)*(IFERROR(YEAR('2. Mercari and Online store'!B$8:B$107),0)=(YEAR(TODAY())-12+ROW()-19))),0)+IFERROR(SUMPRODUCT(('3. Onhand orders JPY'!D$8:D$107)*(IFERROR(YEAR('3. Onhand orders JPY'!B$8:B$107),0)=(YEAR(TODAY())-12+ROW()-19))),0)+IFERROR(SUMPRODUCT(('4. Live Selling Orders'!D$8:D$107)*(IFERROR(YEAR('4. Live Selling Orders'!B$8:B$107),0)=(YEAR(TODAY())-12+ROW()-19))),0)+IFERROR(SUMPRODUCT(('5. On hand orders PHP'!D$8:D$107)*(IFERROR(YEAR('5. On hand orders PHP'!B$8:B$107),0)=(YEAR(TODAY())-12+ROW()-19))),0)+IFERROR(SUMPRODUCT(('6. Pre Orders'!D$8:D$107)*(IFERROR(YEAR('6. Pre Orders'!B$8:B$107),0)=(YEAR(TODAY())-12+ROW()-19))),0)+IFERROR(SUMPRODUCT(('7. Overseas orders'!D$8:D$107)*(IFERROR(YEAR('7. Overseas orders'!B$8:B$107),0)=(YEAR(TODAY())-12+ROW()-19))),0)+IFERROR(SUMPRODUCT(('10. Restock'!D$8:D$107)*(IFERROR(YEAR('10. Restock'!B$8:B$107),0)=(YEAR(TODAY())-12+ROW()-19))),0))) -> 0 | C31: =IF($E$2="Monthly View",IFERROR(SUMIFS('1. Anime Figures'!H$8:H$107,'1. Anime Figures'!C$8:C$107,A31),0)+IFERROR(SUMIFS('2. Mercari and Online store'!H$8:H$107,'2. Mercari and Online store'!C$8:C$107,A31),0)+IFERROR(SUMIFS('3. Onhand orders JPY'!H$8:H$107,'3. Onhand orders JPY'!C$8:C$107,A31),0)+IFERROR(SUMIFS('4. Live Selling Orders'!H$8:H$107,'4. Live Selling Orders'!C$8:C$107,A31),0)+IFERROR(SUMIFS('5. On hand orders PHP'!H$8:H$107,'5. On hand orders PHP'!C$8:C$107,A31),0)+IFERROR(SUMIFS('6. Pre Orders'!H$8:H$107,'6. Pre Orders'!C$8:C$107,A31),0)+IFERROR(SUMIFS('7. Overseas orders'!H$8:H$107,'7. Overseas orders'!C$8:C$107,A31),0)+IFERROR(SUMIFS('10. Restock'!H$8:H$107,'10. Restock'!C$8:C$107,A31),0),IF($E$2="Weekly View",IFERROR(SUMPRODUCT(('1. Anime Figures'!H$8:H$107)*(IFERROR(WEEKNUM('1. Anime Figures'!B$8:B$107,1),0)=ROW()-19)),0)+IFERROR(SUMPRODUCT(('2. Mercari and Online store'!H$8:H$107)*(IFERROR(WEEKNUM('2. Mercari and Online store'!B$8:B$107,1),0)=ROW()-19)),0)+IFERROR(SUMPRODUCT(('3. Onhand orders JPY'!H$8:H$107)*(IFERROR(WEEKNUM('3. Onhand orders JPY'!B$8:B$107,1),0)=ROW()-19)),0)+IFERROR(SUMPRODUCT(('4. Live Selling Orders'!H$8:H$107)*(IFERROR(WEEKNUM('4. Live Selling Orders'!B$8:B$107,1),0)=ROW()-19)),0)+IFERROR(SUMPRODUCT(('5. On hand orders PHP'!H$8:H$107)*(IFERROR(WEEKNUM('5. On hand orders PHP'!B$8:B$107,1),0)=ROW()-19)),0)+IFERROR(SUMPRODUCT(('6. Pre Orders'!H$8:H$107)*(IFERROR(WEEKNUM('6. Pre Orders'!B$8:B$107,1),0)=ROW()-19)),0)+IFERROR(SUMPRODUCT(('7. Overseas orders'!H$8:H$107)*(IFERROR(WEEKNUM('7. Overseas orders'!B$8:B$107,1),0)=ROW()-19)),0)+IFERROR(SUMPRODUCT(('10. Restock'!H$8:H$107)*(IFERROR(WEEKNUM('10. Restock'!B$8:B$107,1),0)=ROW()-19)),0),IFERROR(SUMPRODUCT(('1. Anime Figures'!H$8:H$107)*(IFERROR(YEAR('1. Anime Figures'!B$8:B$107),0)=(YEAR(TODAY())-12+ROW()-19))),0)+IFERROR(SUMPRODUCT(('2. Mercari and Online store'!H$8:H$107)*(IFERROR(YEAR('2. Mercari and Online store'!B$8:B$107),0)=(YEAR(TODAY())-12+ROW()-19))),0)+IFERROR(SUMPRODUCT(('3. Onhand orders JPY'!H$8:H$107)*(IFERROR(YEAR('3. Onhand orders JPY'!B$8:B$107),0)=(YEAR(TODAY())-12+ROW()-19))),0)+IFERROR(SUMPRODUCT(('4. Live Selling Orders'!H$8:H$107)*(IFERROR(YEAR('4. Live Selling Orders'!B$8:B$107),0)=(YEAR(TODAY())-12+ROW()-19))),0)+IFERROR(SUMPRODUCT(('5. On hand orders PHP'!H$8:H$107)*(IFERROR(YEAR('5. On hand orders PHP'!B$8:B$107),0)=(YEAR(TODAY())-12+ROW()-19))),0)+IFERROR(SUMPRODUCT(('6. Pre Orders'!H$8:H$107)*(IFERROR(YEAR('6. Pre Orders'!B$8:B$107),0)=(YEAR(TODAY())-12+ROW()-19))),0)+IFERROR(SUMPRODUCT(('7. Overseas orders'!H$8:H$107)*(IFERROR(YEAR('7. Overseas orders'!B$8:B$107),0)=(YEAR(TODAY())-12+ROW()-19))),0)+IFERROR(SUMPRODUCT(('10. Restock'!H$8:H$107)*(IFERROR(YEAR('10. Restock'!B$8:B$107),0)=(YEAR(TODAY())-12+ROW()-19))),0))) -> 0 | D31: =IF($E$2="Monthly View",IFERROR(SUMIFS('1. Anime Figures'!J$8:J$107,'1. Anime Figures'!C$8:C$107,A31),0)+IFERROR(SUMIFS('2. Mercari and Online store'!J$8:J$107,'2. Mercari and Online store'!C$8:C$107,A31),0)+IFERROR(SUMIFS('3. Onhand orders JPY'!J$8:J$107,'3. Onhand orders JPY'!C$8:C$107,A31),0)+IFERROR(SUMIFS('4. Live Selling Orders'!J$8:J$107,'4. Live Selling Orders'!C$8:C$107,A31),0)+IFERROR(SUMIFS('5. On hand orders PHP'!J$8:J$107,'5. On hand orders PHP'!C$8:C$107,A31),0)+IFERROR(SUMIFS('6. Pre Orders'!J$8:J$107,'6. Pre Orders'!C$8:C$107,A31),0)+IFERROR(SUMIFS('7. Overseas orders'!J$8:J$107,'7. Overseas orders'!C$8:C$107,A31),0)+IFERROR(SUMIFS('10. Restock'!J$8:J$107,'10. Restock'!C$8:C$107,A31),0),IF($E$2="Weekly View",IFERROR(SUMPRODUCT(('1. Anime Figures'!J$8:J$107)*(IFERROR(WEEKNUM('1. Anime Figures'!B$8:B$107,1),0)=ROW()-19)),0)+IFERROR(SUMPRODUCT(('2. Mercari and Online store'!J$8:J$107)*(IFERROR(WEEKNUM('2. Mercari and Online store'!B$8:B$107,1),0)=ROW()-19)),0)+IFERROR(SUMPRODUCT(('3. Onhand orders JPY'!J$8:J$107)*(IFERROR(WEEKNUM('3. Onhand orders JPY'!B$8:B$107,1),0)=ROW()-19)),0)+IFERROR(SUMPRODUCT(('4. Live Selling Orders'!J$8:J$107)*(IFERROR(WEEKNUM('4. Live Selling Orders'!B$8:B$107,1),0)=ROW()-19)),0)+IFERROR(SUMPRODUCT(('5. On hand orders PHP'!J$8:J$107)*(IFERROR(WEEKNUM('5. On hand orders PHP'!B$8:B$107,1),0)=ROW()-19)),0)+IFERROR(SUMPRODUCT(('6. Pre Orders'!J$8:J$107)*(IFERROR(WEEKNUM('6. Pre Orders'!B$8:B$107,1),0)=ROW()-19)),0)+IFERROR(SUMPRODUCT(('7. Overseas orders'!J$8:J$107)*(IFERROR(WEEKNUM('7. Overseas orders'!B$8:B$107,1),0)=ROW()-19)),0)+IFERROR(SUMPRODUCT(('10. Restock'!J$8:J$107)*(IFERROR(WEEKNUM('10. Restock'!B$8:B$107,1),0)=ROW()-19)),0),IFERROR(SUMPRODUCT(('1. Anime Figures'!J$8:J$107)*(IFERROR(YEAR('1. Anime Figures'!B$8:B$107),0)=(YEAR(TODAY())-12+ROW()-19))),0)+IFERROR(SUMPRODUCT(('2. Mercari and Online store'!J$8:J$107)*(IFERROR(YEAR('2. Mercari and Online store'!B$8:B$107),0)=(YEAR(TODAY())-12+ROW()-19))),0)+IFERROR(SUMPRODUCT(('3. Onhand orders JPY'!J$8:J$107)*(IFERROR(YEAR('3. Onhand orders JPY'!B$8:B$107),0)=(YEAR(TODAY())-12+ROW()-19))),0)+IFERROR(SUMPRODUCT(('4. Live Selling Orders'!J$8:J$107)*(IFERROR(YEAR('4. Live Selling Orders'!B$8:B$107),0)=(YEAR(TODAY())-12+ROW()-19))),0)+IFERROR(SUMPRODUCT(('5. On hand orders PHP'!J$8:J$107)*(IFERROR(YEAR('5. On hand orders PHP'!B$8:B$107),0)=(YEAR(TODAY())-12+ROW()-19))),0)+IFERROR(SUMPRODUCT(('6. Pre Orders'!J$8:J$107)*(IFERROR(YEAR('6. Pre Orders'!B$8:B$107),0)=(YEAR(TODAY())-12+ROW()-19))),0)+IFERROR(SUMPRODUCT(('7. Overseas orders'!J$8:J$107)*(IFERROR(YEAR('7. Overseas orders'!B$8:B$107),0)=(YEAR(TODAY())-12+ROW()-19))),0)+IFERROR(SUMPRODUCT(('10. Restock'!J$8:J$107)*(IFERROR(YEAR('10. Restock'!B$8:B$107),0)=(YEAR(TODAY())-12+ROW()-19))),0))) -> 0
A32: =IF($E$2="Monthly View","December",IF($E$2="Weekly View","Week "&(ROW()-20),YEAR(TODAY())-12+ROW()-19)) -> December | B32: =IF($E$2="Monthly View",IFERROR(SUMIFS('1. Anime Figures'!D$8:D$107,'1. Anime Figures'!C$8:C$107,A32),0)+IFERROR(SUMIFS('2. Mercari and Online store'!D$8:D$107,'2. Mercari and Online store'!C$8:C$107,A32),0)+IFERROR(SUMIFS('3. Onhand orders JPY'!D$8:D$107,'3. Onhand orders JPY'!C$8:C$107,A32),0)+IFERROR(SUMIFS('4. Live Selling Orders'!D$8:D$107,'4. Live Selling Orders'!C$8:C$107,A32),0)+IFERROR(SUMIFS('5. On hand orders PHP'!D$8:D$107,'5. On hand orders PHP'!C$8:C$107,A32),0)+IFERROR(SUMIFS('6. Pre Orders'!D$8:D$107,'6. Pre Orders'!C$8:C$107,A32),0)+IFERROR(SUMIFS('7. Overseas orders'!D$8:D$107,'7. Overseas orders'!C$8:C$107,A32),0)+IFERROR(SUMIFS('10. Restock'!D$8:D$107,'10. Restock'!C$8:C$107,A32),0),IF($E$2="Weekly View",IFERROR(SUMPRODUCT(('1. Anime Figures'!D$8:D$107)*(IFERROR(WEEKNUM('1. Anime Figures'!B$8:B$107,1),0)=ROW()-19)),0)+IFERROR(SUMPRODUCT(('2. Mercari and Online store'!D$8:D$107)*(IFERROR(WEEKNUM('2. Mercari and Online store'!B$8:B$107,1),0)=ROW()-19)),0)+IFERROR(SUMPRODUCT(('3. Onhand orders JPY'!D$8:D$107)*(IFERROR(WEEKNUM('3. Onhand orders JPY'!B$8:B$107,1),0)=ROW()-19)),0)+IFERROR(SUMPRODUCT(('4. Live Selling Orders'!D$8:D$107)*(IFERROR(WEEKNUM('4. Live Selling Orders'!B$8:B$107,1),0)=ROW()-19)),0)+IFERROR(SUMPRODUCT(('5. On hand orders PHP'!D$8:D$107)*(IFERROR(WEEKNUM('5. On hand orders PHP'!B$8:B$107,1),0)=ROW()-19)),0)+IFERROR(SUMPRODUCT(('6. Pre Orders'!D$8:D$107)*(IFERROR(WEEKNUM('6. Pre Orders'!B$8:B$107,1),0)=ROW()-19)),0)+IFERROR(SUMPRODUCT(('7. Overseas orders'!D$8:D$107)*(IFERROR(WEEKNUM('7. Overseas orders'!B$8:B$107,1),0)=ROW()-19)),0)+IFERROR(SUMPRODUCT(('10. Restock'!D$8:D$107)*(IFERROR(WEEKNUM('10. Restock'!B$8:B$107,1),0)=ROW()-19)),0),IFERROR(SUMPRODUCT(('1. Anime Figures'!D$8:D$107)*(IFERROR(YEAR('1. Anime Figures'!B$8:B$107),0)=(YEAR(TODAY())-12+ROW()-19))),0)+IFERROR(SUMPRODUCT(('2. Mercari and Online store'!D$8:D$107)*(IFERROR(YEAR('2. Mercari and Online store'!B$8:B$107),0)=(YEAR(TODAY())-12+ROW()-19))),0)+IFERROR(SUMPRODUCT(('3. Onhand orders JPY'!D$8:D$107)*(IFERROR(YEAR('3. Onhand orders JPY'!B$8:B$107),0)=(YEAR(TODAY())-12+ROW()-19))),0)+IFERROR(SUMPRODUCT(('4. Live Selling Orders'!D$8:D$107)*(IFERROR(YEAR('4. Live Selling Orders'!B$8:B$107),0)=(YEAR(TODAY())-12+ROW()-19))),0)+IFERROR(SUMPRODUCT(('5. On hand orders PHP'!D$8:D$107)*(IFERROR(YEAR('5. On hand orders PHP'!B$8:B$107),0)=(YEAR(TODAY())-12+ROW()-19))),0)+IFERROR(SUMPRODUCT(('6. Pre Orders'!D$8:D$107)*(IFERROR(YEAR('6. Pre Orders'!B$8:B$107),0)=(YEAR(TODAY())-12+ROW()-19))),0)+IFERROR(SUMPRODUCT(('7. Overseas orders'!D$8:D$107)*(IFERROR(YEAR('7. Overseas orders'!B$8:B$107),0)=(YEAR(TODAY())-12+ROW()-19))),0)+IFERROR(SUMPRODUCT(('10. Restock'!D$8:D$107)*(IFERROR(YEAR('10. Restock'!B$8:B$107),0)=(YEAR(TODAY())-12+ROW()-19))),0))) -> 0 | C32: =IF($E$2="Monthly View",IFERROR(SUMIFS('1. Anime Figures'!H$8:H$107,'1. Anime Figures'!C$8:C$107,A32),0)+IFERROR(SUMIFS('2. Mercari and Online store'!H$8:H$107,'2. Mercari and Online store'!C$8:C$107,A32),0)+IFERROR(SUMIFS('3. Onhand orders JPY'!H$8:H$107,'3. Onhand orders JPY'!C$8:C$107,A32),0)+IFERROR(SUMIFS('4. Live Selling Orders'!H$8:H$107,'4. Live Selling Orders'!C$8:C$107,A32),0)+IFERROR(SUMIFS('5. On hand orders PHP'!H$8:H$107,'5. On hand orders PHP'!C$8:C$107,A32),0)+IFERROR(SUMIFS('6. Pre Orders'!H$8:H$107,'6. Pre Orders'!C$8:C$107,A32),0)+IFERROR(SUMIFS('7. Overseas orders'!H$8:H$107,'7. Overseas orders'!C$8:C$107,A32),0)+IFERROR(SUMIFS('10. Restock'!H$8:H$107,'10. Restock'!C$8:C$107,A32),0),IF($E$2="Weekly View",IFERROR(SUMPRODUCT(('1. Anime Figures'!H$8:H$107)*(IFERROR(WEEKNUM('1. Anime Figures'!B$8:B$107,1),0)=ROW()-19)),0)+IFERROR(SUMPRODUCT(('2. Mercari and Online store'!H$8:H$107)*(IFERROR(WEEKNUM('2. Mercari and Online store'!B$8:B$107,1),0)=ROW()-19)),0)+IFERROR(SUMPRODUCT(('3. Onhand orders JPY'!H$8:H$107)*(IFERROR(WEEKNUM('3. Onhand orders JPY'!B$8:B$107,1),0)=ROW()-19)),0)+IFERROR(SUMPRODUCT(('4. Live Selling Orders'!H$8:H$107)*(IFERROR(WEEKNUM('4. Live Selling Orders'!B$8:B$107,1),0)=ROW()-19)),0)+IFERROR(SUMPRODUCT(('5. On hand orders PHP'!H$8:H$107)*(IFERROR(WEEKNUM('5. On hand orders PHP'!B$8:B$107,1),0)=ROW()-19)),0)+IFERROR(SUMPRODUCT(('6. Pre Orders'!H$8:H$107)*(IFERROR(WEEKNUM('6. Pre Orders'!B$8:B$107,1),0)=ROW()-19)),0)+IFERROR(SUMPRODUCT(('7. Overseas orders'!H$8:H$107)*(IFERROR(WEEKNUM('7. Overseas orders'!B$8:B$107,1),0)=ROW()-19)),0)+IFERROR(SUMPRODUCT(('10. Restock'!H$8:H$107)*(IFERROR(WEEKNUM('10. Restock'!B$8:B$107,1),0)=ROW()-19)),0),IFERROR(SUMPRODUCT(('1. Anime Figures'!H$8:H$107)*(IFERROR(YEAR('1. Anime Figures'!B$8:B$107),0)=(YEAR(TODAY())-12+ROW()-19))),0)+IFERROR(SUMPRODUCT(('2. Mercari and Online store'!H$8:H$107)*(IFERROR(YEAR('2. Mercari and Online store'!B$8:B$107),0)=(YEAR(TODAY())-12+ROW()-19))),0)+IFERROR(SUMPRODUCT(('3. Onhand orders JPY'!H$8:H$107)*(IFERROR(YEAR('3. Onhand orders JPY'!B$8:B$107),0)=(YEAR(TODAY())-12+ROW()-19))),0)+IFERROR(SUMPRODUCT(('4. Live Selling Orders'!H$8:H$107)*(IFERROR(YEAR('4. Live Selling Orders'!B$8:B$107),0)=(YEAR(TODAY())-12+ROW()-19))),0)+IFERROR(SUMPRODUCT(('5. On hand orders PHP'!H$8:H$107)*(IFERROR(YEAR('5. On hand orders PHP'!B$8:B$107),0)=(YEAR(TODAY())-12+ROW()-19))),0)+IFERROR(SUMPRODUCT(('6. Pre Orders'!H$8:H$107)*(IFERROR(YEAR('6. Pre Orders'!B$8:B$107),0)=(YEAR(TODAY())-12+ROW()-19))),0)+IFERROR(SUMPRODUCT(('7. Overseas orders'!H$8:H$107)*(IFERROR(YEAR('7. Overseas orders'!B$8:B$107),0)=(YEAR(TODAY())-12+ROW()-19))),0)+IFERROR(SUMPRODUCT(('10. Restock'!H$8:H$107)*(IFERROR(YEAR('10. Restock'!B$8:B$107),0)=(YEAR(TODAY())-12+ROW()-19))),0))) -> 0 | D32: =IF($E$2="Monthly View",IFERROR(SUMIFS('1. Anime Figures'!J$8:J$107,'1. Anime Figures'!C$8:C$107,A32),0)+IFERROR(SUMIFS('2. Mercari and Online store'!J$8:J$107,'2. Mercari and Online store'!C$8:C$107,A32),0)+IFERROR(SUMIFS('3. Onhand orders JPY'!J$8:J$107,'3. Onhand orders JPY'!C$8:C$107,A32),0)+IFERROR(SUMIFS('4. Live Selling Orders'!J$8:J$107,'4. Live Selling Orders'!C$8:C$107,A32),0)+IFERROR(SUMIFS('5. On hand orders PHP'!J$8:J$107,'5. On hand orders PHP'!C$8:C$107,A32),0)+IFERROR(SUMIFS('6. Pre Orders'!J$8:J$107,'6. Pre Orders'!C$8:C$107,A32),0)+IFERROR(SUMIFS('7. Overseas orders'!J$8:J$107,'7. Overseas orders'!C$8:C$107,A32),0)+IFERROR(SUMIFS('10. Restock'!J$8:J$107,'10. Restock'!C$8:C$107,A32),0),IF($E$2="Weekly View",IFERROR(SUMPRODUCT(('1. Anime Figures'!J$8:J$107)*(IFERROR(WEEKNUM('1. Anime Figures'!B$8:B$107,1),0)=ROW()-19)),0)+IFERROR(SUMPRODUCT(('2. Mercari and Online store'!J$8:J$107)*(IFERROR(WEEKNUM('2. Mercari and Online store'!B$8:B$107,1),0)=ROW()-19)),0)+IFERROR(SUMPRODUCT(('3. Onhand orders JPY'!J$8:J$107)*(IFERROR(WEEKNUM('3. Onhand orders JPY'!B$8:B$107,1),0)=ROW()-19)),0)+IFERROR(SUMPRODUCT(('4. Live Selling Orders'!J$8:J$107)*(IFERROR(WEEKNUM('4. Live Selling Orders'!B$8:B$107,1),0)=ROW()-19)),0)+IFERROR(SUMPRODUCT(('5. On hand orders PHP'!J$8:J$107)*(IFERROR(WEEKNUM('5. On hand orders PHP'!B$8:B$107,1),0)=ROW()-19)),0)+IFERROR(SUMPRODUCT(('6. Pre Orders'!J$8:J$107)*(IFERROR(WEEKNUM('6. Pre Orders'!B$8:B$107,1),0)=ROW()-19)),0)+IFERROR(SUMPRODUCT(('7. Overseas orders'!J$8:J$107)*(IFERROR(WEEKNUM('7. Overseas orders'!B$8:B$107,1),0)=ROW()-19)),0)+IFERROR(SUMPRODUCT(('10. Restock'!J$8:J$107)*(IFERROR(WEEKNUM('10. Restock'!B$8:B$107,1),0)=ROW()-19)),0),IFERROR(SUMPRODUCT(('1. Anime Figures'!J$8:J$107)*(IFERROR(YEAR('1. Anime Figures'!B$8:B$107),0)=(YEAR(TODAY())-12+ROW()-19))),0)+IFERROR(SUMPRODUCT(('2. Mercari and Online store'!J$8:J$107)*(IFERROR(YEAR('2. Mercari and Online store'!B$8:B$107),0)=(YEAR(TODAY())-12+ROW()-19))),0)+IFERROR(SUMPRODUCT(('3. Onhand orders JPY'!J$8:J$107)*(IFERROR(YEAR('3. Onhand orders JPY'!B$8:B$107),0)=(YEAR(TODAY())-12+ROW()-19))),0)+IFERROR(SUMPRODUCT(('4. Live Selling Orders'!J$8:J$107)*(IFERROR(YEAR('4. Live Selling Orders'!B$8:B$107),0)=(YEAR(TODAY())-12+ROW()-19))),0)+IFERROR(SUMPRODUCT(('5. On hand orders PHP'!J$8:J$107)*(IFERROR(YEAR('5. On hand orders PHP'!B$8:B$107),0)=(YEAR(TODAY())-12+ROW()-19))),0)+IFERROR(SUMPRODUCT(('6. Pre Orders'!J$8:J$107)*(IFERROR(YEAR('6. Pre Orders'!B$8:B$107),0)=(YEAR(TODAY())-12+ROW()-19))),0)+IFERROR(SUMPRODUCT(('7. Overseas orders'!J$8:J$107)*(IFERROR(YEAR('7. Overseas orders'!B$8:B$107),0)=(YEAR(TODAY())-12+ROW()-19))),0)+IFERROR(SUMPRODUCT(('10. Restock'!J$8:J$107)*(IFERROR(YEAR('10. Restock'!B$8:B$107),0)=(YEAR(TODAY())-12+ROW()-19))),0))) -> 0
A34: 📊 CHART SETUP INSTRUCTIONS — Read Before Building
A35: 1. Select cells A20:D32 (Chart Feed Table — Period + 3 data series).
A36: 2. Go to Insert → Column Chart → Clustered Column.
A37: 3. Set 'Purchase Volume' bars to Cool Gray (#6C757D).
A38: 4. Set 'Net Profit' bars to Emerald Green (#28A745).
A39: 5. Set 'Net Losses' bars to Crimson Red (#DC3545).
A40: 6. Remove gridlines. Set chart title: 'Financial Performance & Capital Allocation Analytics'.
A41: 7. When user changes E2 (Monthly/Weekly/Annual), Chart Feed cells recalculate — chart updates instantly.
A42: ⚡ CHART AUTO-SYNC: The chart points to the fixed A20:D32 range. No data source changes needed.
A44: ⚙️ VBA NOTE: Run the 'RefreshSheetNames()' macro from the VBA module to auto-populate Column A (rows 6-14) with the live sheet names. After running, INDIRECT formulas auto-adapt to any renamed or added sheets without manual updates.
A45: ⚡ LIVE CHART: This chart is hardwired to the Chart Feed Table (rows 21–32). Any data change on any tracking sheet → SUMIFS recalculate → Chart redraws INSTANTLY. Changing B2 (month filter) or E2 (timeframe) pivots the chart in real time — no macro needed.

Sheet 10. Restock
A1: KEN JP ANIME FIGURES SHOP
A4: 📦 10. RESTOCK | Rates: 'Exchange Rate'!B5 (PHP→JPY) & E5 (JPY→PHP)
A5: 🔍 FUZZY SEARCH | B5: ⬇ type partial name or ID: | D5: =IF($C$5="","← type above",IFERROR(ROWS(filter($S$8:$S$107,ISNUMBER(SEARCH($C$5,$S$8:$S$107))))&" match(es) found","❌ 0 found")) -> ← type above | E5: View match #: | F5: 1 | G5: =IF($C$5="","— no active search —",IFERROR(INDEX(filter($S$8:$S$107,ISNUMBER(SEARCH($C$5,$S$8:$S$107)),"❌ No Data Found"),VALUE($F$5)),"❌ No Data Found")) -> — no active search — | H5: =IFERROR(IF($G$5="❌ No Data Found","—",IF($G$5="— no active search —","—",INDEX($D$8:$D$107,MATCH($G$5,$S$8:$S$107,0)))),"—") -> — | I5: =IFERROR(IF($G$5="❌ No Data Found","—",IF($G$5="— no active search —","—",INDEX($F$8:$F$107,MATCH($G$5,$S$8:$S$107,0)))),"—") -> — | J5: =IFERROR(IF($G$5="❌ No Data Found","—",IF($G$5="— no active search —","—",INDEX($H$8:$H$107,MATCH($G$5,$S$8:$S$107,0)))),"—") -> — | K5: =IFERROR(IF($G$5="❌ No Data Found","—",IF($G$5="— no active search —","—",INDEX($J$8:$J$107,MATCH($G$5,$S$8:$S$107,0)))),"—") -> — | L5: =IFERROR(IF($G$5="❌ No Data Found","—",IF($G$5="— no active search —","—",INDEX($L$8:$L$107,MATCH($G$5,$S$8:$S$107,0)))),"—") -> —
A7: Product ID | B7: Date of Entry | C7: Transaction Month | D7: Purchase Price (JPY) | E7: Purchase Price (PHP) | F7: Selling Price (PHP) | G7: Selling Price (JPY) | H7: Net Profit (JPY) | I7: Net Profit (PHP) | J7: Net Loss (JPY) | K7: Net Loss (PHP) | L7: Stock Status | M7: Customer Name | N7: Purchase Link | O7: Current Stock | P7: Weekly Run Rate | Q7: Weeks of Supply | R7: Reorder Date | S7: SEARCH_KEY (hidden)
C8: =IF(B8="","",TEXT(B8,"mmmm")) | E8: =IF(D8="","",D8*'Exchange Rate'!$E$5) | G8: =IF(F8="","",F8*'Exchange Rate'!$B$5) | H8: =IF(L8="Inactive",0,IF(ISNUMBER(G8)*ISNUMBER(D8),IF(G8>D8,G8-D8,0),0)) -> 0 | I8: =IF(L8="Inactive",0,IF(ISNUMBER(F8)*ISNUMBER(E8),IF(F8>E8,F8-E8,0),0)) -> 0 | J8: =IF(L8="Inactive",0,IF(ISNUMBER(D8)*ISNUMBER(G8),IF(D8>G8,D8-G8,0),0)) -> 0 | K8: =IF(L8="Inactive",0,IF(ISNUMBER(E8)*ISNUMBER(F8),IF(E8>F8,E8-F8,0),0)) -> 0 | L8: Active | P8: =IFERROR(COUNTIFS('2. Mercari and Online store'!$A$8:$A$107,A8,'2. Mercari and Online store'!$B$8:$B$107,">="&(TODAY()-28))/4,0) -> 0 | Q8: =IFERROR(IF(P8=0,"∞",O8/P8),"—") -> ∞ | R8: =IFERROR(IF(OR(P8=0,O8=""),"N/A",TEXT(TODAY()+(IFERROR(O8/P8,0)*7),"DD-MMM-YYYY")),"—") -> N/A | S8: =IF(A8="","—",A8&" ("&TEXT(B8,"MM/DD/YYYY")&")") -> —
C9: =IF(B9="","",TEXT(B9,"mmmm")) | E9: =IF(D9="","",D9*'Exchange Rate'!$E$5) | G9: =IF(F9="","",F9*'Exchange Rate'!$B$5) | H9: =IF(L9="Inactive",0,IF(ISNUMBER(G9)*ISNUMBER(D9),IF(G9>D9,G9-D9,0),0)) -> 0 | I9: =IF(L9="Inactive",0,IF(ISNUMBER(F9)*ISNUMBER(E9),IF(F9>E9,F9-E9,0),0)) -> 0 | J9: =IF(L9="Inactive",0,IF(ISNUMBER(D9)*ISNUMBER(G9),IF(D9>G9,D9-G9,0),0)) -> 0 | K9: =IF(L9="Inactive",0,IF(ISNUMBER(E9)*ISNUMBER(F9),IF(E9>F9,E9-F9,0),0)) -> 0 | L9: Active | P9: =IFERROR(COUNTIFS('2. Mercari and Online store'!$A$8:$A$107,A9,'2. Mercari and Online store'!$B$8:$B$107,">="&(TODAY()-28))/4,0) -> 0 | Q9: =IFERROR(IF(P9=0,"∞",O9/P9),"—") -> ∞ | R9: =IFERROR(IF(OR(P9=0,O9=""),"N/A",TEXT(TODAY()+(IFERROR(O9/P9,0)*7),"DD-MMM-YYYY")),"—") -> N/A | S9: =IF(A9="","—",A9&" ("&TEXT(B9,"MM/DD/YYYY")&")") -> —
C10: =IF(B10="","",TEXT(B10,"mmmm")) | E10: =IF(D10="","",D10*'Exchange Rate'!$E$5) | G10: =IF(F10="","",F10*'Exchange Rate'!$B$5) | H10: =IF(L10="Inactive",0,IF(ISNUMBER(G10)*ISNUMBER(D10),IF(G10>D10,G10-D10,0),0)) -> 0 | I10: =IF(L10="Inactive",0,IF(ISNUMBER(F10)*ISNUMBER(E10),IF(F10>E10,F10-E10,0),0)) -> 0 | J10: =IF(L10="Inactive",0,IF(ISNUMBER(D10)*ISNUMBER(G10),IF(D10>G10,D10-G10,0),0)) -> 0 | K10: =IF(L10="Inactive",0,IF(ISNUMBER(E10)*ISNUMBER(F10),IF(E10>F10,E10-F10,0),0)) -> 0 | L10: Active | P10: =IFERROR(COUNTIFS('2. Mercari and Online store'!$A$8:$A$107,A10,'2. Mercari and Online store'!$B$8:$B$107,">="&(TODAY()-28))/4,0) -> 0 | Q10: =IFERROR(IF(P10=0,"∞",O10/P10),"—") -> ∞ | R10: =IFERROR(IF(OR(P10=0,O10=""),"N/A",TEXT(TODAY()+(IFERROR(O10/P10,0)*7),"DD-MMM-YYYY")),"—") -> N/A | S10: =IF(A10="","—",A10&" ("&TEXT(B10,"MM/DD/YYYY")&")") -> —
C11: =IF(B11="","",TEXT(B11,"mmmm")) | E11: =IF(D11="","",D11*'Exchange Rate'!$E$5) | G11: =IF(F11="","",F11*'Exchange Rate'!$B$5) | H11: =IF(L11="Inactive",0,IF(ISNUMBER(G11)*ISNUMBER(D11),IF(G11>D11,G11-D11,0),0)) -> 0 | I11: =IF(L11="Inactive",0,IF(ISNUMBER(F11)*ISNUMBER(E11),IF(F11>E11,F11-E11,0),0)) -> 0 | J11: =IF(L11="Inactive",0,IF(ISNUMBER(D11)*ISNUMBER(G11),IF(D11>G11,D11-G11,0),0)) -> 0 | K11: =IF(L11="Inactive",0,IF(ISNUMBER(E11)*ISNUMBER(F11),IF(E11>F11,E11-F11,0),0)) -> 0 | L11: Active | P11: =IFERROR(COUNTIFS('2. Mercari and Online store'!$A$8:$A$107,A11,'2. Mercari and Online store'!$B$8:$B$107,">="&(TODAY()-28))/4,0) -> 0 | Q11: =IFERROR(IF(P11=0,"∞",O11/P11),"—") -> ∞ | R11: =IFERROR(IF(OR(P11=0,O11=""),"N/A",TEXT(TODAY()+(IFERROR(O11/P11,0)*7),"DD-MMM-YYYY")),"—") -> N/A | S11: =IF(A11="","—",A11&" ("&TEXT(B11,"MM/DD/YYYY")&")") -> —
C12: =IF(B12="","",TEXT(B12,"mmmm")) | E12: =IF(D12="","",D12*'Exchange Rate'!$E$5) | G12: =IF(F12="","",F12*'Exchange Rate'!$B$5) | H12: =IF(L12="Inactive",0,IF(ISNUMBER(G12)*ISNUMBER(D12),IF(G12>D12,G12-D12,0),0)) -> 0 | I12: =IF(L12="Inactive",0,IF(ISNUMBER(F12)*ISNUMBER(E12),IF(F12>E12,F12-E12,0),0)) -> 0 | J12: =IF(L12="Inactive",0,IF(ISNUMBER(D12)*ISNUMBER(G12),IF(D12>G12,D12-G12,0),0)) -> 0 | K12: =IF(L12="Inactive",0,IF(ISNUMBER(E12)*ISNUMBER(F12),IF(E12>F12,E12-F12,0),0)) -> 0 | L12: Active | P12: =IFERROR(COUNTIFS('2. Mercari and Online store'!$A$8:$A$107,A12,'2. Mercari and Online store'!$B$8:$B$107,">="&(TODAY()-28))/4,0) -> 0 | Q12: =IFERROR(IF(P12=0,"∞",O12/P12),"—") -> ∞ | R12: =IFERROR(IF(OR(P12=0,O12=""),"N/A",TEXT(TODAY()+(IFERROR(O12/P12,0)*7),"DD-MMM-YYYY")),"—") -> N/A | S12: =IF(A12="","—",A12&" ("&TEXT(B12,"MM/DD/YYYY")&")") -> —
C13: =IF(B13="","",TEXT(B13,"mmmm")) | E13: =IF(D13="","",D13*'Exchange Rate'!$E$5) | G13: =IF(F13="","",F13*'Exchange Rate'!$B$5) | H13: =IF(L13="Inactive",0,IF(ISNUMBER(G13)*ISNUMBER(D13),IF(G13>D13,G13-D13,0),0)) -> 0 | I13: =IF(L13="Inactive",0,IF(ISNUMBER(F13)*ISNUMBER(E13),IF(F13>E13,F13-E13,0),0)) -> 0 | J13: =IF(L13="Inactive",0,IF(ISNUMBER(D13)*ISNUMBER(G13),IF(D13>G13,D13-G13,0),0)) -> 0 | K13: =IF(L13="Inactive",0,IF(ISNUMBER(E13)*ISNUMBER(F13),IF(E13>F13,E13-F13,0),0)) -> 0 | L13: Active | P13: =IFERROR(COUNTIFS('2. Mercari and Online store'!$A$8:$A$107,A13,'2. Mercari and Online store'!$B$8:$B$107,">="&(TODAY()-28))/4,0) -> 0 | Q13: =IFERROR(IF(P13=0,"∞",O13/P13),"—") -> ∞ | R13: =IFERROR(IF(OR(P13=0,O13=""),"N/A",TEXT(TODAY()+(IFERROR(O13/P13,0)*7),"DD-MMM-YYYY")),"—") -> N/A | S13: =IF(A13="","—",A13&" ("&TEXT(B13,"MM/DD/YYYY")&")") -> —
C14: =IF(B14="","",TEXT(B14,"mmmm")) | E14: =IF(D14="","",D14*'Exchange Rate'!$E$5) | G14: =IF(F14="","",F14*'Exchange Rate'!$B$5) | H14: =IF(L14="Inactive",0,IF(ISNUMBER(G14)*ISNUMBER(D14),IF(G14>D14,G14-D14,0),0)) -> 0 | I14: =IF(L14="Inactive",0,IF(ISNUMBER(F14)*ISNUMBER(E14),IF(F14>E14,F14-E14,0),0)) -> 0 | J14: =IF(L14="Inactive",0,IF(ISNUMBER(D14)*ISNUMBER(G14),IF(D14>G14,D14-G14,0),0)) -> 0 | K14: =IF(L14="Inactive",0,IF(ISNUMBER(E14)*ISNUMBER(F14),IF(E14>F14,E14-F14,0),0)) -> 0 | L14: Active | P14: =IFERROR(COUNTIFS('2. Mercari and Online store'!$A$8:$A$107,A14,'2. Mercari and Online store'!$B$8:$B$107,">="&(TODAY()-28))/4,0) -> 0 | Q14: =IFERROR(IF(P14=0,"∞",O14/P14),"—") -> ∞ | R14: =IFERROR(IF(OR(P14=0,O14=""),"N/A",TEXT(TODAY()+(IFERROR(O14/P14,0)*7),"DD-MMM-YYYY")),"—") -> N/A | S14: =IF(A14="","—",A14&" ("&TEXT(B14,"MM/DD/YYYY")&")") -> —
C15: =IF(B15="","",TEXT(B15,"mmmm")) | E15: =IF(D15="","",D15*'Exchange Rate'!$E$5) | G15: =IF(F15="","",F15*'Exchange Rate'!$B$5) | H15: =IF(L15="Inactive",0,IF(ISNUMBER(G15)*ISNUMBER(D15),IF(G15>D15,G15-D15,0),0)) -> 0 | I15: =IF(L15="Inactive",0,IF(ISNUMBER(F15)*ISNUMBER(E15),IF(F15>E15,F15-E15,0),0)) -> 0 | J15: =IF(L15="Inactive",0,IF(ISNUMBER(D15)*ISNUMBER(G15),IF(D15>G15,D15-G15,0),0)) -> 0 | K15: =IF(L15="Inactive",0,IF(ISNUMBER(E15)*ISNUMBER(F15),IF(E15>F15,E15-F15,0),0)) -> 0 | L15: Active | P15: =IFERROR(COUNTIFS('2. Mercari and Online store'!$A$8:$A$107,A15,'2. Mercari and Online store'!$B$8:$B$107,">="&(TODAY()-28))/4,0) -> 0 | Q15: =IFERROR(IF(P15=0,"∞",O15/P15),"—") -> ∞ | R15: =IFERROR(IF(OR(P15=0,O15=""),"N/A",TEXT(TODAY()+(IFERROR(O15/P15,0)*7),"DD-MMM-YYYY")),"—") -> N/A | S15: =IF(A15="","—",A15&" ("&TEXT(B15,"MM/DD/YYYY")&")") -> —
C16: =IF(B16="","",TEXT(B16,"mmmm")) | E16: =IF(D16="","",D16*'Exchange Rate'!$E$5) | G16: =IF(F16="","",F16*'Exchange Rate'!$B$5) | H16: =IF(L16="Inactive",0,IF(ISNUMBER(G16)*ISNUMBER(D16),IF(G16>D16,G16-D16,0),0)) -> 0 | I16: =IF(L16="Inactive",0,IF(ISNUMBER(F16)*ISNUMBER(E16),IF(F16>E16,F16-E16,0),0)) -> 0 | J16: =IF(L16="Inactive",0,IF(ISNUMBER(D16)*ISNUMBER(G16),IF(D16>G16,D16-G16,0),0)) -> 0 | K16: =IF(L16="Inactive",0,IF(ISNUMBER(E16)*ISNUMBER(F16),IF(E16>F16,E16-F16,0),0)) -> 0 | L16: Active | P16: =IFERROR(COUNTIFS('2. Mercari and Online store'!$A$8:$A$107,A16,'2. Mercari and Online store'!$B$8:$B$107,">="&(TODAY()-28))/4,0) -> 0 | Q16: =IFERROR(IF(P16=0,"∞",O16/P16),"—") -> ∞ | R16: =IFERROR(IF(OR(P16=0,O16=""),"N/A",TEXT(TODAY()+(IFERROR(O16/P16,0)*7),"DD-MMM-YYYY")),"—") -> N/A | S16: =IF(A16="","—",A16&" ("&TEXT(B16,"MM/DD/YYYY")&")") -> —
C17: =IF(B17="","",TEXT(B17,"mmmm")) | E17: =IF(D17="","",D17*'Exchange Rate'!$E$5) | G17: =IF(F17="","",F17*'Exchange Rate'!$B$5) | H17: =IF(L17="Inactive",0,IF(ISNUMBER(G17)*ISNUMBER(D17),IF(G17>D17,G17-D17,0),0)) -> 0 | I17: =IF(L17="Inactive",0,IF(ISNUMBER(F17)*ISNUMBER(E17),IF(F17>E17,F17-E17,0),0)) -> 0 | J17: =IF(L17="Inactive",0,IF(ISNUMBER(D17)*ISNUMBER(G17),IF(D17>G17,D17-G17,0),0)) -> 0 | K17: =IF(L17="Inactive",0,IF(ISNUMBER(E17)*ISNUMBER(F17),IF(E17>F17,E17-F17,0),0)) -> 0 | L17: Active | P17: =IFERROR(COUNTIFS('2. Mercari and Online store'!$A$8:$A$107,A17,'2. Mercari and Online store'!$B$8:$B$107,">="&(TODAY()-28))/4,0) -> 0 | Q17: =IFERROR(IF(P17=0,"∞",O17/P17),"—") -> ∞ | R17: =IFERROR(IF(OR(P17=0,O17=""),"N/A",TEXT(TODAY()+(IFERROR(O17/P17,0)*7),"DD-MMM-YYYY")),"—") -> N/A | S17: =IF(A17="","—",A17&" ("&TEXT(B17,"MM/DD/YYYY")&")") -> —
C18: =IF(B18="","",TEXT(B18,"mmmm")) | E18: =IF(D18="","",D18*'Exchange Rate'!$E$5) | G18: =IF(F18="","",F18*'Exchange Rate'!$B$5) | H18: =IF(L18="Inactive",0,IF(ISNUMBER(G18)*ISNUMBER(D18),IF(G18>D18,G18-D18,0),0)) -> 0 | I18: =IF(L18="Inactive",0,IF(ISNUMBER(F18)*ISNUMBER(E18),IF(F18>E18,F18-E18,0),0)) -> 0 | J18: =IF(L18="Inactive",0,IF(ISNUMBER(D18)*ISNUMBER(G18),IF(D18>G18,D18-G18,0),0)) -> 0 | K18: =IF(L18="Inactive",0,IF(ISNUMBER(E18)*ISNUMBER(F18),IF(E18>F18,E18-F18,0),0)) -> 0 | L18: Active | P18: =IFERROR(COUNTIFS('2. Mercari and Online store'!$A$8:$A$107,A18,'2. Mercari and Online store'!$B$8:$B$107,">="&(TODAY()-28))/4,0) -> 0 | Q18: =IFERROR(IF(P18=0,"∞",O18/P18),"—") -> ∞ | R18: =IFERROR(IF(OR(P18=0,O18=""),"N/A",TEXT(TODAY()+(IFERROR(O18/P18,0)*7),"DD-MMM-YYYY")),"—") -> N/A | S18: =IF(A18="","—",A18&" ("&TEXT(B18,"MM/DD/YYYY")&")") -> —
C19: =IF(B19="","",TEXT(B19,"mmmm")) | E19: =IF(D19="","",D19*'Exchange Rate'!$E$5) | G19: =IF(F19="","",F19*'Exchange Rate'!$B$5) | H19: =IF(L19="Inactive",0,IF(ISNUMBER(G19)*ISNUMBER(D19),IF(G19>D19,G19-D19,0),0)) -> 0 | I19: =IF(L19="Inactive",0,IF(ISNUMBER(F19)*ISNUMBER(E19),IF(F19>E19,F19-E19,0),0)) -> 0 | J19: =IF(L19="Inactive",0,IF(ISNUMBER(D19)*ISNUMBER(G19),IF(D19>G19,D19-G19,0),0)) -> 0 | K19: =IF(L19="Inactive",0,IF(ISNUMBER(E19)*ISNUMBER(F19),IF(E19>F19,E19-F19,0),0)) -> 0 | L19: Active | P19: =IFERROR(COUNTIFS('2. Mercari and Online store'!$A$8:$A$107,A19,'2. Mercari and Online store'!$B$8:$B$107,">="&(TODAY()-28))/4,0) -> 0 | Q19: =IFERROR(IF(P19=0,"∞",O19/P19),"—") -> ∞ | R19: =IFERROR(IF(OR(P19=0,O19=""),"N/A",TEXT(TODAY()+(IFERROR(O19/P19,0)*7),"DD-MMM-YYYY")),"—") -> N/A | S19: =IF(A19="","—",A19&" ("&TEXT(B19,"MM/DD/YYYY")&")") -> —
... C107: =IF(B107="","",TEXT(B107,"mmmm")) | E107: =IF(D107="","",D107*'Exchange Rate'!$E$5) | G107: =IF(F107="","",F107*'Exchange Rate'!$B$5) | H107: =IF(L107="Inactive",0,IF(ISNUMBER(G107)*ISNUMBER(D107),IF(G107>D107,G107-D107,0),0)) -> 0 | I107: =IF(L107="Inactive",0,IF(ISNUMBER(F107)*ISNUMBER(E107),IF(F107>E107,F107-E107,0),0)) -> 0 | J107: =IF(L107="Inactive",0,IF(ISNUMBER(D107)*ISNUMBER(G107),IF(D107>G107,D107-G107,0),0)) -> 0 | K107: =IF(L107="Inactive",0,IF(ISNUMBER(E107)*ISNUMBER(F107),IF(E107>F107,E107-F107,0),0)) -> 0 | L107: Active | P107: =IFERROR(COUNTIFS('2. Mercari and Online store'!$A$8:$A$107,A107,'2. Mercari and Online store'!$B$8:$B$107,">="&(TODAY()-28))/4,0) -> 0 | Q107: =IFERROR(IF(P107=0,"∞",O107/P107),"—") -> ∞ | R107: =IFERROR(IF(OR(P107=0,O107=""),"N/A",TEXT(TODAY()+(IFERROR(O107/P107,0)*7),"DD-MMM-YYYY")),"—") -> N/A | S107: =IF(A107="","—",A107&" ("&TEXT(B107,"MM/DD/YYYY")&")") -> —
A108: TOTAL CATEGORY VALUE | D108: =SUM(D8:D107) -> 0 | E108: =SUM(E8:E107) -> 0 | F108: =SUM(F8:F107) -> 0 | G108: =SUM(G8:G107) -> 0 | H108: =SUM(H8:H107) -> 0 | I108: =SUM(I8:I107) -> 0 | J108: =SUM(J8:J107) -> 0 | K108: =SUM(K8:K107) -> 0 | ... R108: =SUM(R8:R107) -> 0
A110: 📋 USER GUIDE & OPERATIONAL INSTRUCTIONS
A111: Step 1 — DATA ENTRY
A112: Input rows sequentially. Type directly into Col D (Purchase JPY) and Col F (Selling PHP) ONLY. All other columns auto-calculate. Yellow cells = manual entry. White cells = formulas.
A113: Step 2 — DUPLICATE IDs
A114: If tracking duplicate items, check the QUICK-VIEW bar (Row 5). A ⚠️ alert fires when the same Product ID appears more than once. Use the 'Date of Entry' (Col B) timestamp in the lookup to immediately distinguish which entry is which.
A115: Step 3 — ANALYTICS FILTER
A116: Toggle the Analytics view on the '9. Overall Analytics' sheet using the timeframe filter (D2) to review Weekly, Monthly, or Annual financial health variations.
A117: Step 4 — EXCHANGE RATES
A118: Never manually edit currency columns. To update rates, go to the 'Exchange Rate' sheet and edit ONLY cells B5 (PHP→JPY) or E5 (JPY→PHP). All values across the workbook update instantly.
A119: Step 5 — STOCK STATUS
A120: Use Column L dropdown (Active/Inactive) to toggle items. Inactive rows contribute ZERO to profit, loss, and analytics totals — ideal for recalled, damaged, or discontinued stock.
A121: Step 6 — RESTOCK RUNWAY (Cols O–R)
